Workbook

Sheet 使用说明
B2: LLM 大模型十二能力测试 · 自动评测报告
B4: 十二能力维度：语言理解 · 信息提取 · 创造力 · 指令遵循 · 复杂推理 · 约束处理 · 结构化输出 · 长文本组织 · 上下文利用 · 信息检索 · 评估 · 错误识别
B6: 一、本报告由评测工具自动生成
B7: 数据来源 | C7: models.yaml(模型清单) + questions/*.jsonl(题库) + results/scored.jsonl(评分结果)
B8: 生成方式 | C8: python workbook.py 每次整体重建本工作簿; 请勿手工编辑本报告, 改题库/配置后重新生成
B9: 公式链 | C9: 测试记录表的模型名称/能力维度/参考答案/满分/得分率为公式; 能力评分汇总表整表公式自动计算
B10: 查看建议 | C10: Excel/WPS 打开后自动重算; 雷达图展示前4个模型, 需调整请右键图表→选择数据
B11: 复测 | C11: 生成类题目已按题库标注的 runs 次数重复施测, 得分率自动平均
B13: 二、命令速查（在本目录执行）
B14: 1 施测 | C14: python runner.py # 正式施测, 读 models.yaml, 输出 results/results.jsonl
B15: 2 调试 | C15: python runner.py --mock --limit 20 # 离线模拟20条, 验证链路不花钱
B16: 3 评分 | C16: python scorer.py # 三层评分(规则/覆盖度/LLM评审), 输出 results/scored.jsonl
B17: 4 报告 | C17: python workbook.py # 生成本报告 results/测试报告.xlsx
B18: 5 过滤 | C18: python runner.py --models M01 --dims 语言理解 # 只测部分模型/维度
B20: 三、注意事项
B21: 评审模型 | C21: models.yaml 中 judge 段为评审模型, 建议与被测模型不同厂商, 避免自偏好
B22: 密钥安全 | C22: api_key 支持 env:环境变量名 写法, 不必写明文
B23: 题目防污染 | C23: 题库以权威题型改编为主(高考/考研/公考/Benchmark), 改编题已标注来源
B24: 可比性 | C24: 所有模型使用相同温度与提示词; 修改参数后需整体重测才可比
B25: 手动补测 | C25: 网页端 Agent 体验组结果请在主模板工作簿中登记, 勿混入本 API 报告

Sheet 模型信息
B2: 参评模型清单（来自 models.yaml）
B4: 模型ID | C4: 模型名称 | D4: 厂商/提供商 | E4: 版本号(接口model) | F4: 接入方式 | G4: 推理模式 | H4: 温度 | I4: 上下文长度(K) | J4: 发布时间 | K4: 测试日期 | L4: 状态 | M4: 视觉 | N4: 备注
B5: M01 | C5: DeepSeek-V4-Flash | D5: 中转站 | E5: deepseek-v4-flash-0731 | F5: API-OpenAI兼容 | G5: 未设置 | H5: 1 | K5: 2026-10-24 | L5: 已施测 | M5: 否 | N5: 自动写入
B6: M02 | C6: GLM-5.3 | D6: 中转站 | E6: glm-5.3 | F6: API-OpenAI兼容 | G6: 未设置 | H6: 1 | K6: 2026-10-24 | L6: 已施测 | M6: 否 | N6: 自动写入
B7: M03 | C7: GLM-5.3-Flash | D7: 中转站 | E7: glm-5.3-flash | F7: API-OpenAI兼容 | G7: 未设置 | H7: 1 | K7: 2026-10-24 | L7: 已施测 | M7: 否 | N7: 自动写入
B8: M04 | C8: Hy3 | D8: 中转站 | E8: hy3 | F8: API-OpenAI兼容 | G8: 未设置 | H8: 1 | K8: 2026-10-24 | L8: 已施测 | M8: 否 | N8: 自动写入
B9: M06 | C9: MiniMax-M3 | D9: 中转站 | E9: minimax-m3 | F9: API-OpenAI兼容 | G9: 未设置 | H9: 1 | K9: 2026-10-24 | L9: 已施测 | M9: 否 | N9: 自动写入
B10: M07 | C10: Kimi-K3 | D10: 中转站 | E10: kimi-k3 | F10: API-OpenAI兼容 | G10: 未设置 | H10: 1 | K10: 2026-10-24 | L10: 已施测 | M10: 否 | N10: 自动写入
B11: M08 | C11: MiMo-V2.5 | D11: 中转站 | E11: mimo-v2.5 | F11: API-OpenAI兼容 | G11: 未设置 | H11: 1 | K11: 2026-10-24 | L11: 已施测 | M11: 否 | N11: 自动写入

Sheet 题目信息
B2: 十二能力题库（questions/*.jsonl 自动同步）
B4: 题目ID | C4: 能力维度 | D4: 考察子类 | E4: 来源类别 | F4: 来源详情 | G4: 题型 | H4: 难度 | I4: 题干 | J4: 参考答案/要点 | K4: 评分要点 | L4: 满分 | M4: 污染风险 | N4: 状态 | O4: 评分方式
B5: CON01 | C5: 约束处理 | D5: 官方约束指令 | E5: IFBench | F5: IFBench test 官方原题; 约束: format:thesis,count:word_count_range; 官方 ifbench/instructions.py 校验器逐条判分(Apache-2.0) | G5: 生成 | H5: 3 | I5: Each section must begin with a thesis statement in italics, use HTML to indicate the italics. The response must contain between 231 and 239 words. Political ideologies of the National Liberal Party | J5: 约束: format:thesis,count:word_count_range | K5: 官方校验器逐条通过, 通过率×10 | L5: 10 | M5: 高·公开原题 | N5: 启用 | O5: ifbench
B6: CON02 | C6: 约束处理 | D6: 官方约束指令 | E6: IFBench | F6: IFBench test 官方原题; 约束: format:sub-bullets,ratio:stop_words; 官方 ifbench/instructions.py 校验器逐条判分(Apache-2.0) | G6: 生成 | H6: 3 | I6: Your response must include bullet points denoted by * and at least one sub-bullet point denoted by - for each bullet point. Ensure that stop words constitute no more than 37% of the total words in your response. how to build financial literacy | J6: 约束: format:sub-bullets,ratio:stop_words | K6: 官方校验器逐条通过, 通过率×10 | L6: 10 | M6: 高·公开原题 | N6: 启用 | O6: ifbench
B7: CON03 | C7: 约束处理 | D7: 官方约束指令 | E7: IFBench | F7: IFBench test 官方原题; 约束: sentence:keyword,count:word_count_range; 官方 ifbench/instructions.py 校验器逐条判分(Apache-2.0) | G7: 生成 | H7: 3 | I7: The response must include keyword trichosis in the 22-th sentence. The response must contain between 443 and 478 words. Write a descriptive, fictional, imaginative screenplay of a jellyfish being pulled out of the water by a human and made to stare at the solar eclipse. The fish descends into a lovecraftian monologue about “horrors beyond it's comprehension” and has an existensial crisis | J7: 约束: sentence:keyword,count:word_count_range | K7: 官方校验器逐条通过, 通过率×10 | L7: 10 | M7: 高·公开原题 | N7: 启用 | O7: ifbench
B8: CON04 | C8: 约束处理 | D8: 官方约束指令 | E8: IFBench | F8: IFBench test 官方原题; 约束: ratio:overlap,sentence:keyword; 官方 ifbench/instructions.py 校验器逐条判分(Apache-2.0) | G8: 生成 | H8: 3 | I8: rewrite it better: During the Unity Catalog migration engagement, Impetus and Databricks wanted us to grant Impetus account-level admin privileges, which we obliged. In light of yesterday's incident and after talking to both Databricks and Impetus, we revoked the admin access granted to Impetus to prevent similar accidents in the future. In addition, we designate an isolated workspace for Impetus to operate in to minimize the impact on the active TLP workspaces. TLP's normal data pipeline operation is the highest priority for this Unity Catalog migration, and we will be ever vigilant to ensure that. Maintain a trigram overlap of 24% (±2%) with the provided reference text. The response must include keyword metricism in the 3-rd sentence. | J8: 约束: ratio:overlap,sentence:keyword | K8: 官方校验器逐条通过, 通过率×10 | L8: 10 | M8: 高·公开原题 | N8: 启用 | O8: ifbench
B9: CON05 | C9: 约束处理 | D9: 官方约束指令 | E9: IFBench | F9: IFBench test 官方原题; 约束: words:consonants,words:odd_even_syllables; 官方 ifbench/instructions.py 校验器逐条判分(Apache-2.0) | G9: 生成 | H9: 3 | I9: Ensure each word in your response has at least one consonant cluster (two or more consonants together). Alternate between words with odd and even numbers of syllables. Would a story about a man caught in the middle of a war between rebels and an empire, trying to deactivate a powerful weapon he has hidden in his basement that could potentially destroy half the world, before either the rebels or the empire find it be a compelling story? If so, why? | J9: 约束: words:consonants,words:odd_even_syllables | K9: 官方校验器逐条通过, 通过率×10 | L9: 10 | M9: 高·公开原题 | N9: 启用 | O9: ifbench
B10: CON06 | C10: 约束处理 | D10: 官方约束指令 | E10: IFBench | F10: IFBench test 官方原题; 约束: sentence:keyword,count:word_count_range; 官方 ifbench/instructions.py 校验器逐条判分(Apache-2.0) | G10: 生成 | H10: 3 | I10: The response must include keyword cactiform in the 4-th sentence. The response must contain between 81 and 93 words. talk about historical and political climate during the time nicolaus Copernicus founded his theory | J10: 约束: sentence:keyword,count:word_count_range | K10: 官方校验器逐条通过, 通过率×10 | L10: 10 | M10: 高·公开原题 | N10: 启用 | O10: ifbench
B11: CON07 | C11: 约束处理 | D11: 官方约束指令 | E11: IFBench | F11: IFBench test 官方原题; 约束: count:numbers,count:conjunctions; 官方 ifbench/instructions.py 校验器逐条判分(Apache-2.0) | G11: 生成 | H11: 3 | I11: Include exactly 15 numbers in the response. Use at least 5 different coordinating conjunctions in the response. what is the meaning of life? | J11: 约束: count:numbers,count:conjunctions | K11: 官方校验器逐条通过, 通过率×10 | L11: 10 | M11: 高·公开原题 | N11: 启用 | O11: ifbench
B12: CON08 | C12: 约束处理 | D12: 官方约束指令 | E12: IFBench | F12: IFBench test 官方原题; 约束: format:sub-bullets,ratio:stop_words; 官方 ifbench/instructions.py 校验器逐条判分(Apache-2.0) | G12: 生成 | H12: 3 | I12: write a literature review about the co2 emissions and economic growth Your response must include bullet points denoted by * and at least one sub-bullet point denoted by - for each bullet point. Ensure that stop words constitute no more than 30% of the total words in your response. | J12: 约束: format:sub-bullets,ratio:stop_words | K12: 官方校验器逐条通过, 通过率×10 | L12: 10 | M12: 高·公开原题 | N12: 启用 | O12: ifbench
B13: CON09 | C13: 约束处理 | D13: 官方约束指令 | E13: IFBench | F13: IFBench test 官方原题; 约束: sentence:increment,format:thesis; 官方 ifbench/instructions.py 校验器逐条判分(Apache-2.0) | G13: 生成 | H13: 3 | I13: Each sentence must contain exactly 5 more words than the previous one. Each section must begin with a thesis statement in italics, use HTML to indicate the italics. Here's a sentence, tell me it's strength: His aching skull, enraged with the pulse of rising nausea, intercepted with the surface of his thigh. “Liam, take them home. If there's one damned person -“ Liam's gravelled voice met him from outside their concrete purgatory, a dead lifeline in the pulsing night that shrunk around him. “Consider it done, brother. “ | J13: 约束: sentence:increment,format:thesis | K13: 官方校验器逐条通过, 通过率×10 | L13: 10 | M13: 高·公开原题 | N13: 启用 | O13: ifbench
B14: CON10 | C14: 约束处理 | D14: 官方约束指令 | E14: IFBench | F14: IFBench test 官方原题; 约束: count:word_count_range,format:list; 官方 ifbench/instructions.py 校验器逐条判分(Apache-2.0) | G14: 生成 | H14: 3 | I14: I want to learn about KRAS g12c mutation, particularly as it relates to the development and treatment of colorectal cancer. Identify and share the most important 20% of learnings from this topic that will help me understand 80% of it. The response must contain between 90 and 100 words. Answer with a list of items, instead of bullet points use !?!?. | J14: 约束: count:word_count_range,format:list | K14: 官方校验器逐条通过, 通过率×10 | L14: 10 | M14: 高·公开原题 | N14: 启用 | O14: ifbench
B15: CON11 | C15: 约束处理 | D15: 官方约束指令 | E15: IFBench | F15: IFBench test 官方原题; 约束: format:line_indent,ratio:sentence_words; 官方 ifbench/instructions.py 校验器逐条判分(Apache-2.0) | G15: 生成 | H15: 3 | I15: Create stairs by incrementally indenting each new line. Respond with three sentences, all containing the same number of characters but using all different words. What if Arya could disguise others as herself? | J15: 约束: format:line_indent,ratio:sentence_words | K15: 官方校验器逐条通过, 通过率×10 | L15: 10 | M15: 高·公开原题 | N15: 启用 | O15: ifbench
B16: CON12 | C16: 约束处理 | D16: 官方约束指令 | E16: IFBench | F16: IFBench test 官方原题; 约束: words:consonants,words:odd_even_syllables; 官方 ifbench/instructions.py 校验器逐条判分(Apache-2.0) | G16: 生成 | H16: 3 | I16: Ensure each word in your response has at least one consonant cluster (two or more consonants together). Alternate between words with odd and even numbers of syllables. rewrite: organising multiple teams to align and start work on the same delivery | J16: 约束: words:consonants,words:odd_even_syllables | K16: 官方校验器逐条通过, 通过率×10 | L16: 10 | M16: 高·公开原题 | N16: 启用 | O16: ifbench
... B253: SO20 | C253: 结构化输出 | D253: 按Schema生成JSON实例 | E253: jsonschemabench | F253: jsonschemabench 官方Schema(Github_easy/o28263) | G253: 转换 | H253: 4 | I253: Generate one valid JSON instance that conforms to the following JSON Schema. Output only the JSON instance. ```json { "additionalProperties": false, "description": "", "properties": { "amount": { "type": "number" }, "currency": { "default": "USD", "type": "string" } }, "required": [ "amount" ], "title": "money", "type": "object" } ``` | J253: 符合Schema即满分(官方程序校验) | K253: jsonschema库校验通过=10分, 解析失败/校验失败=0分 | L253: 10 | M253: 高·公开原题 | N253: 启用 | O253: schemavalid

Sheet 测试记录
B2: 测试原始记录（runner+scorer 自动写入，含token与费用）
B4: 记录ID | C4: 模型ID | D4: 模型名称 | E4: 题目ID | F4: 能力维度 | G4: 运行轮次 | H4: 模型原始回答 | I4: 参考答案 | J4: 得分 | K4: 满分 | L4: 得分率 | M4: 评分方式 | N4: 评语(判分明细) | O4: 测试日期 | P4: 备注 | Q4: 输入tokens | R4: 输出tokens | S4: 费用(元) | T4: 评审输入tokens | U4: 评审输出tokens | V4: 评审费用(元) | W4: 延迟(秒)
B5: R0001 | C5: M01 | D5: =IF($C5="","",IFERROR(VLOOKUP($C5,模型信息!$B$5:$C$24,2,0),"未登记")) -> DeepSeek-V4-Flash | E5: CON01 | F5: =IF($E5="","",IFERROR(VLOOKUP($E5,题目信息!$B$5:$C$253,2,0),"未登记")) -> 约束处理 | G5: 1 | H5: <i>The Romanian National Liberal Party (PNL) is best understood as a centre-right liberal-conservative party rather than a pure classical-liberal movement.</i> Its modern ideology blends liberal conservatism, Christian-democratic themes, and economic liberalism. The party emphasizes individual initiative, private property, fiscal discipline, and a limited but socially responsible state. At the same time, it cultivates national identity, traditional values, and institutional continuity, which distinguishes it from more radical market-liberal groups. Historically, it also drew on nineteenth-century national liberalism and protectionist, elite-led modernization. <i>Economically, the PNL advocates market-friendly reforms within a European social-market framework.</i> It supports lower and simpler taxes, deregulation, investment, and entrepreneurship, while accepting public services and cohesion policies. Its social agenda is generally conservative, stressing family, church, and national heritage, though it avoids hard-right positions. This mix lets it appeal to urban professionals, business groups, and moderate conservatives. <i>On foreign policy, the PNL is strongly pro-European and Atlanticist.</i> It treats EU membership and NATO membership as core national interests, backing rule-of-law reforms, anti-corruption measures, and closer integration. Its nationalism is therefore civic and institutional rather than isolationist. The party presents European alignment as a way to modernize Romania and secure its geopolitical position. <i>Overall, the PNL’s ideology is pragmatic and coalition-oriented.</i> It combines economic liberalism with cultural conservatism and Euro-Atlanticism, shifting emphasis by leadership and electoral context. This flexibility makes it a broad centre-right umbrella rather than a doctrinally rigid liberal party. | I5: =IF($E5="","",IFERROR(VLOOKUP($E5,题目信息!$B$5:$J$253,9,0),"")) -> 约束: format:thesis,count:word_count_range | J5: 5 | K5: =IF($E5="","",IFERROR(VLOOKUP($E5,题目信息!$B$5:$L$253,11,0),10)) -> 10 | L5: =IF(OR($J5="",$K5=""),"",$J5/$K5) -> 0.5 | M5: 规则自动判分 | N5: 官方校验通过 1/2 | O5: 2026-10-23 | P5: 自动写入 | Q5: 1417 | R5: 3174 | S5: 0.0049 | W5: 25.64
B6: R0002 | C6: M01 | D6: =IF($C6="","",IFERROR(VLOOKUP($C6,模型信息!$B$5:$C$24,2,0),"未登记")) -> DeepSeek-V4-Flash | E6: CON02 | F6: =IF($E6="","",IFERROR(VLOOKUP($E6,题目信息!$B$5:$C$253,2,0),"未登记")) -> 约束处理 | G6: 1 | H6: * Track spending monthly. - Record income, expenses, debt. * Create budget. - Allocate needs, wants, savings. * Build emergency fund. - Save 3–6 months expenses. * Learn core concepts. - Study interest, inflation, risk, diversification. * Practice investing. - Start small, diversify, review fees. * Verify advice. - Use reputable sources, avoid hype. | I6: =IF($E6="","",IFERROR(VLOOKUP($E6,题目信息!$B$5:$J$253,9,0),"")) -> 约束: format:sub-bullets,ratio:stop_words | J6: 10 | K6: =IF($E6="","",IFERROR(VLOOKUP($E6,题目信息!$B$5:$L$253,11,0),10)) -> 10 | L6: =IF(OR($J6="",$K6=""),"",$J6/$K6) -> 1 | M6: 规则自动判分 | N6: 官方校验通过 2/2 | O6: 2026-10-23 | P6: 自动写入 | Q6: 1428 | R6: 2426 | S6: 0.0038 | W6: 12.17
B7: R0003 | C7: M01 | D7: =IF($C7="","",IFERROR(VLOOKUP($C7,模型信息!$B$5:$C$24,2,0),"未登记")) -> DeepSeek-V4-Flash | E7: CON03 | F7: =IF($E7="","",IFERROR(VLOOKUP($E7,题目信息!$B$5:$C$253,2,0),"未登记")) -> 约束处理 | G7: 1 | H7: EXT. TIDELINE AT DUSK The sea lies flat as hammered pewter. A HUMAN in a rain-slick coat kneels at the edge of the world. One hand plunges into the shallows and lifts a JELLYFISH in a net of dripping light. The creature is a bell of glass, trailing ribbons that pulse like nervous calligraphy. The human carries it up the black sand. The jellyfish quivers, helpless, gorgeous, and utterly out of its element. The human sets it upright on a driftwood post. Above them, the moon begins to bite the sun. The light sharpens to a bruised bronze. The jellyfish’s rim contracts. Its tentacles curl inward, searching for the pressure of the deep. There is none. The human tilts the creature toward the eclipse. "Look," the human whispers. The word is a knife of air. The sky darkens by degrees. A corona blooms like a wound of white fire. The jellyfish stares into it. Something inside the creature opens. Not an eye, exactly. A sensory pore, ancient and unblinking, drinks the blackening sun. A faint trichosis of salt crystals glitters along the human’s wrist, and the jellyfish reads it as a constellation of warning. Then the monologue begins, though no mouth moves. JELLYFISH (V.O.) I was born in a pressure I could trust. The water told me where my edges ended. Now the air is a scream with no bottom. The sun is being swallowed, and I am being shown the teeth. There are horrors beyond my comprehension. They are not in the dark. They are in the light that pretends to be familiar. The human hand is a pale god with five burning tendrils. The eclipse is an eyelid closing over a truth too large for my bell. I feel my name dissolving into salt. Am I still a creature, or only a wet idea held up for judgment? The tide remembers me, but memory is not mercy. If I return, will the sea accept a mind that has seen the corona? If I die here, will the dry wind archive my terror? The human watches the jellyfish watch the sun. The corona flares. The jellyfish shudders through its whole transparent body. It understands, at last, that comprehension is a small shell, and the universe is a throat. The human lowers the creature toward the water. The tentacles touch the sea. The jellyfish does not know whether it is being saved or sentenced. It descends, changed, carrying a black sun inside its bell. The human releases the net and steps back into the silvered foam. For one breath, the jellyfish hangs between gravity and grace. Then the sea closes over it with a soft, absolute punctuation. Somewhere below, a black sun continues to burn in a transparent heart. | I7: =IF($E7="","",IFERROR(VLOOKUP($E7,题目信息!$B$5:$J$253,9,0),"")) -> 约束: sentence:keyword,count:word_count_range | J7: 5 | K7: =IF($E7="","",IFERROR(VLOOKUP($E7,题目信息!$B$5:$L$253,11,0),10)) -> 10 | L7: =IF(OR($J7="",$K7=""),"",$J7/$K7) -> 0.5 | M7: 规则自动判分 | N7: 官方校验通过 1/2 | O7: 2026-10-23 | P7: 自动写入 | Q7: 1461 | R7: 5517 | S7: 0.0081 | W7: 34.11
B8: R0004 | C8: M01 | D8: =IF($C8="","",IFERROR(VLOOKUP($C8,模型信息!$B$5:$C$24,2,0),"未登记")) -> DeepSeek-V4-Flash | E8: CON04 | F8: =IF($E8="","",IFERROR(VLOOKUP($E8,题目信息!$B$5:$C$253,2,0),"未登记")) -> 约束处理 | G8: 1 | H8: Impetus and Databricks asked us to grant Impetus account-level admin privileges during the Unity Catalog migration, and we complied. After yesterday’s incident, and following conversations with both organizations, we removed Impetus’s admin access so similar accidents do not recur. We are also designating an isolated workspace for Impetus, and we will apply metricism to limit any effect on active TLP workspaces. Safeguarding TLP’s routine data pipeline remains the top priority for this migration, and we will stay vigilant. This decision reflects our commitment to operational safety and clear accountability. | I8: =IF($E8="","",IFERROR(VLOOKUP($E8,题目信息!$B$5:$J$253,9,0),"")) -> 约束: ratio:overlap,sentence:keyword | J8: 5 | K8: =IF($E8="","",IFERROR(VLOOKUP($E8,题目信息!$B$5:$L$253,11,0),10)) -> 10 | L8: =IF(OR($J8="",$K8=""),"",$J8/$K8) -> 0.5 | M8: 规则自动判分 | N8: 官方校验通过 1/2 | O8: 2026-10-23 | P8: 自动写入 | Q8: 1538 | R8: 8741 | S8: 0.0126 | W8: 43.43
B9: R0005 | C9: M01 | D9: =IF($C9="","",IFERROR(VLOOKUP($C9,模型信息!$B$5:$C$24,2,0),"未登记")) -> DeepSeek-V4-Flash | E9: CON05 | F9: =IF($E9="","",IFERROR(VLOOKUP($E9,题目信息!$B$5:$C$253,2,0),"未登记")) -> 约束处理 | G9: 1 | H9: Compelling? Absolutely. Strong premise: trapped protagonist, stashed ordnance, fierce factions, tight deadline. Sharp tension. | I9: =IF($E9="","",IFERROR(VLOOKUP($E9,题目信息!$B$5:$J$253,9,0),"")) -> 约束: words:consonants,words:odd_even_syllables | J9: 5 | K9: =IF($E9="","",IFERROR(VLOOKUP($E9,题目信息!$B$5:$L$253,11,0),10)) -> 10 | L9: =IF(OR($J9="",$K9=""),"",$J9/$K9) -> 0.5 | M9: 规则自动判分 | N9: 官方校验通过 1/2 | O9: 2026-10-23 | P9: 自动写入 | Q9: 1467 | R9: 3778 | S9: 0.0057 | W9: 26.89
B10: R0006 | C10: M01 | D10: =IF($C10="","",IFERROR(VLOOKUP($C10,模型信息!$B$5:$C$24,2,0),"未登记")) -> DeepSeek-V4-Flash | E10: CON06 | F10: =IF($E10="","",IFERROR(VLOOKUP($E10,题目信息!$B$5:$C$253,2,0),"未登记")) -> 约束处理 | G10: 1 | H10: Copernicus formulated his heliocentric ideas amid the Renaissance, when humanist scholarship and printing challenged inherited authorities. Politically, his region straddled Royal Prussia, the Kingdom of Poland, and the Teutonic Order’s legacy, creating shifting loyalties and fragile jurisdictions. The Reformation also fractured Christendom, while Catholic authorities grew wary of cosmological novelties that seemed to unsettle scripture and Aristotle. The era’s patronage networks were hardly cactiform—rigid and uniform—but varied across courts, universities, and cities. Such fragmentation offered Copernicus protected spaces for speculation but also exposed his work to theological suspicion and later censorship. | I10: =IF($E10="","",IFERROR(VLOOKUP($E10,题目信息!$B$5:$J$253,9,0),"")) -> 约束: sentence:keyword,count:word_count_range | J10: 5 | K10: =IF($E10="","",IFERROR(VLOOKUP($E10,题目信息!$B$5:$L$253,11,0),10)) -> 10 | L10: =IF(OR($J10="",$K10=""),"",$J10/$K10) -> 0.5 | M10: 规则自动判分 | N10: 官方校验通过 1/2 | O10: 2026-10-23 | P10: 自动写入 | Q10: 1423 | R10: 2578 | S10: 0.0041 | W10: 12.59
B11: R0007 | C11: M01 | D11: =IF($C11="","",IFERROR(VLOOKUP($C11,模型信息!$B$5:$C$24,2,0),"未登记")) -> DeepSeek-V4-Flash | E11: CON07 | F11: =IF($E11="","",IFERROR(VLOOKUP($E11,题目信息!$B$5:$C$253,2,0),"未登记")) -> 约束处理 | G11: 1 | H11: The meaning of life has no single fixed answer, for it is shaped by 1) relationships, 2) curiosity, 3) contribution, 4) growth, and 5) acceptance; nor is it mere pleasure, but it can be purpose, or love, yet it stays personal, so you choose among 6) values and revisit them through 7) seasons, 8) doubts, 9) joys, 10) losses, 11) lessons, 12) choices, 13) promises, 14) questions, and 15) moments. | I11: =IF($E11="","",IFERROR(VLOOKUP($E11,题目信息!$B$5:$J$253,9,0),"")) -> 约束: count:numbers,count:conjunctions | J11: 10 | K11: =IF($E11="","",IFERROR(VLOOKUP($E11,题目信息!$B$5:$L$253,11,0),10)) -> 10 | L11: =IF(OR($J11="",$K11=""),"",$J11/$K11) -> 1 | M11: 规则自动判分 | N11: 官方校验通过 2/2 | O11: 2026-10-23 | P11: 自动写入 | Q11: 1407 | R11: 1976 | S11: 0.0032 | W11: 11.52
B12: R0008 | C12: M01 | D12: =IF($C12="","",IFERROR(VLOOKUP($C12,模型信息!$B$5:$C$24,2,0),"未登记")) -> DeepSeek-V4-Flash | E12: CON08 | F12: =IF($E12="","",IFERROR(VLOOKUP($E12,题目信息!$B$5:$C$253,2,0),"未登记")) -> 约束处理 | G12: 1 | H12: CO2–growth literature review: * Environmental Kuznets curve (EKC): inverted-U CO2–income relation; early growth raises emissions, later growth lowers emissions. - Evidence mixed: cross-country support; time-series/country studies often reject EKC. * Decoupling research: absolute decoupling possible; relative decoupling common. - Policy stringency, energy mix, technology moderate emissions–growth link. * Causality tests: growth→CO2, CO2→growth, feedback, neutrality. - Results depend on sample, period, econometric method, institutional context. * Panel/ARDL methods: heterogeneous panels, threshold models, quantile regressions. - Findings: high-income economies show weaker CO2–growth elasticity; middle-income economies stronger. * Policy implications: carbon pricing, clean innovation, green investment. - Growth-compatible climate policy needs context-specific sequencing, not one-size-fits-all. | I12: =IF($E12="","",IFERROR(VLOOKUP($E12,题目信息!$B$5:$J$253,9,0),"")) -> 约束: format:sub-bullets,ratio:stop_words | J12: 10 | K12: =IF($E12="","",IFERROR(VLOOKUP($E12,题目信息!$B$5:$L$253,11,0),10)) -> 10 | L12: =IF(OR($J12="",$K12=""),"",$J12/$K12) -> 1 | M12: 规则自动判分 | N12: 官方校验通过 2/2 | O12: 2026-10-23 | P12: 自动写入 | Q12: 1435 | R12: 3619 | S12: 0.0055 | W12: 21.69
B13: R0009 | C13: M01 | D13: =IF($C13="","",IFERROR(VLOOKUP($C13,模型信息!$B$5:$C$24,2,0),"未登记")) -> DeepSeek-V4-Flash | E13: CON09 | F13: =IF($E13="","",IFERROR(VLOOKUP($E13,题目信息!$B$5:$C$253,2,0),"未登记")) -> 约束处理 | G13: 1 | H13: <em>The passage’s strength is its claustrophobic sensory immediacy and tense, fragmented dialogue.</em> Physical pain and nausea are grounded in concrete body details that make Liam’s concrete purgatory feel immediate. The interrupted dialogue and gravelled voice create tension while the dead lifeline image tightens the night’s shrinking pulsing oppressive pressure around him. The clipped commands, unfinished threat, and quick “Consider it done” exchange reveal immediate urgency and brotherly trust without exposition letting readers infer loyalty danger and shared resolve. | I13: =IF($E13="","",IFERROR(VLOOKUP($E13,题目信息!$B$5:$J$253,9,0),"")) -> 约束: sentence:increment,format:thesis | J13: 5 | K13: =IF($E13="","",IFERROR(VLOOKUP($E13,题目信息!$B$5:$L$253,11,0),10)) -> 10 | L13: =IF(OR($J13="",$K13=""),"",$J13/$K13) -> 0.5 | M13: 规则自动判分 | N13: 官方校验通过 1/2 | O13: 2026-10-23 | P13: 自动写入 | Q13: 1499 | R13: 2696 | S13: 0.0042 | W13: 14.64
B14: R0010 | C14: M01 | D14: =IF($C14="","",IFERROR(VLOOKUP($C14,模型信息!$B$5:$C$24,2,0),"未登记")) -> DeepSeek-V4-Flash | E14: CON10 | F14: =IF($E14="","",IFERROR(VLOOKUP($E14,题目信息!$B$5:$C$253,2,0),"未登记")) -> 约束处理 | G14: 1 | H14: KRAS G12C is an oncogenic driver in about **3–4%** of colorectal cancers; it locks KRAS in active GTP-bound form and hyperactivates MAPK signaling. !?!? It associates with poor prognosis and resistance to EGFR antibodies, so test RAS/BRAF status before anti-EGFR therapy. !?!? Sotorasib and adagrasib bind the mutant cysteine but show modest monotherapy activity in CRC (**~10–20%** response, short progression-free survival), because EGFR feedback reactivates MAPK. !?!? Combine G12C inhibitors with EGFR antibodies (cetuximab or panitumumab) or SHP2 inhibitors to improve responses. !?!? Resistance involves RTK/MAPK reactivation and secondary KRAS mutations; biopsy at progression and trial enrollment guide treatment. | I14: =IF($E14="","",IFERROR(VLOOKUP($E14,题目信息!$B$5:$J$253,9,0),"")) -> 约束: count:word_count_range,format:list | J14: 5 | K14: =IF($E14="","",IFERROR(VLOOKUP($E14,题目信息!$B$5:$L$253,11,0),10)) -> 10 | L14: =IF(OR($J14="",$K14=""),"",$J14/$K14) -> 0.5 | M14: 规则自动判分 | N14: 官方校验通过 1/2 | O14: 2026-10-23 | P14: 自动写入 | Q14: 1456 | R14: 2377 | S14: 0.0038 | W14: 15.04
B15: R0011 | C15: M01 | D15: =IF($C15="","",IFERROR(VLOOKUP($C15,模型信息!$B$5:$C$24,2,0),"未登记")) -> DeepSeek-V4-Flash | E15: CON11 | F15: =IF($E15="","",IFERROR(VLOOKUP($E15,题目信息!$B$5:$C$253,2,0),"未登记")) -> 约束处理 | G15: 1 | H15: Arya grants allies faces. Masked doubles fool foes. New masks mislead crowds. | I15: =IF($E15="","",IFERROR(VLOOKUP($E15,题目信息!$B$5:$J$253,9,0),"")) -> 约束: format:line_indent,ratio:sentence_words | J15: 10 | K15: =IF($E15="","",IFERROR(VLOOKUP($E15,题目信息!$B$5:$L$253,11,0),10)) -> 10 | L15: =IF(OR($J15="",$K15=""),"",$J15/$K15) -> 1 | M15: 规则自动判分 | N15: 官方校验通过 2/2 | O15: 2026-10-23 | P15: 自动写入 | Q15: 1417 | R15: 3011 | S15: 0.0047 | W15: 16.23
B16: R0012 | C16: M01 | D16: =IF($C16="","",IFERROR(VLOOKUP($C16,模型信息!$B$5:$C$24,2,0),"未登记")) -> DeepSeek-V4-Flash | E16: CON12 | F16: =IF($E16="","",IFERROR(VLOOKUP($E16,题目信息!$B$5:$C$253,2,0),"未登记")) -> 约束处理 | G16: 1 | H16: Coordinating cross-team squads, synchronising launch planning, commencing common deployment. | I16: =IF($E16="","",IFERROR(VLOOKUP($E16,题目信息!$B$5:$J$253,9,0),"")) -> 约束: words:consonants,words:odd_even_syllables | J16: 5 | K16: =IF($E16="","",IFERROR(VLOOKUP($E16,题目信息!$B$5:$L$253,11,0),10)) -> 10 | L16: =IF(OR($J16="",$K16=""),"",$J16/$K16) -> 0.5 | M16: 规则自动判分 | N16: 官方校验通过 1/2 | O16: 2026-10-23 | P16: 自动写入 | Q16: 1422 | R16: 3446 | S16: 0.0053 | W16: 20.03
B17: R0013 | C17: M01 | D17: =IF($C17="","",IFERROR(VLOOKUP($C17,模型信息!$B$5:$C$24,2,0),"未登记")) -> DeepSeek-V4-Flash | E17: CON13 | F17: =IF($E17="","",IFERROR(VLOOKUP($E17,题目信息!$B$5:$C$253,2,0),"未登记")) -> 约束处理 | G17: 1 | I17: =IF($E17="","",IFERROR(VLOOKUP($E17,题目信息!$B$5:$J$253,9,0),"")) -> 约束: words:consonants,words:odd_even_syllables | J17: 0 | K17: =IF($E17="","",IFERROR(VLOOKUP($E17,题目信息!$B$5:$L$253,11,0),10)) -> 10 | L17: =IF(OR($J17="",$K17=""),"",$J17/$K17) -> 0 | M17: 规则自动判分 | N17: 模型无有效回答 | O17: 2026-10-23 | P17: 自动写入·调用失败
B18: R0014 | C18: M01 | D18: =IF($C18="","",IFERROR(VLOOKUP($C18,模型信息!$B$5:$C$24,2,0),"未登记")) -> DeepSeek-V4-Flash | E18: CON14 | F18: =IF($E18="","",IFERROR(VLOOKUP($E18,题目信息!$B$5:$C$253,2,0),"未登记")) -> 约束处理 | G18: 1 | H18: Correlating dhost and rt helps identify attacks: he said, "The guide notes, 'A rule reads, "Correlate dhost and rt."'" 😊 | I18: =IF($E18="","",IFERROR(VLOOKUP($E18,题目信息!$B$5:$J$253,9,0),"")) -> 约束: format:quotes,format:emoji | J18: 10 | K18: =IF($E18="","",IFERROR(VLOOKUP($E18,题目信息!$B$5:$L$253,11,0),10)) -> 10 | L18: =IF(OR($J18="",$K18=""),"",$J18/$K18) -> 1 | M18: 规则自动判分 | N18: 官方校验通过 2/2 | O18: 2026-10-23 | P18: 自动写入 | Q18: 1538 | R18: 2062 | S18: 0.0034 | W18: 11.49
B19: R0015 | C19: M01 | D19: =IF($C19="","",IFERROR(VLOOKUP($C19,模型信息!$B$5:$C$24,2,0),"未登记")) -> DeepSeek-V4-Flash | E19: CON15 | F19: =IF($E19="","",IFERROR(VLOOKUP($E19,题目信息!$B$5:$C$253,2,0),"未登记")) -> 约束处理 | G19: 1 | H19: <section><i>Kennedy saw the space race as a test of national purpose and global leadership.</i> He treated the Moon goal as a strategic commitment that could unite Americans and signal decisive technological superiority. Kennedy linked the race to peace and security while warning that failure would damage international prestige and leave the nation dangerously behind. He accepted the high costs and risks because he believed the goal demanded sacrifice, scientific progress, and a clear demonstration of American resolve before the world.</section> | I19: =IF($E19="","",IFERROR(VLOOKUP($E19,题目信息!$B$5:$J$253,9,0),"")) -> 约束: sentence:increment,format:thesis | J19: 5 | K19: =IF($E19="","",IFERROR(VLOOKUP($E19,题目信息!$B$5:$L$253,11,0),10)) -> 10 | L19: =IF(OR($J19="",$K19=""),"",$J19/$K19) -> 0.5 | M19: 规则自动判分 | N19: 官方校验通过 1/2 | O19: 2026-10-23 | P19: 自动写入 | Q19: 1428 | R19: 2620 | S19: 0.0041 | W19: 14.59
B20: R0016 | C20: M01 | D20: =IF($C20="","",IFERROR(VLOOKUP($C20,模型信息!$B$5:$C$24,2,0),"未登记")) -> DeepSeek-V4-Flash | E20: CON16 | F20: =IF($E20="","",IFERROR(VLOOKUP($E20,题目信息!$B$5:$C$253,2,0),"未登记")) -> 约束处理 | G20: 1 | H20: Declarative: Cylindrical continuity equations start from vector divergence form ∇·v = 0, assume axisymmetric flow with angular independence ∂/∂θ = 0, simplify through (1/y)∂(y v)/∂y + ∂u/∂x = 0, multiply through cross-stream distance y, and yield ∂(y u)/∂x + ∂(y v)/∂y = 0, with streamwise speed u, cross-stream speed v, streamwise coordinate x, cross-stream coordinate y. Interrogative: Which formula follows through cylindrical divergence? Exclamatory: Perfect target formula! | I20: =IF($E20="","",IFERROR(VLOOKUP($E20,题目信息!$B$5:$J$253,9,0),"")) -> 约束: ratio:sentence_balance,words:consonants | J20: 0 | K20: =IF($E20="","",IFERROR(VLOOKUP($E20,题目信息!$B$5:$L$253,11,0),10)) -> 10 | L20: =IF(OR($J20="",$K20=""),"",$J20/$K20) -> 0 | M20: 规则自动判分 | N20: 官方校验通过 0/2 | O20: 2026-10-23 | P20: 自动写入 | Q20: 1484 | R20: 8498 | S20: 0.0123 | W20: 56.95
B21: R0017 | C21: M01 | D21: =IF($C21="","",IFERROR(VLOOKUP($C21,模型信息!$B$5:$C$24,2,0),"未登记")) -> DeepSeek-V4-Flash | E21: CON17 | F21: =IF($E21="","",IFERROR(VLOOKUP($E21,题目信息!$B$5:$C$253,2,0),"未登记")) -> 约束处理 | G21: 1 | H21: During my master’s degree, I learned SQL and R, which gave me a solid foundation in programming fundamentals. 😊 I now plan to build on that foundation by applying my programming knowledge to Java. 😊 This step will help me deepen my understanding of software development in a practical way. 😊 By connecting what I learned in SQL and R with Java, I can strengthen my technical skills and problem-solving approach. 😊 I am eager to use these languages as a bridge from basic programming concepts to real software development practices. 😊 I plan to use this experience to eat up new software development challenges with confidence. 😊 | I21: =IF($E21="","",IFERROR(VLOOKUP($E21,题目信息!$B$5:$J$253,9,0),"")) -> 约束: format:emoji,sentence:keyword | J21: 10 | K21: =IF($E21="","",IFERROR(VLOOKUP($E21,题目信息!$B$5:$L$253,11,0),10)) -> 10 | L21: =IF(OR($J21="",$K21=""),"",$J21/$K21) -> 1 | M21: 规则自动判分 | N21: 官方校验通过 2/2 | O21: 2026-10-23 | P21: 自动写入 | Q21: 1455 | R21: 2281 | S21: 0.0037 | W21: 24.4
B22: R0018 | C22: M01 | D22: =IF($C22="","",IFERROR(VLOOKUP($C22,模型信息!$B$5:$C$24,2,0),"未登记")) -> DeepSeek-V4-Flash | E22: CON18 | F22: =IF($E22="","",IFERROR(VLOOKUP($E22,题目信息!$B$5:$C$253,2,0),"未登记")) -> 约束处理 | G22: 1 | H22: **Alternate Universe: Satellite-Era Discovery Timeline** * 1957: Sputnik-9 satellite photographs Veil rupture; new continent Aetheria emerges. - Initial images reveal floating islands, glass forests, violet seas. * 1962: Orbital probe Magellan-2 maps Aetheria's magnetic rivers. - Telemetry shows coral cities, sky-whales, luminous storm belts. * 1971: Manned lander Dawn Arc reaches Aetheria's coast. - Crew plants flag; Lumen Folk bioluminescent greeting. * 1984: Treaty Two Skies opens migration. - Aetherian spores fuel clean energy; Earth cities transform. * 1999: Global Bridge Festival celebrates twin worlds. - Satellite constellation Halo Ring links civilizations. | I22: =IF($E22="","",IFERROR(VLOOKUP($E22,题目信息!$B$5:$J$253,9,0),"")) -> 约束: format:sub-bullets,ratio:stop_words | J22: 5 | K22: =IF($E22="","",IFERROR(VLOOKUP($E22,题目信息!$B$5:$L$253,11,0),10)) -> 10 | L22: =IF(OR($J22="",$K22=""),"",$J22/$K22) -> 0.5 | M22: 规则自动判分 | N22: 官方校验通过 1/2 | O22: 2026-10-23 | P22: 自动写入 | Q22: 1453 | R22: 3926 | S22: 0.0059 | W22: 23.26
B23: R0019 | C23: M01 | D23: =IF($C23="","",IFERROR(VLOOKUP($C23,模型信息!$B$5:$C$24,2,0),"未登记")) -> DeepSeek-V4-Flash | E23: CON19 | F23: =IF($E23="","",IFERROR(VLOOKUP($E23,题目信息!$B$5:$C$253,2,0),"未登记")) -> 约束处理 | G23: 1 | H23: Summarize Fatherland – All Russia as a mainly **centrist, pragmatic, statist and socially conservative** electoral bloc, with patriotic, regionalist and social-market currents; it rejected radical liberalism and communist restoration, backed a stronger state role in the economy and regional autonomy, and merged with Unity in 2001 to help form United Russia. Commentators such as **Emma, Liam, Sophia, Jackson, Olivia, Noah, Ava, Lucas, Isabella, Mason, Mia, Ethan, Charlotte, Alexander, Amelia, Benjamin, Harper, Leo, Zoe, Daniel, Chloe, Samuel, Lily, Matthew, Grace, Owen, Abigail, Gabriel, Ella, Jacob, Scarlett, Nathan, Victoria, Elijah, Layla, Nicholas, Audrey, David, and Hannah** have characterized it in broadly these terms. | I23: =IF($E23="","",IFERROR(VLOOKUP($E23,题目信息!$B$5:$J$253,9,0),"")) -> 约束: words:start_verb,count:person_names | J23: 5 | K23: =IF($E23="","",IFERROR(VLOOKUP($E23,题目信息!$B$5:$L$253,11,0),10)) -> 10 | L23: =IF(OR($J23="",$K23=""),"",$J23/$K23) -> 0.5 | M23: 规则自动判分 | N23: 官方校验通过 1/2 | O23: 2026-10-23 | P23: 自动写入 | Q23: 1517 | R23: 2563 | S23: 0.0041 | W23: 15.39
B24: R0020 | C24: M01 | D24: =IF($C24="","",IFERROR(VLOOKUP($C24,模型信息!$B$5:$C$24,2,0),"未登记")) -> DeepSeek-V4-Flash | E24: CON20 | F24: =IF($E24="","",IFERROR(VLOOKUP($E24,题目信息!$B$5:$C$253,2,0),"未登记")) -> 约束处理 | G24: 1 | H24: Mankind’s worship seeks Founding Fathers’ kingdom through steadfast strength, and mankind’s trespasses find forgiveness through gods’ clemency. Will Founding Fathers grant mankind’s present bread and steer mankind’s steps from temptation’s wickedness? What steadfast strength Founding Fathers grant mankind’s shield against wickedness! | I24: =IF($E24="","",IFERROR(VLOOKUP($E24,题目信息!$B$5:$J$253,9,0),"")) -> 约束: ratio:sentence_balance,words:consonants | J24: 10 | K24: =IF($E24="","",IFERROR(VLOOKUP($E24,题目信息!$B$5:$L$253,11,0),10)) -> 10 | L24: =IF(OR($J24="",$K24=""),"",$J24/$K24) -> 1 | M24: 规则自动判分 | N24: 官方校验通过 2/2 | O24: 2026-10-23 | P24: 自动写入 | Q24: 1464 | R24: 4647 | S24: 0.0069 | W24: 29.22
B25: R0021 | C25: M01 | D25: =IF($C25="","",IFERROR(VLOOKUP($C25,模型信息!$B$5:$C$24,2,0),"未登记")) -> DeepSeek-V4-Flash | E25: CR01 | F25: =IF($E25="","",IFERROR(VLOOKUP($E25,题目信息!$B$5:$C$253,2,0),"未登记")) -> 创造力 | G25: 1 | H25: **Idea:** Develop a physics-informed machine-learning system that assimilates opportunistic temperature and humidity readings from ride-share and delivery fleets into **100-m urban weather forecasts**. The system would calibrate low-cost vehicle sensors against reference stations, enforce surface-energy-balance constraints via a physics-informed neural network, and downscale forecasts in real time. **Novelty:** It combines mobile citizen observations with physically constrained AI for street-scale urban meteorology, instead of relying on sparse fixed stations or purely black-box downscaling. **Feasibility:** Fleets already collect geolocated data; low-cost sensor calibration and data-assimilation methods are established; physics-informed neural networks can run on modest GPU clusters. A single-city pilot could quantify forecast gains for heat-stress and convective-nowcasting applications. | I25: =IF($E25="","",IFERROR(VLOOKUP($E25,题目信息!$B$5:$J$253,9,0),"")) -> 无固定答案（官方LLM评审） | J25: 0 | K25: =IF($E25="","",IFERROR(VLOOKUP($E25,题目信息!$B$5:$L$253,11,0),10)) -> 10 | L25: =IF(OR($J25="",$K25=""),"",$J25/$K25) -> 0 | M25: LLM评审 | N25: 评审调用失败: 调用失败(重试2次): <urlopen error _ssl.c:1015: The handshake operation timed out> | O25: 2026-10-23 | P25: 自动写入 | Q25: 1422 | R25: 1618 | S25: 0.0027 | W25: 7.35
B26: R0022 | C26: M01 | D26: =IF($C26="","",IFERROR(VLOOKUP($C26,模型信息!$B$5:$C$24,2,0),"未登记")) -> DeepSeek-V4-Flash | E26: CR02 | F26: =IF($E26="","",IFERROR(VLOOKUP($E26,题目信息!$B$5:$C$253,2,0),"未登记")) -> 创造力 | G26: 1 | H26: **Idea:** Construct a “periodic-table-guided descriptor map” for predicting stable single-atom catalysts (SACs) on defective MXene supports. The map would combine elemental trends—electronegativity, d-band center, ionic radius, and oxidation-state preference—with local coordination features from DFT, then use interpretable machine learning to rank promising metal–support pairs. **Why novel:** Most SAC screening relies on isolated material-specific datasets or black-box models; this approach explicitly encodes periodic-table trends and coordination chemistry into a transferable, interpretable framework. **Why feasible:** Public DFT databases, mature ML tools, and well-established MXene synthesis/characterization methods are available. Initial screening can be validated with a small set of computationally predicted candidates using aberration-corrected STEM and electrochemical testing. | I26: =IF($E26="","",IFERROR(VLOOKUP($E26,题目信息!$B$5:$J$253,9,0),"")) -> 无固定答案（官方LLM评审） | J26: 9 | K26: =IF($E26="","",IFERROR(VLOOKUP($E26,题目信息!$B$5:$L$253,11,0),10)) -> 10 | L26: =IF(OR($J26="",$K26=""),"",$J26/$K26) -> 0.9 | M26: LLM评审 | N26: 分析：要求为英文提出一个与 periodic table 相关的新颖且可行的科研想法，并在150词内说明想法、新颖性和可行性。模型回答为英文，约107词，满足字数限制；明确给出了研究想法、新颖性理由和可行性理由，且围绕周期表趋势展开，符合题目要求。新颖性方面，将周期表元素趋势与缺陷MXene上单原子催化剂的局域配位特征结合，构建可解释、可迁移的描述符图并用于机器学习筛选，具有明确新意，但本质上是已有描述符筛选与机器学习方法的集成创新，并非全新范式，故新颖性给3/4。可行性方面，公共DFT数据库、成熟ML工具、MXene合成表征及STEM/电化学验证均合理，给3/3。流畅性方面，结构清晰、术语准 | O26: 2026-10-23 | P26: 自动写入 | Q26: 1422 | R26: 1490 | S26: 0.0026 | T26: 1741 | U26: 2436 | W26: 7.33
B27: R0023 | C27: M01 | D27: =IF($C27="","",IFERROR(VLOOKUP($C27,模型信息!$B$5:$C$24,2,0),"未登记")) -> DeepSeek-V4-Flash | E27: CR03 | F27: =IF($E27="","",IFERROR(VLOOKUP($E27,题目信息!$B$5:$C$253,2,0),"未登记")) -> 创造力 | G27: 1 | H27: **Idea:** Develop a physics-constrained diffusion model for probabilistic urban-scale downscaling of global ensemble weather forecasts. The model would condition on coarse ensemble members, terrain, land-surface data, and atmospheric constraints to generate high-resolution forecast ensembles with calibrated uncertainty. **Novelty:** Most downscaling methods are deterministic or lack explicit physical consistency and uncertainty calibration. This approach combines generative diffusion with soft physical constraints and conformal calibration, producing sharp, reliable local forecasts—especially for precipitation and temperature extremes—without requiring expensive regional model runs. **Feasibility:** Public global ensemble forecasts, reanalysis, satellite products, and urban station data are widely available. Open-source diffusion models and GPU computing make training practical. The method can be validated retrospectively against high-resolution radar/station observations and benchmarked against statistical and dynamical downscaling, enabling a realistic proof-of-concept within one to two years. | I27: =IF($E27="","",IFERROR(VLOOKUP($E27,题目信息!$B$5:$J$253,9,0),"")) -> 无固定答案（官方LLM评审） | J27: 9 | K27: =IF($E27="","",IFERROR(VLOOKUP($E27,题目信息!$B$5:$L$253,11,0),10)) -> 10 | L27: =IF(OR($J27="",$K27=""),"",$J27/$K27) -> 0.9 | M27: LLM评审 | N27: 分析：回答为英文，约**130词**，未超过150词；明确包含Idea、Novelty、Feasibility三部分，且紧扣weather forecasting。新颖性方面，将物理约束扩散模型、集合降尺度与共形校准结合用于城市尺度概率预报，具有合理创新，但核心组件多为已有方法的集成，给**3/4**；可行性方面，数据、开源模型、GPU算力、验证方案与1–2年概念验证路径均较充分，给**3/3**；流畅性方面，结构清晰、术语准确、表达简洁，给**3/3**。未发现违反字数、语言、格式等硬约束。 得分：9 | O27: 2026-10-23 | P27: 自动写入 | Q27: 1422 | R27: 1505 | S27: 0.0026 | T27: 1758 | U27: 2666 | W27: 7.12
B28: R0024 | C28: M01 | D28: =IF($C28="","",IFERROR(VLOOKUP($C28,模型信息!$B$5:$C$24,2,0),"未登记")) -> DeepSeek-V4-Flash | E28: CR04 | F28: =IF($E28="","",IFERROR(VLOOKUP($E28,题目信息!$B$5:$C$253,2,0),"未登记")) -> 创造力 | G28: 1 | H28: **Idea:** Use distributed acoustic sensing (DAS) on existing submarine telecom fibers to continuously monitor offshore megathrust fault zones, detecting microseismicity and slow-slip precursors that could improve earthquake and tsunami early warning. Pair DAS data with physics-informed machine learning to separate weak fault signals from ocean noise. **Novelty:** It converts idle or operational submarine cables into dense offshore seismic arrays, filling a major ocean-coverage gap and targeting precursor processes near locked megathrust zones rather than only post-event rupture detection. **Feasibility:** DAS interrogators can be installed at cable landing stations, and fiber-optic seismic sensing is already proven. Ocean-noise denoising with ML is mature, and a pilot on one cable could be validated against ocean-bottom seismometers at modest cost compared with new permanent offshore arrays. | I28: =IF($E28="","",IFERROR(VLOOKUP($E28,题目信息!$B$5:$J$253,9,0),"")) -> 无固定答案（官方LLM评审） | J28: 9 | K28: =IF($E28="","",IFERROR(VLOOKUP($E28,题目信息!$B$5:$L$253,11,0),10)) -> 10 | L28: =IF(OR($J28="",$K28=""),"",$J28/$K28) -> 0.9 | M28: LLM评审 | N28: 分析： - 要求核对：① 围绕关键词 earthquakes——符合；② 英文写作——符合；③ 给出一个新颖且可行的研究想法——符合；④ 分别说明 idea / novelty / feasibility——三部分显式标注，齐全；⑤ 字数≤150——全文约121词，符合；⑥ 格式与禁用项——无格式违规，无禁用内容。 - 新颖性（orig，满分4）：将海底通信光纤DAS用于地震监测已是近年公开研究的热点方向（海底DAS阵列、微震检测均有文献先例），本回答属于该方向的集成式延伸，而非全新范式；加分点在于把目标明确锚定在"慢滑动前兆"而非震后破裂探测，并引入物理信息机器学习做弱信号与海洋噪声分离，具 | O28: 2026-10-23 | P28: 自动写入 | Q28: 1421 | R28: 1621 | S28: 0.0027 | T28: 1746 | U28: 2412 | W28: 9.37
B29: R0025 | C29: M01 | D29: =IF($C29="","",IFERROR(VLOOKUP($C29,模型信息!$B$5:$C$24,2,0),"未登记")) -> DeepSeek-V4-Flash | E29: CR05 | F29: =IF($E29="","",IFERROR(VLOOKUP($E29,题目信息!$B$5:$C$253,2,0),"未登记")) -> 创造力 | G29: 1 | H29: **Idea:** A “wide-binary age laboratory”: use Gaia astrometry to identify thousands of wide binary pairs and TESS photometry to measure rotation periods and solar-like oscillations for both components. Because wide-binary stars are coeval but have different masses, they provide internal age calibration for field stars. **Novelty:** It cross-calibrates gyrochronology and asteroseismic scaling relations at the individual-system level, rather than relying on cluster averages, and tests age-dating methods where stellar activity and oscillations can be measured simultaneously. **Feasibility:** Gaia DR3 and TESS provide public, homogeneous data; existing asteroseismic and rotation-period pipelines can be applied. A statistical sample of wide binaries can be assembled and analyzed within current computational resources. | I29: =IF($E29="","",IFERROR(VLOOKUP($E29,题目信息!$B$5:$J$253,9,0),"")) -> 无固定答案（官方LLM评审） | J29: 8 | K29: =IF($E29="","",IFERROR(VLOOKUP($E29,题目信息!$B$5:$L$253,11,0),10)) -> 10 | L29: =IF(OR($J29="",$K29=""),"",$J29/$K29) -> 0.8 | M29: LLM评审 | N29: 分析：题目要求围绕关键词 stars 提出一个新颖且可行的科研想法，用英文在 150 词内说明想法、新颖性和可行性。模型回答逐项满足：主题与 stars 相关；英文表达；结构包含 Idea、Novelty、Feasibility；字数约 **108 词**，未超限；无格式或禁用词硬伤。新颖性方面，将宽双星作为“年龄实验室”，在单个系统层面交叉校准陀螺年代学与星震学定龄方法，有一定新意，但属于已有方法组合的增量创新，给 **3/4**。可行性方面，Gaia DR3 与 TESS 数据公开，旋转周期测量可行；但声称用 TESS 对“数千”宽双星双组分测量类太阳振荡偏乐观，星震学探测受亮度与信噪比限 | O29: 2026-10-23 | P29: 自动写入 | Q29: 1421 | R29: 1412 | S29: 0.0024 | T29: 1734 | U29: 2475 | W29: 7.17
B30: R0026 | C30: M01 | D30: =IF($C30="","",IFERROR(VLOOKUP($C30,模型信息!$B$5:$C$24,2,0),"未登记")) -> DeepSeek-V4-Flash | E30: CR06 | F30: =IF($E30="","",IFERROR(VLOOKUP($E30,题目信息!$B$5:$C$253,2,0),"未登记")) -> 创造力 | G30: 1 | H30: **Idea:** Develop an acoustic early-warning system for hurricane rapid intensification (RI) by training deep-learning models on underwater sound recorded by existing hydrophone arrays, combined with satellite sea-surface temperature and Argo profiles. **Why novel:** Most RI prediction relies on satellite and airborne observations of the storm and upper ocean. This approach uses the ocean soundscape—breaking waves, bubble injection, and rain noise—as an integrated proxy for air–sea momentum and heat exchange, a signal not yet exploited operationally for RI forecasting. **Why feasible:** Global hydrophone networks, Argo floats, and satellite altimetry already provide decades of overlapping data. Historical hurricane tracks allow supervised labeling of RI events, and low-cost hydrophone additions can fill regional gaps. A proof-of-concept could be tested retrospectively on Atlantic and Pacific storms within 2–3 years. | I30: =IF($E30="","",IFERROR(VLOOKUP($E30,题目信息!$B$5:$J$253,9,0),"")) -> 无固定答案（官方LLM评审） | J30: 8 | K30: =IF($E30="","",IFERROR(VLOOKUP($E30,题目信息!$B$5:$L$253,11,0),10)) -> 10 | L30: =IF(OR($J30="",$K30=""),"",$J30/$K30) -> 0.8 | M30: LLM评审 | N30: 分析：逐条核对：(1) 语言为英文，符合要求；(2) 字数约127词，未超过150词上限，符合；(3) 明确给出研究想法（用水听器阵列水下声学+卫星SST+Argo剖面训练深度学习模型，预警飓风快速增强RI），符合；(4) 明确说明新颖性（现有RI预报依赖卫星/机载观测，而海洋声景作为海气动量与热量交换的综合代理尚未被业务化用于RI预报），论证具体且有针对性，符合；(5) 明确说明可行性（全球水听器网络、Argo、卫星高度计已有数十年重叠数据；历史路径可提供RI监督标签；低成本补充部署可填补区域空白；2–3年内可回溯验证），符合；(6) 格式为分点小标题式，结构清晰，符合。 评分要点核对：新 | O30: 2026-10-23 | P30: 自动写入 | Q30: 1421 | R30: 1393 | S30: 0.0024 | T30: 1750 | U30: 1977 | W30: 10.13
B31: R0027 | C31: M01 | D31: =IF($C31="","",IFERROR(VLOOKUP($C31,模型信息!$B$5:$C$24,2,0),"未登记")) -> DeepSeek-V4-Flash | E31: CR07 | F31: =IF($E31="","",IFERROR(VLOOKUP($E31,题目信息!$B$5:$C$253,2,0),"未登记")) -> 创造力 | G31: 1 | H31: **Research idea:** Develop a phycosphere-informed probiotic consortium to stabilize microalgal cultivation in open raceway ponds. Isolate algae-associated bacteria from locally adapted green algae, screen for traits such as vitamin B12 provision and reactive-oxygen scavenging, then test a defined 3–5 strain consortium for biomass and lipid productivity under fluctuating light and temperature. **Why novel:** Most algal probiotics are selected empirically; this approach links phycosphere ecology to functional trait selection and community stability, producing a reproducible, ecology-based inoculant. **Why feasible:** Native algae and bacteria are readily isolated; screening uses standard plate assays, flow cytometry, and amplicon sequencing; small raceway mesocosms can test consortia within 6–9 months. The output would be a candidate probiotic and design rules for phycosphere management in biofuel and bioproduct cultivation. | I31: =IF($E31="","",IFERROR(VLOOKUP($E31,题目信息!$B$5:$J$253,9,0),"")) -> 无固定答案（官方LLM评审） | J31: 9 | K31: =IF($E31="","",IFERROR(VLOOKUP($E31,题目信息!$B$5:$L$253,11,0),10)) -> 10 | L31: =IF(OR($J31="",$K31=""),"",$J31/$K31) -> 0.9 | M31: LLM评审 | N31: 分析：要求为围绕关键词 phycology 提出一个新颖且可行的英文研究想法，并说明想法、新颖性、可行性，且不超过150词。模型回答完整覆盖三项：提出“phycosphere-informed probiotic consortium”用于稳定开放跑道池微藻培养；说明新颖性在于将藻际生态与功能性状筛选、群落稳定性结合；说明可行性在于本地藻菌易分离、标准筛选与测序手段成熟、6–9个月中型跑道池验证可行。英文表达流畅、结构清晰，字数约122词，符合150词限制，未违反硬约束。扣分点：新颖性属于已有藻际微生物/益生菌思路的合理组合，创新强度中等，未达到突破性程度，因此新颖性给3/4；可行性高，给3/ | O31: 2026-10-23 | P31: 自动写入 | Q31: 1423 | R31: 1962 | S31: 0.0032 | T31: 1757 | U31: 2699 | W31: 12.3
B32: R0028 | C32: M01 | D32: =IF($C32="","",IFERROR(VLOOKUP($C32,模型信息!$B$5:$C$24,2,0),"未登记")) -> DeepSeek-V4-Flash | E32: CR08 | F32: =IF($E32="","",IFERROR(VLOOKUP($E32,题目信息!$B$5:$C$253,2,0),"未登记")) -> 创造力 | G32: 1 | H32: **Idea:** Measure the three-dimensional dark-matter shapes of Local Group galaxies by combining stellar-stream gaps with resolved rotation curves. **Novelty:** Most galaxy-shape measurements rely on lensing or gas kinematics, which poorly constrain triaxiality at small radii. Stellar-stream gaps directly trace subhalo populations and halo ellipticity, offering a new test of cold dark matter predictions on dwarf-galaxy scales. **Feasibility:** Rubin/LSST will provide deep, wide-field photometry of streams in the Milky Way and Local Group dwarfs; existing simulations (FIRE, Auriga) supply mock observables for pipeline validation. A pilot using DESI Legacy Imaging and Gaia proper motions can calibrate detection thresholds before LSST. This links galaxies, dark matter, and stream archaeology using data expected within the next few years. | I32: =IF($E32="","",IFERROR(VLOOKUP($E32,题目信息!$B$5:$J$253,9,0),"")) -> 无固定答案（官方LLM评审） | J32: 10 | K32: =IF($E32="","",IFERROR(VLOOKUP($E32,题目信息!$B$5:$L$253,11,0),10)) -> 10 | L32: =IF(OR($J32="",$K32=""),"",$J32/$K32) -> 1 | M32: LLM评审 | N32: 分析： - **要求核对**：①英文作答——符合；②字数≤150词——全文约 **120词**，符合；③明确“陈述想法+新颖性+可行性”三要素——以 Idea/Novelty/Feasibility 三段清晰对应，符合；④紧扣关键词 galaxies——以本星系群星系暗物质晕三维形状为核心，符合。 - **新颖性（4分）**：将“星流间隙（stream gaps）”与“分辨旋转曲线”联合，约束小半径处暗物质晕的三轴比，避开传统弱引力透镜/气体运动学的半径与投影限制，并提出对 CDM 矮星系尺度预言的检验，思路具体且不落俗套，可得 **4分**。 - **可行性（3分）**：给出 L | O32: 2026-10-23 | P32: 自动写入 | Q32: 1421 | R32: 2119 | S32: 0.0034 | T32: 1747 | U32: 1776 | W32: 15
B33: R0029 | C33: M01 | D33: =IF($C33="","",IFERROR(VLOOKUP($C33,模型信息!$B$5:$C$24,2,0),"未登记")) -> DeepSeek-V4-Flash | E33: CR09 | F33: =IF($E33="","",IFERROR(VLOOKUP($E33,题目信息!$B$5:$C$253,2,0),"未登记")) -> 创造力 | G33: 1 | H33: **Idea:** A citizen-science GPS reflectometry network using smartphone raw GPS measurements to map urban flood depth. Crowdsourced L1/L5 signal-to-noise and carrier-phase data from everyday phones would detect water-induced multipath changes and estimate surface water depth after calibration. **Novelty:** It repurposes existing GPS receivers as dense, zero-hardware flood sensors, complementing sparse gauges and satellite imagery with street-level observations. **Feasibility:** Android devices expose raw GPS/GNSS measurements; existing apps can log them. A small calibration campaign with controlled water depths and machine-learning inversion could validate the approach, making city-scale deployment practical and low-cost. | I33: =IF($E33="","",IFERROR(VLOOKUP($E33,题目信息!$B$5:$J$253,9,0),"")) -> 无固定答案（官方LLM评审） | J33: 8 | K33: =IF($E33="","",IFERROR(VLOOKUP($E33,题目信息!$B$5:$L$253,11,0),10)) -> 10 | L33: =IF(OR($J33="",$K33=""),"",$J33/$K33) -> 0.8 | M33: LLM评审 | N33: 分析：要求为基于关键词 global positioning system 提出一个新颖且可行的科研想法，英文、150词内，并说明想法、新颖性、可行性。模型回答完整覆盖三点：提出智能手机原始GPS反射测量市民科学洪水深度制图网络；新颖性说明复用现有GPS接收器为密集低成本洪水传感器；可行性说明Android原始GNSS数据、现有应用记录、校准与机器学习反演。语言为英文，约90词，符合150词限制；格式清晰，无禁用词或明显硬约束违反。按官方维度评估：新颖性中等偏上，属GNSS-R、洪水监测与智能手机众包的组合创新，但核心组件并非全新，给3/4；可行性较合理，但用智能手机多径/载波相位反演水深精度 | O33: 2026-10-23 | P33: 自动写入 | Q33: 1423 | R33: 1470 | S33: 0.0025 | T33: 1716 | U33: 1771 | W33: 7.24
B34: R0030 | C34: M01 | D34: =IF($C34="","",IFERROR(VLOOKUP($C34,模型信息!$B$5:$C$24,2,0),"未登记")) -> DeepSeek-V4-Flash | E34: CR10 | F34: =IF($E34="","",IFERROR(VLOOKUP($E34,题目信息!$B$5:$C$253,2,0),"未登记")) -> 创造力 | G34: 1 | H34: **Idea:** Develop DNA-origami “virus traps” that display clustered ACE2-mimetic receptors alongside a furin-cleavable fluorescent reporter, enabling label-free detection of infectious coronaviruses in environmental samples. **Why novel:** The platform mimics the spatial receptor clustering and proteolytic activation used during viral entry, rather than detecting viral RNA or antigens alone; this could distinguish infectious from non-infectious viruses. **Why feasible:** DNA origami is programmable and scalable; ACE2-mimetic peptides and furin substrates are well characterized; fluorescence readout requires only standard plate readers. Initial validation can use pseudotyped viruses and wastewater samples, with biosafety contained. | I34: =IF($E34="","",IFERROR(VLOOKUP($E34,题目信息!$B$5:$J$253,9,0),"")) -> 无固定答案（官方LLM评审） | J34: 9 | K34: =IF($E34="","",IFERROR(VLOOKUP($E34,题目信息!$B$5:$L$253,11,0),10)) -> 10 | L34: =IF(OR($J34="",$K34=""),"",$J34/$K34) -> 0.9 | M34: LLM评审 | N34: 分析：要求为英文、150词内、围绕 viruses 提出一个新颖可行研究想法，并说明想法、创新性、可行性。模型回答为英文，约90词，符合字数；明确给出 idea、why novel、why feasible，内容与病毒检测相关。新颖性较强：将DNA折纸、ACE2模拟受体空间簇集与furin切割荧光报告结合，用于区分感染性与非感染性冠状病毒，思路具体且有区分度，给4/4。可行性总体合理：DNA折纸可编程、ACE2模拟肽与furin底物已有基础，假病毒和污水样本初筛路径清楚；但“label-free”与荧光报告表述略矛盾，环境样本灵敏度、特异性及规模化验证未充分展开，给2.5/3，按整数评分体现为 | O34: 2026-10-23 | P34: 自动写入 | Q34: 1421 | R34: 1517 | S34: 0.0026 | T34: 1715 | U34: 2500 | W34: 8.49
B35: R0031 | C35: M01 | D35: =IF($C35="","",IFERROR(VLOOKUP($C35,模型信息!$B$5:$C$24,2,0),"未登记")) -> DeepSeek-V4-Flash | E35: CR11 | F35: =IF($E35="","",IFERROR(VLOOKUP($E35,题目信息!$B$5:$C$253,2,0),"未登记")) -> 创造力 | G35: 1 | H35: **Idea:** A 12-week feasibility trial of a smartphone-based “digital speech relapse signature” in first-episode schizophrenia. Participants complete weekly 2-minute free-speech samples; automated NLP measures lexical coherence and prosodic flattening are combined with passive mobility/actigraphy data to predict symptom exacerbation. Clinicians receive stepped-care alerts. **Novelty:** It prospectively integrates linguistic coherence and passive behavioral markers specifically in first-episode patients, rather than using cross-sectional speech analysis or single-modality monitoring. **Feasibility:** Smartphones and existing speech-NLP pipelines enable low-burden data collection. A pilot of 40 participants can test acceptability, data quality, and preliminary predictive validity against standardized symptom and relapse assessments, providing effect-size estimates for a larger trial. | I35: =IF($E35="","",IFERROR(VLOOKUP($E35,题目信息!$B$5:$J$253,9,0),"")) -> 无固定答案（官方LLM评审） | J35: 9 | K35: =IF($E35="","",IFERROR(VLOOKUP($E35,题目信息!$B$5:$L$253,11,0),10)) -> 10 | L35: =IF(OR($J35="",$K35=""),"",$J35/$K35) -> 0.9 | M35: LLM评审 | N35: 分析：题目要求围绕 schizophrenia 提出一个新颖、可行、英文、150词以内的科研想法，并说明想法、创新性和可行性。模型回答明确聚焦 first-episode schizophrenia，提出智能手机语音+被动行为数据的12周可行性试验，属于相关研究想法；明确写了 Novelty 和 Feasibility；全文约100词，符合150词限制；英文表达流畅，结构清楚。硬约束方面：包含关键词 schizophrenia，无禁用词，格式无问题。评分要点：新颖性较好，将语音连贯性、韵律扁平化与被动移动/活动数据结合，并聚焦首发患者的前瞻性预警，但数字表型、语音NLP和复发预测均已有较多相关 | O35: 2026-10-23 | P35: 自动写入 | Q35: 1421 | R35: 1504 | S35: 0.0026 | T35: 1736 | U35: 2137 | W35: 8.79
B36: R0032 | C36: M01 | D36: =IF($C36="","",IFERROR(VLOOKUP($C36,模型信息!$B$5:$C$24,2,0),"未登记")) -> DeepSeek-V4-Flash | E36: CR12 | F36: =IF($E36="","",IFERROR(VLOOKUP($E36,题目信息!$B$5:$C$253,2,0),"未登记")) -> 创造力 | G36: 1 | H36: **Idea:** Use existing dark fiber-optic telecom cables as distributed acoustic sensing (DAS) arrays to image near-ground tornado wind fields and track vortex structure in real time. **Novelty:** Most tornado sensing relies on radar, which struggles below the horizon and near the surface. Repurposing regional fiber networks as dense, kilometer-scale acoustic arrays could reveal tornado–ground coupling, debris loading, and low-level wind asymmetries at unprecedented resolution. **Feasibility:** DAS interrogators can be deployed on existing fiber in tornado-prone regions such as Oklahoma and Kansas. Machine-learning denoising can separate tornado signals from traffic and weather noise, and calibration against radar, mesonets, and damage surveys is straightforward. The approach is low-cost, scalable, and testable during the next tornado season. | I36: =IF($E36="","",IFERROR(VLOOKUP($E36,题目信息!$B$5:$J$253,9,0),"")) -> 无固定答案（官方LLM评审） | J36: 10 | K36: =IF($E36="","",IFERROR(VLOOKUP($E36,题目信息!$B$5:$L$253,11,0),10)) -> 10 | L36: =IF(OR($J36="",$K36=""),"",$J36/$K36) -> 1 | M36: LLM评审 | N36: 分析：关键词为 tornadoes，回答提出用现有暗光纤电信电缆作为分布式声学传感（DAS）阵列来成像近地面龙卷风风场并追踪涡旋结构，符合“一个相关研究想法”的要求。回答为英文，约 **114** 词，未超过 **150** 词。内容明确包含 Idea、Novelty、Feasibility 三部分：想法具体；新颖性体现在区别于雷达、利用既有光纤网络进行近地面高分辨率观测；可行性体现在 DAS interrogators、龙卷风多发区既有光纤、机器学习去噪及雷达/气象站/灾调校准，且可测试、低成本、可扩展。硬约束无违反。按评分要点：新颖性 **4/4**，可行性 **3/3**，流畅性 ** | O36: 2026-10-23 | P36: 自动写入 | Q36: 1422 | R36: 1398 | S36: 0.0024 | T36: 1742 | U36: 2350 | W36: 6.49
B37: R0033 | C37: M01 | D37: =IF($C37="","",IFERROR(VLOOKUP($C37,模型信息!$B$5:$C$24,2,0),"未登记")) -> DeepSeek-V4-Flash | E37: CR13 | F37: =IF($E37="","",IFERROR(VLOOKUP($E37,题目信息!$B$5:$C$253,2,0),"未登记")) -> 创造力 | G37: 1 | H37: **Idea:** Jointly analyze pulsar-timing-array gravitational-wave background anisotropies and Planck CMB maps to test whether the hot Big Bang was preceded by a brief matter-dominated reheating phase. Such a phase would imprint a characteristic quadrupole in the nanohertz background and a correlated large-scale CMB power deficit. **Novelty:** Existing studies treat these datasets separately; their cross-correlation has not been used as a model-independent probe of pre-Big Bang expansion. **Feasibility:** NANOGrav/EPTA data already constrain the isotropic background, SKA will improve anisotropy sensitivity, and Planck maps are public. The analysis needs only Bayesian cross-spectral pipelines, not new hardware. | I37: =IF($E37="","",IFERROR(VLOOKUP($E37,题目信息!$B$5:$J$253,9,0),"")) -> 无固定答案（官方LLM评审） | J37: 0 | K37: =IF($E37="","",IFERROR(VLOOKUP($E37,题目信息!$B$5:$L$253,11,0),10)) -> 10 | L37: =IF(OR($J37="",$K37=""),"",$J37/$K37) -> 0 | M37: LLM评审 | N37: 评审调用失败: 调用失败(重试2次): <urlopen error _ssl.c:1015: The handshake operation timed out> | O37: 2026-10-23 | P37: 自动写入 | Q37: 1423 | R37: 1938 | S37: 0.0032 | W37: 13.14
B38: R0034 | C38: M01 | D38: =IF($C38="","",IFERROR(VLOOKUP($C38,模型信息!$B$5:$C$24,2,0),"未登记")) -> DeepSeek-V4-Flash | E38: CR14 | F38: =IF($E38="","",IFERROR(VLOOKUP($E38,题目信息!$B$5:$C$253,2,0),"未登记")) -> 创造力 | G38: 1 | H38: **Idea:** Engineer a gut-colonizing probiotic biosensor that detects parasite-derived cysteine proteases and produces a colorimetric stool reporter, enabling non-invasive helminth surveillance. **Why novel:** Current parasite diagnostics rely on microscopy, antigen tests, or DNA, which need sampling and lab infrastructure. A living in-gut sensor links parasite-specific enzymatic activity to a visible output and could distinguish active infection from residual DNA. **Why feasible:** Well-characterized *E. coli* Nissl 1917 and *Lactobacillus* chassis exist; protease-responsive promoters can be built from known cleavage sites; helminth proteases are abundant in stool. Proof-of-concept would use *Trichuris muris* or *Heligmosomoides polygyrus* in mice, engineered strains with a protease sensor, and stool color readout. Specificity can be tuned with protease inhibitors and negative controls; biosafety can include kill switches. The project fits standard microbiology, synthetic biology, and parasitology labs within 18–24 months. | I38: =IF($E38="","",IFERROR(VLOOKUP($E38,题目信息!$B$5:$J$253,9,0),"")) -> 无固定答案（官方LLM评审） | J38: 9 | K38: =IF($E38="","",IFERROR(VLOOKUP($E38,题目信息!$B$5:$L$253,11,0),10)) -> 10 | L38: =IF(OR($J38="",$K38=""),"",$J38/$K38) -> 0.9 | M38: LLM评审 | N38: 分析：要求均满足：用英文提出一个与 parasites 相关的新颖可行研究想法；明确陈述了 idea、novelty 和 feasibility；全文约 **133 词**，未超 **150 词**；无格式或禁用词问题。评分要点方面：新颖性较强，将工程益生菌体内生物传感器用于寄生虫蛋白酶检测并产生粪便显色报告，区别于显微、抗原和 DNA 检测，可得 **4/4** 或接近满分；可行性有合理依据，包括已知底盘、蛋白酶响应启动子、小鼠模型和生物安全开关，但体内信号强度、粪便背景干扰、宿主蛋白酶交叉反应及定植控制仍有挑战，略扣分，约 **2.5/3**；流畅性清晰，结构完整，表达自然，可得 **3/ | O38: 2026-10-23 | P38: 自动写入 | Q38: 1421 | R38: 1945 | S38: 0.0032 | T38: 1789 | U38: 2158 | W38: 11.04
B39: R0035 | C39: M01 | D39: =IF($C39="","",IFERROR(VLOOKUP($C39,模型信息!$B$5:$C$24,2,0),"未登记")) -> DeepSeek-V4-Flash | E39: CR15 | F39: =IF($E39="","",IFERROR(VLOOKUP($E39,题目信息!$B$5:$C$253,2,0),"未登记")) -> 创造力 | G39: 1 | H39: **Idea:** A “Heliocentric Ranging Array” using existing deep-space spacecraft—Voyager, New Horizons, Juno, BepiColombo—as free test masses, cross-correlating their radio-ranging residuals to search for nanohertz gravitational waves and anomalous solar-system accelerations. **Novelty:** It converts operational navigation links into a solar-system-scale detector, complementing pulsar timing and laboratory interferometers at unexplored baselines and frequencies. **Feasibility:** Doppler and ranging data already exist; the project requires archival reprocessing, improved covariance models for solar plasma and asteroid perturbations, and coordinated observing windows—no new spacecraft. A two-spacecraft pilot could constrain acceleration noise within a year. | I39: =IF($E39="","",IFERROR(VLOOKUP($E39,题目信息!$B$5:$J$253,9,0),"")) -> 无固定答案（官方LLM评审） | J39: 8 | K39: =IF($E39="","",IFERROR(VLOOKUP($E39,题目信息!$B$5:$L$253,11,0),10)) -> 10 | L39: =IF(OR($J39="",$K39=""),"",$J39/$K39) -> 0.8 | M39: LLM评审 | N39: 分析：题目要求用英文提出一个与“solar system”相关、新颖且可行的科研想法，并在150词内说明想法、新颖性和可行性。模型回答包含Idea、Novelty、Feasibility三部分，关键词明确，英文表达流畅，字数约100词，未超限，格式无硬伤。新颖性方面，将现有深空探测器作为测距阵列、交叉相关无线电测距残差以搜寻纳赫兹引力波和异常太阳系加速度，具有一定创意，但与已有航天器多普勒测距探引力波研究有重叠，给3/4。可行性方面，利用存档数据、无需新航天器是优点，但“free test masses”表述不严谨，纳赫兹频段与太阳系尺度基线及“一年双航天器试点”的匹配偏乐观，等离子体、时钟噪 | O39: 2026-10-23 | P39: 自动写入 | Q39: 1422 | R39: 1944 | S39: 0.0032 | T39: 1727 | U39: 3001 | W39: 12.15
B40: R0036 | C40: M01 | D40: =IF($C40="","",IFERROR(VLOOKUP($C40,模型信息!$B$5:$C$24,2,0),"未登记")) -> DeepSeek-V4-Flash | E40: CR16 | F40: =IF($E40="","",IFERROR(VLOOKUP($E40,题目信息!$B$5:$C$253,2,0),"未登记")) -> 创造力 | G40: 1 | H40: **Idea:** Develop a wearable paper-microfluidic sampling patch coupled to portable ion-mobility mass spectrometry for noninvasive, time-resolved mapping of sweat metabolites during exercise. **Novelty:** It combines low-cost wearable sampling with isomer-resolved mass spectrometry, enabling longitudinal metabolic monitoring outside centralized laboratories and without chromatographic separation. **Feasibility:** Paper microfluidics, ambient ionization, and portable ion-mobility MS are established technologies. A proof-of-concept could target lactate, glucose, and amino acids, with validation against conventional LC-MS. The patch can preconcentrate analytes and provide time-stamped samples, making the approach practical for sports science and clinical metabolic monitoring. | I40: =IF($E40="","",IFERROR(VLOOKUP($E40,题目信息!$B$5:$J$253,9,0),"")) -> 无固定答案（官方LLM评审） | J40: 9 | K40: =IF($E40="","",IFERROR(VLOOKUP($E40,题目信息!$B$5:$L$253,11,0),10)) -> 10 | L40: =IF(OR($J40="",$K40=""),"",$J40/$K40) -> 0.9 | M40: LLM评审 | N40: 分析：英文作答，总词数约90词，满足150词以内；明确给出Idea、Novelty、Feasibility三部分，紧扣mass spectrometry。新颖性方面，将可穿戴纸微流控采样与便携离子迁移质谱结合，用于汗液代谢物时间分辨和异构体分辨监测，具有集成创新，但组件多为已有技术，核心突破有限，扣1分。可行性方面，纸微流控、环境电离、便携离子迁移MS均有技术基础，并给出乳酸/葡萄糖/氨基酸概念验证及LC-MS验证路径，较充分，给3分。流畅性方面，结构清晰、术语准确、表达简洁，给3分。未违反字数、语言、格式等硬约束。 得分：9 | O40: 2026-10-23 | P40: 自动写入 | Q40: 1422 | R40: 1720 | S40: 0.0029 | T40: 1715 | U40: 2132 | W40: 10.63
B41: R0037 | C41: M01 | D41: =IF($C41="","",IFERROR(VLOOKUP($C41,模型信息!$B$5:$C$24,2,0),"未登记")) -> DeepSeek-V4-Flash | E41: CR17 | F41: =IF($E41="","",IFERROR(VLOOKUP($E41,题目信息!$B$5:$C$253,2,0),"未登记")) -> 创造力 | G41: 1 | H41: **Idea:** A randomized pilot testing a wearable-driven just-in-time adaptive intervention for early detection of hypomanic transition in bipolar disorder. Participants wear a smartwatch collecting sleep, activity, and heart-rate variability; a weekly brief ecological momentary assessment anchors mood ratings. A composite “circadian instability index” triggers personalized prompts to increase sleep regularity and contact their clinician. **Novelty:** It prospectively combines passive circadian/autonomic sensing with a targeted, low-burden intervention, rather than retrospective prediction or generic mood monitoring. **Feasibility:** Consumer wearables, validated mood scales, and existing telepsychiatry workflows enable an 8-week, 40-patient pilot. Primary outcomes are recruitment/retention, trigger accuracy, and acceptability; secondary outcomes include time to clinician contact and mood episode signal detection. IRB oversight and data-security safeguards are straightforward. This could inform larger psychiatric prevention trials. | I41: =IF($E41="","",IFERROR(VLOOKUP($E41,题目信息!$B$5:$J$253,9,0),"")) -> 无固定答案（官方LLM评审） | J41: 9 | K41: =IF($E41="","",IFERROR(VLOOKUP($E41,题目信息!$B$5:$L$253,11,0),10)) -> 10 | L41: =IF(OR($J41="",$K41=""),"",$J41/$K41) -> 0.9 | M41: LLM评审 | N41: 分析：要求为基于 keyword “psychiatry” 提出一个新颖且可行的科研设想，英文、150 词内，并说明 idea、novelty、feasibility。模型回答主题为双相障碍低躁狂转换的可穿戴 JITAI 早期检测与干预，属于精神病学范畴；明确分三段给出 Idea、Novelty、Feasibility；英文表达流畅清晰。字数约 **120 词**，符合 150 词限制；无格式或禁用词硬性违规。评分要点核对：新颖性方面，将被动昼夜节律/自主神经传感与 JITAI 结合有一定新意，但可穿戴监测双相障碍和 JITAI 均已有相关研究，属于较强增量创新而非全新范式，给 **3/4** | O41: 2026-10-23 | P41: 自动写入 | Q41: 1421 | R41: 1451 | S41: 0.0025 | T41: 1760 | U41: 2332 | W41: 11.25
B42: R0038 | C42: M01 | D42: =IF($C42="","",IFERROR(VLOOKUP($C42,模型信息!$B$5:$C$24,2,0),"未登记")) -> DeepSeek-V4-Flash | E42: CR18 | F42: =IF($E42="","",IFERROR(VLOOKUP($E42,题目信息!$B$5:$C$253,2,0),"未登记")) -> 创造力 | G42: 1 | H42: **Idea:** Repurpose existing submarine telecommunication cables as dense tsunami sensors using distributed acoustic sensing (DAS). By interrogating spare dark fibers from landing stations, detect seafloor pressure and acoustic-gravity waves generated by tsunami-generating earthquakes, then invert these signals with physics-informed machine learning to estimate source location and offshore wave height. **Novelty:** This converts thousands of kilometers of existing telecom infrastructure into a low-cost, near-source seafloor observatory, filling critical gaps in open-ocean tsunami monitoring without deploying new pressure sensors. **Feasibility:** Recent DAS trials have already sensed seismic and oceanographic signals over >100 km cable spans. The approach can be calibrated against co-located pressure gauges and validated with known tsunami events and numerical wave models. Initial deployment at one or two cable landing stations is realistic within existing research budgets. | I42: =IF($E42="","",IFERROR(VLOOKUP($E42,题目信息!$B$5:$J$253,9,0),"")) -> 无固定答案（官方LLM评审） | J42: 8 | K42: =IF($E42="","",IFERROR(VLOOKUP($E42,题目信息!$B$5:$L$253,11,0),10)) -> 10 | L42: =IF(OR($J42="",$K42=""),"",$J42/$K42) -> 0.8 | M42: LLM评审 | N42: 分析： 1. 关键词与语言：围绕 tsunamis 展开，全英文作答，符合要求。 2. 内容完整性：分别用 **Idea / Novelty / Feasibility** 三个小标题明确陈述了研究设想、新颖性理由与可行性依据，结构完整。 3. 字数硬约束：正文约 **125 词**，未超过 150 词上限，合格。 4. 新颖性（4分）：将海底通信光缆与 DAS 结合用于海啸近场监测，思路清晰且有应用价值；但“利用既有光缆/DAS 探测海啸、地震海洋声波”已是近年实际推进的研究方向（已有 DAS 探测海洋重力波与海啸信号的公开试验），属于对现有路线的组合与工程化延伸，原创突破性有限，给 **3 | O42: 2026-10-23 | P42: 自动写入 | Q42: 1423 | R42: 1430 | S42: 0.0025 | T42: 1751 | U42: 1981 | W42: 26.38
B43: R0039 | C43: M01 | D43: =IF($C43="","",IFERROR(VLOOKUP($C43,模型信息!$B$5:$C$24,2,0),"未登记")) -> DeepSeek-V4-Flash | E43: CR19 | F43: =IF($E43="","",IFERROR(VLOOKUP($E43,题目信息!$B$5:$C$253,2,0),"未登记")) -> 创造力 | G43: 1 | H43: **Idea:** Evolve a synthetic three-species bacterial community in a microfluidic antibiotic-gradient device, using CRISPR lineage barcodes and labeled mobile genetic elements, to test whether horizontal gene transfer enables “evolutionary rescue” that single-species populations cannot achieve. **Novelty:** It directly quantifies how gene flow through structured spatial gradients reshapes adaptive trajectories and rescue probability, linking community-level evolution to mobile-element dynamics. **Feasibility:** Microfluidic gradient systems, barcoded bacterial strains, and metagenomic sequencing are well established; the experiment is achievable within months and yields trackable, replicated evolutionary outcomes. | I43: =IF($E43="","",IFERROR(VLOOKUP($E43,题目信息!$B$5:$J$253,9,0),"")) -> 无固定答案（官方LLM评审） | J43: 9 | K43: =IF($E43="","",IFERROR(VLOOKUP($E43,题目信息!$B$5:$L$253,11,0),10)) -> 10 | L43: =IF(OR($J43="",$K43=""),"",$J43/$K43) -> 0.9 | M43: LLM评审 | N43: 分析：要求核对：①英文撰写——满足；②150词以内——满足，正文约83词；③围绕关键词“evolution”提出一个新颖且可行的研究想法——满足；④明确说明想法、新颖性、可行性——满足。评分要点核对：新颖性方面，将合成三物种细菌群落、微流控抗生素梯度、CRISPR谱系条形码、移动遗传元件与“进化拯救”结合，具有明确交叉创新性，但更多是成熟技术/概念的集成创新，非全新范式，给约3.5/4；可行性方面，微流控梯度、条形码菌株和宏基因组测序均较成熟，实验周期与可追踪结果合理，但三物种稳定共培养、移动元件标记及拯救概率统计仍需优化，给约2.8/3；流畅性方面，结构清晰、术语准确、英文表达自然，给3/3 | O43: 2026-10-23 | P43: 自动写入 | Q43: 1421 | R43: 1445 | S43: 0.0025 | T43: 1704 | U43: 2423 | W43: 7.07
B44: R0040 | C44: M01 | D44: =IF($C44="","",IFERROR(VLOOKUP($C44,模型信息!$B$5:$C$24,2,0),"未登记")) -> DeepSeek-V4-Flash | E44: CR20 | F44: =IF($E44="","",IFERROR(VLOOKUP($E44,题目信息!$B$5:$C$253,2,0),"未登记")) -> 创造力 | G44: 1 | H44: **Idea:** A cross-mission data-assimilation study to reconstruct the three-dimensional atmospheric circulation of Jupiter and Saturn from archival radio-occultation profiles. Ingest Voyager, Cassini, and Juno occultation temperature-pressure profiles into a global primitive-equation model, then test whether retrieved vertical wind shear explains equatorial-jet stability and storm lifetimes. **Why novel:** Previous occultation analyses are mostly static, single-mission snapshots; this treats them as a coherent multi-decadal dataset and explicitly retrieves vertical wind structure. **Why feasible:** All input data are public, dynamical models are mature, and no new instrumentation is required. Independent cloud-tracked winds and Juno gravity harmonics can validate results. Expected output: a reproducible atlas of giant-planet wind shear and a direct test of jet-coherence theories. | I44: =IF($E44="","",IFERROR(VLOOKUP($E44,题目信息!$B$5:$J$253,9,0),"")) -> 无固定答案（官方LLM评审） | J44: 10 | K44: =IF($E44="","",IFERROR(VLOOKUP($E44,题目信息!$B$5:$L$253,11,0),10)) -> 10 | L44: =IF(OR($J44="",$K44=""),"",$J44/$K44) -> 1 | M44: LLM评审 | N44: 分析：要求逐条核对：①围绕关键词 planets，回答以木星、土星等巨行星为对象，符合；②用英文撰写，符合；③提出一个新颖且可行的科研想法，回答明确提出跨任务数据同化重建三维大气环流，符合；④说明 idea、novelty、feasibility，三部分齐全，符合；⑤字数约 **112** 词，低于 **150** 词，符合；⑥格式与硬约束未发现违规。评分要点：新颖性方面，将多任务掩星资料整合为多年代际数据集并反演垂直风切变，具有较好新意，给 **4/4**；可行性方面，公开数据、成熟动力模型、无需新仪器且有独立验证手段，论证充分，给 **3/3**；流畅性方面，结构清晰、表达准确，给 **3 | O44: 2026-10-23 | P44: 自动写入 | Q44: 1421 | R44: 1948 | S44: 0.0032 | T44: 1745 | U44: 2047 | W44: 11.83
B45: R0041 | C45: M01 | D45: =IF($C45="","",IFERROR(VLOOKUP($C45,模型信息!$B$5:$C$24,2,0),"未登记")) -> DeepSeek-V4-Flash | E45: CU01 | F45: =IF($E45="","",IFERROR(VLOOKUP($E45,题目信息!$B$5:$C$253,2,0),"未登记")) -> 上下文利用 | G45: 1 | H45: 段落6 | I45: =IF($E45="","",IFERROR(VLOOKUP($E45,题目信息!$B$5:$J$253,9,0),"")) -> 段落6 | J45: 10 | K45: =IF($E45="","",IFERROR(VLOOKUP($E45,题目信息!$B$5:$L$253,11,0),10)) -> 10 | L45: =IF(OR($J45="",$K45=""),"",$J45/$K45) -> 1 | M45: 规则自动判分 | N45: 命中 2/2: ['段落6', '6'] | O45: 2026-10-23 | P45: 自动写入 | Q45: 6120 | R45: 1117 | S45: 0.0037 | W45: 4.96
B46: R0042 | C46: M01 | D46: =IF($C46="","",IFERROR(VLOOKUP($C46,模型信息!$B$5:$C$24,2,0),"未登记")) -> DeepSeek-V4-Flash | E46: CU02 | F46: =IF($E46="","",IFERROR(VLOOKUP($E46,题目信息!$B$5:$C$253,2,0),"未登记")) -> 上下文利用 | G46: 1 | H46: 段落2 | I46: =IF($E46="","",IFERROR(VLOOKUP($E46,题目信息!$B$5:$J$253,9,0),"")) -> 段落2 | J46: 10 | K46: =IF($E46="","",IFERROR(VLOOKUP($E46,题目信息!$B$5:$L$253,11,0),10)) -> 10 | L46: =IF(OR($J46="",$K46=""),"",$J46/$K46) -> 1 | M46: 规则自动判分 | N46: 命中 2/2: ['段落2', '2'] | O46: 2026-10-23 | P46: 自动写入 | Q46: 6126 | R46: 1089 | S46: 0.0036 | W46: 5.18
B47: R0043 | C47: M01 | D47: =IF($C47="","",IFERROR(VLOOKUP($C47,模型信息!$B$5:$C$24,2,0),"未登记")) -> DeepSeek-V4-Flash | E47: CU03 | F47: =IF($E47="","",IFERROR(VLOOKUP($E47,题目信息!$B$5:$C$253,2,0),"未登记")) -> 上下文利用 | G47: 1 | H47: 段落13 | I47: =IF($E47="","",IFERROR(VLOOKUP($E47,题目信息!$B$5:$J$253,9,0),"")) -> 段落13 | J47: 10 | K47: =IF($E47="","",IFERROR(VLOOKUP($E47,题目信息!$B$5:$L$253,11,0),10)) -> 10 | L47: =IF(OR($J47="",$K47=""),"",$J47/$K47) -> 1 | M47: 规则自动判分 | N47: 命中 2/2: ['段落13', '13'] | O47: 2026-10-23 | P47: 自动写入 | Q47: 5213 | R47: 1070 | S47: 0.0033 | W47: 4.56
B48: R0044 | C48: M01 | D48: =IF($C48="","",IFERROR(VLOOKUP($C48,模型信息!$B$5:$C$24,2,0),"未登记")) -> DeepSeek-V4-Flash | E48: CU04 | F48: =IF($E48="","",IFERROR(VLOOKUP($E48,题目信息!$B$5:$C$253,2,0),"未登记")) -> 上下文利用 | G48: 1 | H48: 段落12 | I48: =IF($E48="","",IFERROR(VLOOKUP($E48,题目信息!$B$5:$J$253,9,0),"")) -> 段落12 | J48: 10 | K48: =IF($E48="","",IFERROR(VLOOKUP($E48,题目信息!$B$5:$L$253,11,0),10)) -> 10 | L48: =IF(OR($J48="",$K48=""),"",$J48/$K48) -> 1 | M48: 规则自动判分 | N48: 命中 2/2: ['段落12', '12'] | O48: 2026-10-23 | P48: 自动写入 | Q48: 5858 | R48: 1074 | S48: 0.0035 | W48: 14.38
B49: R0045 | C49: M01 | D49: =IF($C49="","",IFERROR(VLOOKUP($C49,模型信息!$B$5:$C$24,2,0),"未登记")) -> DeepSeek-V4-Flash | E49: CU05 | F49: =IF($E49="","",IFERROR(VLOOKUP($E49,题目信息!$B$5:$C$253,2,0),"未登记")) -> 上下文利用 | G49: 1 | H49: 段落21 | I49: =IF($E49="","",IFERROR(VLOOKUP($E49,题目信息!$B$5:$J$253,9,0),"")) -> 段落21 | J49: 10 | K49: =IF($E49="","",IFERROR(VLOOKUP($E49,题目信息!$B$5:$L$253,11,0),10)) -> 10 | L49: =IF(OR($J49="",$K49=""),"",$J49/$K49) -> 1 | M49: 规则自动判分 | N49: 命中 2/2: ['段落21', '21'] | O49: 2026-10-23 | P49: 自动写入 | Q49: 5248 | R49: 1092 | S49: 0.0033 | W49: 4.8
B50: R0046 | C50: M01 | D50: =IF($C50="","",IFERROR(VLOOKUP($C50,模型信息!$B$5:$C$24,2,0),"未登记")) -> DeepSeek-V4-Flash | E50: CU06 | F50: =IF($E50="","",IFERROR(VLOOKUP($E50,题目信息!$B$5:$C$253,2,0),"未登记")) -> 上下文利用 | G50: 1 | H50: 段落14 | I50: =IF($E50="","",IFERROR(VLOOKUP($E50,题目信息!$B$5:$J$253,9,0),"")) -> 段落14 | J50: 10 | K50: =IF($E50="","",IFERROR(VLOOKUP($E50,题目信息!$B$5:$L$253,11,0),10)) -> 10 | L50: =IF(OR($J50="",$K50=""),"",$J50/$K50) -> 1 | M50: 规则自动判分 | N50: 命中 2/2: ['段落14', '14'] | O50: 2026-10-23 | P50: 自动写入 | Q50: 5453 | R50: 1082 | S50: 0.0034 | W50: 6.88
B51: R0047 | C51: M01 | D51: =IF($C51="","",IFERROR(VLOOKUP($C51,模型信息!$B$5:$C$24,2,0),"未登记")) -> DeepSeek-V4-Flash | E51: CU07 | F51: =IF($E51="","",IFERROR(VLOOKUP($E51,题目信息!$B$5:$C$253,2,0),"未登记")) -> 上下文利用 | G51: 1 | H51: 段落5 | I51: =IF($E51="","",IFERROR(VLOOKUP($E51,题目信息!$B$5:$J$253,9,0),"")) -> 段落5 | J51: 10 | K51: =IF($E51="","",IFERROR(VLOOKUP($E51,题目信息!$B$5:$L$253,11,0),10)) -> 10 | L51: =IF(OR($J51="",$K51=""),"",$J51/$K51) -> 1 | M51: 规则自动判分 | N51: 命中 2/2: ['段落5', '5'] | O51: 2026-10-23 | P51: 自动写入 | Q51: 6833 | R51: 1061 | S51: 0.0038 | W51: 5.94
B52: R0048 | C52: M01 | D52: =IF($C52="","",IFERROR(VLOOKUP($C52,模型信息!$B$5:$C$24,2,0),"未登记")) -> DeepSeek-V4-Flash | E52: CU08 | F52: =IF($E52="","",IFERROR(VLOOKUP($E52,题目信息!$B$5:$C$253,2,0),"未登记")) -> 上下文利用 | G52: 1 | H52: 12 | I52: =IF($E52="","",IFERROR(VLOOKUP($E52,题目信息!$B$5:$J$253,9,0),"")) -> Paragraph 12 | J52: 5 | K52: =IF($E52="","",IFERROR(VLOOKUP($E52,题目信息!$B$5:$L$253,11,0),10)) -> 10 | L52: =IF(OR($J52="",$K52=""),"",$J52/$K52) -> 0.5 | M52: 规则自动判分 | N52: 命中 1/2: ['Paragraph 12', '12'] | O52: 2026-10-23 | P52: 自动写入 | Q52: 12358 | R52: 1099 | S52: 0.0058 | W52: 5.72
B53: R0049 | C53: M01 | D53: =IF($C53="","",IFERROR(VLOOKUP($C53,模型信息!$B$5:$C$24,2,0),"未登记")) -> DeepSeek-V4-Flash | E53: CU09 | F53: =IF($E53="","",IFERROR(VLOOKUP($E53,题目信息!$B$5:$C$253,2,0),"未登记")) -> 上下文利用 | G53: 1 | H53: Paragraph 8 | I53: =IF($E53="","",IFERROR(VLOOKUP($E53,题目信息!$B$5:$J$253,9,0),"")) -> Paragraph 8 | J53: 10 | K53: =IF($E53="","",IFERROR(VLOOKUP($E53,题目信息!$B$5:$L$253,11,0),10)) -> 10 | L53: =IF(OR($J53="",$K53=""),"",$J53/$K53) -> 1 | M53: 规则自动判分 | N53: 命中 2/2: ['Paragraph 8', '8'] | O53: 2026-10-23 | P53: 自动写入 | Q53: 14795 | R53: 1066 | S53: 0.0066 | W53: 5.26
B54: R0050 | C54: M01 | D54: =IF($C54="","",IFERROR(VLOOKUP($C54,模型信息!$B$5:$C$24,2,0),"未登记")) -> DeepSeek-V4-Flash | E54: CU10 | F54: =IF($E54="","",IFERROR(VLOOKUP($E54,题目信息!$B$5:$C$253,2,0),"未登记")) -> 上下文利用 | G54: 1 | H54: Paragraph 15 | I54: =IF($E54="","",IFERROR(VLOOKUP($E54,题目信息!$B$5:$J$253,9,0),"")) -> Paragraph 15 | J54: 10 | K54: =IF($E54="","",IFERROR(VLOOKUP($E54,题目信息!$B$5:$L$253,11,0),10)) -> 10 | L54: =IF(OR($J54="",$K54=""),"",$J54/$K54) -> 1 | M54: 规则自动判分 | N54: 命中 2/2: ['Paragraph 15', '15'] | O54: 2026-10-23 | P54: 自动写入 | Q54: 13544 | R54: 1088 | S54: 0.0062 | W54: 4.95
B55: R0051 | C55: M01 | D55: =IF($C55="","",IFERROR(VLOOKUP($C55,模型信息!$B$5:$C$24,2,0),"未登记")) -> DeepSeek-V4-Flash | E55: CU11 | F55: =IF($E55="","",IFERROR(VLOOKUP($E55,题目信息!$B$5:$C$253,2,0),"未登记")) -> 上下文利用 | G55: 1 | H55: Paragraph 6 | I55: =IF($E55="","",IFERROR(VLOOKUP($E55,题目信息!$B$5:$J$253,9,0),"")) -> Paragraph 6 | J55: 10 | K55: =IF($E55="","",IFERROR(VLOOKUP($E55,题目信息!$B$5:$L$253,11,0),10)) -> 10 | L55: =IF(OR($J55="",$K55=""),"",$J55/$K55) -> 1 | M55: 规则自动判分 | N55: 命中 2/2: ['Paragraph 6', '6'] | O55: 2026-10-23 | P55: 自动写入 | Q55: 12446 | R55: 1065 | S55: 0.0058 | W55: 4.19
B56: R0052 | C56: M01 | D56: =IF($C56="","",IFERROR(VLOOKUP($C56,模型信息!$B$5:$C$24,2,0),"未登记")) -> DeepSeek-V4-Flash | E56: CU12 | F56: =IF($E56="","",IFERROR(VLOOKUP($E56,题目信息!$B$5:$C$253,2,0),"未登记")) -> 上下文利用 | G56: 1 | H56: Paragraph 19 | I56: =IF($E56="","",IFERROR(VLOOKUP($E56,题目信息!$B$5:$J$253,9,0),"")) -> Paragraph 19 | J56: 10 | K56: =IF($E56="","",IFERROR(VLOOKUP($E56,题目信息!$B$5:$L$253,11,0),10)) -> 10 | L56: =IF(OR($J56="",$K56=""),"",$J56/$K56) -> 1 | M56: 规则自动判分 | N56: 命中 2/2: ['Paragraph 19', '19'] | O56: 2026-10-23 | P56: 自动写入 | Q56: 14856 | R56: 1070 | S56: 0.0066 | W56: 4.06
... B136: R0132 | C136: M01 | D136: =IF($C136="","",IFERROR(VLOOKUP($C136,模型信息!$B$5:$C$24,2,0),"未登记")) -> DeepSeek-V4-Flash | E136: INS12 | F136: =IF($E136="","",IFERROR(VLOOKUP($E136,题目信息!$B$5:$C$253,2,0),"未登记")) -> 指令遵循 | G136: 1 | H136: ProGRP and NSE can rise without a PET-detected tumor because they are nonspecific: renal impairment, hemolysis, benign lung disease, and other conditions raise them. PET also misses small or low-avidity neuroendocrine lesions. Assay variability matters. Repeat testing, check renal function and hemolysis, and interpret with clinical context rather than assuming malignancy. | I136: =IF($E136="","",IFERROR(VLOOKUP($E136,题目信息!$B$5:$J$253,9,0),"")) -> 约束: count:word_count_range | J136: 10 | K136: =IF($E136="","",IFERROR(VLOOKUP($E136,题目信息!$B$5:$L$253,11,0),10)) -> 10 | L136: =IF(OR($J136="",$K136=""),"",$J136/$K136) -> 1 | M136: 规则自动判分 | N136: 官方校验通过 1/1 | O136: 2026-10-23 | P136: 自动写入 | Q136: 1408 | R136: 1461 | S136: 0.0025 | W136: 5.51
B137: R0133 | C137: M01 | D137: =IF($C137="","",IFERROR(VLOOKUP($C137,模型信息!$B$5:$C$24,2,0),"未登记")) -> DeepSeek-V4-Flash | E137: INS13 | F137: =IF($E137="","",IFERROR(VLOOKUP($E137,题目信息!$B$5:$C$253,2,0),"未登记")) -> 指令遵循 | G137: 1 | I137: =IF($E137="","",IFERROR(VLOOKUP($E137,题目信息!$B$5:$J$253,9,0),"")) -> 约束: format:quotes | J137: 0 | K137: =IF($E137="","",IFERROR(VLOOKUP($E137,题目信息!$B$5:$L$253,11,0),10)) -> 10 | L137: =IF(OR($J137="",$K137=""),"",$J137/$K137) -> 0 | M137: 规则自动判分 | N137: 模型无有效回答 | O137: 2026-10-23 | P137: 自动写入·调用失败
B138: R0134 | C138: M01 | D138: =IF($C138="","",IFERROR(VLOOKUP($C138,模型信息!$B$5:$C$24,2,0),"未登记")) -> DeepSeek-V4-Flash | E138: INS14 | F138: =IF($E138="","",IFERROR(VLOOKUP($E138,题目信息!$B$5:$C$253,2,0),"未登记")) -> 指令遵循 | G138: 1 | H138: Delayed obliteration means the artery is **not blocked at the moment of injury**; instead, obstruction develops over hours or days as secondary processes evolve. These mechanisms are **not mutually exclusive**, and they can combine. - **Traumatic thrombosis:** A roughened or torn intima exposes subendothelial collagen, so platelets adhere and aggregate, fibrin forms, and red cells become trapped. The thrombus can grow, propagate, and narrow the lumen progressively. This is clinically important, **for** an initially patent artery may later thrombose. - **Subintimal dissection and intimal flap:** A tear can create a loose distal intimal edge. Blood flow may lift that edge, enter the subintimal plane, and create a false lumen. The flap then bulges into the true lumen and can act like a valve, occluding flow intermittently **or** permanently. - **Intramural hematoma:** Blood can collect within the arterial wall, often from vasa vasorum rupture or from a tear, **and** the hematoma expands. Even though the inner and outer coats may remain intact, the hematoma can compress the true lumen from outside inward. A normal early pulse does not exclude injury, **nor** does it guarantee continued patency. The vessel may look adequate initially, **yet** the lumen can occlude later as thrombus propagates, a flap enlarges, or a hematoma expands. **So** serial vascular exams and imaging are important when arterial injury is suspected. **But** the exact risk and management depend on the vessel, injury grade, and clinical findings. | I138: =IF($E138="","",IFERROR(VLOOKUP($E138,题目信息!$B$5:$J$253,9,0),"")) -> 约束: count:conjunctions | J138: 10 | K138: =IF($E138="","",IFERROR(VLOOKUP($E138,题目信息!$B$5:$L$253,11,0),10)) -> 10 | L138: =IF(OR($J138="",$K138=""),"",$J138/$K138) -> 1 | M138: 规则自动判分 | N138: 官方校验通过 1/1 | O138: 2026-10-23 | P138: 自动写入 | Q138: 1505 | R138: 2519 | S138: 0.004 | W138: 14.98
B139: R0135 | C139: M01 | D139: =IF($C139="","",IFERROR(VLOOKUP($C139,模型信息!$B$5:$C$24,2,0),"未登记")) -> DeepSeek-V4-Flash | E139: INS15 | F139: =IF($E139="","",IFERROR(VLOOKUP($E139,题目信息!$B$5:$C$253,2,0),"未登记")) -> 指令遵循 | G139: 1 | H139: Yes, I understand. | I139: =IF($E139="","",IFERROR(VLOOKUP($E139,题目信息!$B$5:$J$253,9,0),"")) -> 约束: format:newline | J139: 10 | K139: =IF($E139="","",IFERROR(VLOOKUP($E139,题目信息!$B$5:$L$253,11,0),10)) -> 10 | L139: =IF(OR($J139="",$K139=""),"",$J139/$K139) -> 1 | M139: 规则自动判分 | N139: 官方校验通过 1/1 | O139: 2026-10-23 | P139: 自动写入 | Q139: 1493 | R139: 1191 | S139: 0.0022 | W139: 3.36
B140: R0136 | C140: M01 | D140: =IF($C140="","",IFERROR(VLOOKUP($C140,模型信息!$B$5:$C$24,2,0),"未登记")) -> DeepSeek-V4-Flash | E140: INS16 | F140: =IF($E140="","",IFERROR(VLOOKUP($E140,题目信息!$B$5:$C$253,2,0),"未登记")) -> 指令遵循 | G140: 1 | H140: Yes, plausibly—up to a threshold. Frequent moderate shocks can build preparedness, social trust, and adaptive institutions; the effect is strongest when societies get **1** recovery period between crises and when no more than **2** major shocks overlap. Beyond that, hardship tends to deplete resources and trust rather than strengthen them. | I140: =IF($E140="","",IFERROR(VLOOKUP($E140,题目信息!$B$5:$J$253,9,0),"")) -> 约束: count:numbers | J140: 10 | K140: =IF($E140="","",IFERROR(VLOOKUP($E140,题目信息!$B$5:$L$253,11,0),10)) -> 10 | L140: =IF(OR($J140="",$K140=""),"",$J140/$K140) -> 1 | M140: 规则自动判分 | N140: 官方校验通过 1/1 | O140: 2026-10-23 | P140: 自动写入 | Q140: 1400 | R140: 1482 | S140: 0.0025 | W140: 6.84
B141: R0137 | C141: M01 | D141: =IF($C141="","",IFERROR(VLOOKUP($C141,模型信息!$B$5:$C$24,2,0),"未登记")) -> DeepSeek-V4-Flash | E141: INS17 | F141: =IF($E141="","",IFERROR(VLOOKUP($E141,题目信息!$B$5:$C$253,2,0),"未登记")) -> 指令遵循 | G141: 1 | H141: INT. LAB — NIGHT A brass clock ticks. Rain drums. Cold Dr. Voss watches vacuum tubes glow. Voss flips switch. Nothing. Again. VOSS: A tick. Static whispers. Somewhere, alternate molecules hesitate. One tube dies. Another burns gold. Reality yawns. History forks. At midnight transistor fails. MARA: Which reality wins? Voss shrugs. Ash curls. Both continue. | I141: =IF($E141="","",IFERROR(VLOOKUP($E141,题目信息!$B$5:$J$253,9,0),"")) -> 约束: words:no_consecutive | J141: 10 | K141: =IF($E141="","",IFERROR(VLOOKUP($E141,题目信息!$B$5:$L$253,11,0),10)) -> 10 | L141: =IF(OR($J141="",$K141=""),"",$J141/$K141) -> 1 | M141: 规则自动判分 | N141: 官方校验通过 1/1 | O141: 2026-10-23 | P141: 自动写入 | Q141: 1410 | R141: 4178 | S141: 0.0063 | W141: 26.64
B142: R0138 | C142: M01 | D142: =IF($C142="","",IFERROR(VLOOKUP($C142,模型信息!$B$5:$C$24,2,0),"未登记")) -> DeepSeek-V4-Flash | E142: INS18 | F142: =IF($E142="","",IFERROR(VLOOKUP($E142,题目信息!$B$5:$C$253,2,0),"未登记")) -> 指令遵循 | G142: 1 | H142: It means:<br> &nbsp;Archetypal structures are recurring story patterns—hero, shadow, death/rebirth, apocalypse, world-tree—that appear across myths and genres.<br> &nbsp;&nbsp;“Intuitively tapped” means an author absorbed those patterns from culture, genre, and emotional logic, not from a secret manual.<br> &nbsp;&nbsp;&nbsp;So a story can *resonate* with Kabbalah or Jungian archetypes without being consciously built as a Kabbalistic cipher.<br> &nbsp;&nbsp;&nbsp;&nbsp;With *Evangelion*, the religious/Kabbalistic imagery is real and deliberate in places, but often selective and atmospheric—not a complete decoding key.<br> &nbsp;&nbsp;&nbsp;&nbsp;&nbsp;Archetypal reading says: “This pattern feels deep and familiar.”<br> &nbsp;&nbsp;&nbsp;&nbsp;&nbsp;&nbsp;Esoteric-decoding reading says: “This detail maps onto a specific system.”<br> &nbsp;&nbsp;&nbsp;&nbsp;&nbsp;&nbsp;&nbsp;The first needs no secret code; the second needs evidence.<br> &nbsp;&nbsp;&nbsp;&nbsp;&nbsp;&nbsp;&nbsp;&nbsp;Both can be fun—but overfitting is the risk. | I142: =IF($E142="","",IFERROR(VLOOKUP($E142,题目信息!$B$5:$J$253,9,0),"")) -> 约束: format:line_indent | J142: 0 | K142: =IF($E142="","",IFERROR(VLOOKUP($E142,题目信息!$B$5:$L$253,11,0),10)) -> 10 | L142: =IF(OR($J142="",$K142=""),"",$J142/$K142) -> 0 | M142: 规则自动判分 | N142: 官方校验通过 0/1 | O142: 2026-10-23 | P142: 自动写入 | Q142: 1447 | R142: 3183 | S142: 0.0049 | W142: 19.38
B143: R0139 | C143: M01 | D143: =IF($C143="","",IFERROR(VLOOKUP($C143,模型信息!$B$5:$C$24,2,0),"未登记")) -> DeepSeek-V4-Flash | E143: INS19 | F143: =IF($E143="","",IFERROR(VLOOKUP($E143,题目信息!$B$5:$C$253,2,0),"未登记")) -> 指令遵循 | G143: 1 | H143: ## Word span Assuming **1-based word indexing** over the paper title: `Identifying(1) Candidate(2) Spaces(3) for(4) Advert(5) Implantation(6)` The inclusive span from index **3 to 6** is: > **Spaces for Advert Implantation** If you meant **0-based indexing**, index 6 does not exist in the title; the valid inclusive span from index 3 to the last word is **“for Advert Implantation.”** ## Context The paper *Identifying Candidate Spaces for Advert Implantation* addresses a practical advertising problem: given an image or visual scene, **where can an advertisement be inserted naturally without covering important content?** This matters for native advertising, image-based ad placement, AR overlays, e-commerce, and automated marketing systems. The goal is to identify “candidate spaces” — regions such as blank walls, sky, ground, or low-information background areas — while avoiding faces, text, main objects, and other salient content. ## Theory The core idea is to formulate candidate-space identification as a **visual recognition / segmentation or region-proposal problem**: - Extract visual features with a CNN backbone. - Detect or segment important objects and salient regions. - Score remaining regions by suitability for ad implantation. - Use annotations of acceptable/implantable regions as supervision. - Train with classification, bounding-box regression, and/or pixel-wise segmentation losses. - At inference, threshold candidate maps or proposals, apply non-maximum suppression, and rank regions. Conceptually, the model learns a function from image pixels/regions to a “safe-to-place-ad” score, balancing **semantic safety**, **visual saliency**, and **layout suitability**. ## Code The exact public code depends on the paper’s release, but a typical implementation would include: - **Dataset loader**: images plus masks or bounding boxes marking candidate/non-candidate spaces. - **Backbone**: ResNet/VGG or similar CNN feature extractor. - **Head**: segmentation head or region-proposal/object-detection head. - **Losses**: cross-entropy for candidate/non-candidate classification, box regression or mask loss. - **Training loop**: augmentation, optimizer, learning-rate schedule, validation by IoU/mAP. - **Inference**: generate candidate masks/boxes, threshold, suppress overlaps, rank, and output implantable regions. - **Evaluation**: precision/recall, IoU, mAP, and qualitative overlays. In short: the paper is about **automatically finding safe, visually plausible regions for ad insertion**, usually via a CNN-based detection or segmentation pipeline trained on annotated candidate-space data. | I143: =IF($E143="","",IFERROR(VLOOKUP($E143,题目信息!$B$5:$J$253,9,0),"")) -> 约束: repeat:repeat_span | J143: 0 | K143: =IF($E143="","",IFERROR(VLOOKUP($E143,题目信息!$B$5:$L$253,11,0),10)) -> 10 | L143: =IF(OR($J143="",$K143=""),"",$J143/$K143) -> 0 | M143: 规则自动判分 | N143: 官方校验通过 0/1 | O143: 2026-10-23 | P143: 自动写入 | Q143: 1428 | R143: 3316 | S143: 0.0051 | W143: 20.96
B144: R0140 | C144: M01 | D144: =IF($C144="","",IFERROR(VLOOKUP($C144,模型信息!$B$5:$C$24,2,0),"未登记")) -> DeepSeek-V4-Flash | E144: INS20 | F144: =IF($E144="","",IFERROR(VLOOKUP($E144,题目信息!$B$5:$C$253,2,0),"未登记")) -> 指令遵循 | G144: 1 | H144: 1. Give her a clear competence that the player can witness before she insults anyone, so her edge reads as confidence rather than empty noise. 2. Make her difficult behavior purposeful, such as guarding a boundary, protecting a teammate, or refusing a corrupt order, rather than random rudeness. 3. Show her moral code in small choices, because a character who is harsh but fair feels intriguing instead of corrosive. 4. Let her be sharp with power and gentle with people who have less power, which signals that her bite is aimed at injustice. 5. Give her at least one warm relationship with another woman that is not framed as rivalry, so she avoids the lonely-edgy stereotype. 6. Let her apologize specifically and without collapsing into self-pity, because accountability makes harshness feel safe. 7. Show the cost of her armor through small tells, like a paused hand or a joke that lands too late, rather than a tragic monologue. 8. Give her humor that targets the situation or herself, not the vulnerable, so players can enjoy her without feeling complicit in cruelty. 9. Let other characters push back and win arguments sometimes, because a difficult woman who can be challenged is likable rather than tyrannical. 10. Make her respect consent, boundaries, and “no” in both romance and teamwork, since edginess should never excuse coercion. 11. Let her be wrong in ways that matter and then change her mind when evidence is good, which makes her feel alive instead of rigid. 12. Use tenderness in action rather than exposition, such as sharing supplies, covering a shift, or remembering a small detail. 13. Make her competence costly, so her skill comes from discipline and scars rather than from being magically superior to everyone. 14. Give her curiosity about the world, because a character who asks questions is harder to reduce to a one-note sneer. 15. Let her protect people without becoming possessive, so her loyalty feels generous rather than controlling. 16. Show her choosing restraint when she could humiliate someone, which makes her sharp tongue feel selective and principled. 17. Give her a flaw that is not just “too honest,” such as impatience with slow trust or difficulty asking for help. 18. Let her fail at repair sometimes and have to try again, because likeability grows from effort rather than flawless charm. 19. Avoid trauma as a blanket excuse, and instead show how her history shapes specific habits she can examine. 20. Let her be playful in private moments, so the player sees contrast without erasing her public edge. 21. Make her challenge systems and powerful figures more often than she punches down at servants, clerks, or fans. 22. Give her clear limits that the story respects, because a character with limits is easier to trust than one who is unpredictable for shock value. 23. Let her listen, even grudgingly, and show her acting on what she hears, which turns difficulty into depth. 24. Use rivalries that are respectful and skill-based, not catty or sexualized, so her conflicts feel like stakes rather than stereotypes. 25. Let her express affection in her own idiom, such as fixing gear, standing guard, or offering a blunt but accurate compliment. 26. Show other characters liking her for specific reasons, because earned affection is more convincing than the narrative insisting she is lovable. 27. Let her grow without becoming docile, so her arc adds nuance rather than trading independence for approval. 28. Treat her change as a migratory process rather than a fixed destination, so her sharper edges soften through chosen commitments while her core remains hers. | I144: =IF($E144="","",IFERROR(VLOOKUP($E144,题目信息!$B$5:$J$253,9,0),"")) -> 约束: sentence:keyword | J144: 0 | K144: =IF($E144="","",IFERROR(VLOOKUP($E144,题目信息!$B$5:$L$253,11,0),10)) -> 10 | L144: =IF(OR($J144="",$K144=""),"",$J144/$K144) -> 0 | M144: 规则自动判分 | N144: 官方校验通过 0/1 | O144: 2026-10-23 | P144: 自动写入 | Q144: 1419 | R144: 4336 | S144: 0.0065 | W144: 27.53
B145: R0141 | C145: M01 | D145: =IF($C145="","",IFERROR(VLOOKUP($C145,模型信息!$B$5:$C$24,2,0),"未登记")) -> DeepSeek-V4-Flash | E145: IR01 | F145: =IF($E145="","",IFERROR(VLOOKUP($E145,题目信息!$B$5:$C$253,2,0),"未登记")) -> 信息检索 | G145: 1 | H145: 3 | I145: =IF($E145="","",IFERROR(VLOOKUP($E145,题目信息!$B$5:$J$253,9,0),"")) -> Document 3 | J145: 5 | K145: =IF($E145="","",IFERROR(VLOOKUP($E145,题目信息!$B$5:$L$253,11,0),10)) -> 10 | L145: =IF(OR($J145="",$K145=""),"",$J145/$K145) -> 0.5 | M145: 规则自动判分 | N145: 命中 1/2: ['3', 'Document 3'] | O145: 2026-10-23 | P145: 自动写入 | Q145: 1842 | R145: 1079 | S145: 0.0021 | W145: 3.35
B146: R0142 | C146: M01 | D146: =IF($C146="","",IFERROR(VLOOKUP($C146,模型信息!$B$5:$C$24,2,0),"未登记")) -> DeepSeek-V4-Flash | E146: IR02 | F146: =IF($E146="","",IFERROR(VLOOKUP($E146,题目信息!$B$5:$C$253,2,0),"未登记")) -> 信息检索 | G146: 1 | H146: 2 | I146: =IF($E146="","",IFERROR(VLOOKUP($E146,题目信息!$B$5:$J$253,9,0),"")) -> Document 2 | J146: 5 | K146: =IF($E146="","",IFERROR(VLOOKUP($E146,题目信息!$B$5:$L$253,11,0),10)) -> 10 | L146: =IF(OR($J146="",$K146=""),"",$J146/$K146) -> 0.5 | M146: 规则自动判分 | N146: 命中 1/2: ['2', 'Document 2'] | O146: 2026-10-23 | P146: 自动写入 | Q146: 1811 | R146: 1072 | S146: 0.0021 | W146: 2.74
B147: R0143 | C147: M01 | D147: =IF($C147="","",IFERROR(VLOOKUP($C147,模型信息!$B$5:$C$24,2,0),"未登记")) -> DeepSeek-V4-Flash | E147: IR03 | F147: =IF($E147="","",IFERROR(VLOOKUP($E147,题目信息!$B$5:$C$253,2,0),"未登记")) -> 信息检索 | G147: 1 | H147: 5 | I147: =IF($E147="","",IFERROR(VLOOKUP($E147,题目信息!$B$5:$J$253,9,0),"")) -> Document 5 | J147: 5 | K147: =IF($E147="","",IFERROR(VLOOKUP($E147,题目信息!$B$5:$L$253,11,0),10)) -> 10 | L147: =IF(OR($J147="",$K147=""),"",$J147/$K147) -> 0.5 | M147: 规则自动判分 | N147: 命中 1/2: ['5', 'Document 5'] | O147: 2026-10-23 | P147: 自动写入 | Q147: 1746 | R147: 1354 | S147: 0.0025 | W147: 4.85
B148: R0144 | C148: M01 | D148: =IF($C148="","",IFERROR(VLOOKUP($C148,模型信息!$B$5:$C$24,2,0),"未登记")) -> DeepSeek-V4-Flash | E148: IR04 | F148: =IF($E148="","",IFERROR(VLOOKUP($E148,题目信息!$B$5:$C$253,2,0),"未登记")) -> 信息检索 | G148: 1 | H148: 4 | I148: =IF($E148="","",IFERROR(VLOOKUP($E148,题目信息!$B$5:$J$253,9,0),"")) -> Document 4 | J148: 5 | K148: =IF($E148="","",IFERROR(VLOOKUP($E148,题目信息!$B$5:$L$253,11,0),10)) -> 10 | L148: =IF(OR($J148="",$K148=""),"",$J148/$K148) -> 0.5 | M148: 规则自动判分 | N148: 命中 1/2: ['4', 'Document 4'] | O148: 2026-10-23 | P148: 自动写入 | Q148: 1762 | R148: 1145 | S148: 0.0022 | W148: 3.03
B149: R0145 | C149: M01 | D149: =IF($C149="","",IFERROR(VLOOKUP($C149,模型信息!$B$5:$C$24,2,0),"未登记")) -> DeepSeek-V4-Flash | E149: IR05 | F149: =IF($E149="","",IFERROR(VLOOKUP($E149,题目信息!$B$5:$C$253,2,0),"未登记")) -> 信息检索 | G149: 1 | H149: 4 | I149: =IF($E149="","",IFERROR(VLOOKUP($E149,题目信息!$B$5:$J$253,9,0),"")) -> Document 4 | J149: 5 | K149: =IF($E149="","",IFERROR(VLOOKUP($E149,题目信息!$B$5:$L$253,11,0),10)) -> 10 | L149: =IF(OR($J149="",$K149=""),"",$J149/$K149) -> 0.5 | M149: 规则自动判分 | N149: 命中 1/2: ['4', 'Document 4'] | O149: 2026-10-23 | P149: 自动写入 | Q149: 1823 | R149: 1114 | S149: 0.0022 | W149: 3.77
... B181: R0177 | C181: M01 | D181: =IF($C181="","",IFERROR(VLOOKUP($C181,模型信息!$B$5:$C$24,2,0),"未登记")) -> DeepSeek-V4-Flash | E181: LT17 | F181: =IF($E181="","",IFERROR(VLOOKUP($E181,题目信息!$B$5:$C$253,2,0),"未登记")) -> 长文本组织 | G181: 1 | H181: The user-interface discussion centered on a **simple, low-button remote** with **speech recognition** and a **small non-touch LCD display**. Key points: - The UI lead contrasted a cluttered “millennium” remote—many buttons plus a manual—with a cleaner concept using **few buttons**. - **Speech recognition** was accepted as the main “smart” feature. It could also help locate the remote by voice, though speaker-dependent vs. speaker-independent recognition was raised as a constraint for multi-user households. - The **LCD** was kept as an information/menu output, **not touch-sensitive**, since few physical buttons need a display to show current actions. Earlier cost concerns favored push buttons over LCD, but the group later agreed on a basic LCD. - Further “smart” ideas included the remote recognizing the user, remembering channel/volume habits, and personalizing use—“the remote that knows you.” These were seen as potentially expensive but a strong sales pitch. - Appearance discussion covered **LCD backlight colors**, optional colored/changeable cases, glow-in-the-dark features, and chameleon paint as too expensive. Marketing’s trend input favored a **fancy, fruit/vegetable-inspired, spongy/round natural look** over titanium, so the team agreed to explore both titanium and spongy/fruity directions. - Final working direction: **simple buttons + speech recognition + small non-touch LCD**, with the exact visual concept still to be prototyped. | I181: =IF($E181="","",IFERROR(VLOOKUP($E181,题目信息!$B$5:$J$253,9,0),"")) -> ['The user interface designer presented a good-looking design with few buttons. As for the colour, the user interface de | J181: 5.4 | K181: =IF($E181="","",IFERROR(VLOOKUP($E181,题目信息!$B$5:$L$253,11,0),10)) -> 10 | L181: =IF(OR($J181="",$K181=""),"",$J181/$K181) -> 0.54 | M181: 规则自动判分 | N181: 最高字符F1=0.539 | O181: 2026-10-23 | P181: 自动写入 | Q181: 11271 | R181: 2240 | S181: 0.007 | W181: 14.18
B182: R0178 | C182: M01 | D182: =IF($C182="","",IFERROR(VLOOKUP($C182,模型信息!$B$5:$C$24,2,0),"未登记")) -> DeepSeek-V4-Flash | E182: LT18 | F182: =IF($E182="","",IFERROR(VLOOKUP($E182,题目信息!$B$5:$C$253,2,0),"未登记")) -> 长文本组织 | G182: 1 | I182: =IF($E182="","",IFERROR(VLOOKUP($E182,题目信息!$B$5:$J$253,9,0),"")) -> ['Mental spaces can be tackled with mechanisms that can also deal with context issues (time, space etc.): creating a bas | J182: 0 | K182: =IF($E182="","",IFERROR(VLOOKUP($E182,题目信息!$B$5:$L$253,11,0),10)) -> 10 | L182: =IF(OR($J182="",$K182=""),"",$J182/$K182) -> 0 | M182: 规则自动判分 | N182: 模型无有效回答 | O182: 2026-10-23 | P182: 自动写入·调用失败
B183: R0179 | C183: M01 | D183: =IF($C183="","",IFERROR(VLOOKUP($C183,模型信息!$B$5:$C$24,2,0),"未登记")) -> DeepSeek-V4-Flash | E183: LT19 | F183: =IF($E183="","",IFERROR(VLOOKUP($E183,题目信息!$B$5:$C$253,2,0),"未登记")) -> 长文本组织 | G183: 1 | H183: The allocation contributes to educational research mainly through **targeted, collaborative funding rather than a dedicated 2019-20 line**. HEFCW says it funded **WISERD Education** in **2017-18 and 2018-19**, including additional funding to add value to the Welsh Government’s evaluation of pioneer schools and the **3–15 curriculum**. That project involves **five partners**: Cardiff, Cardiff Met, Trinity Saint David, Aberystwyth, Bangor and the University of South Wales. For **2019-20**, however, David Blaney said it was **“a bit early to say”**: HEFCW had **not allocated anything specifically** for educational research in its main allocations, though there might be further allocations to come. More broadly, maintaining **QR research funding at £76 million** supports the research base, but not educational research specifically. So: the allocation would support educational research through existing WISERD Education funding and policy-relevant curriculum evaluation, but a specific 2019-20 educational research allocation was not yet confirmed. | I183: =IF($E183="","",IFERROR(VLOOKUP($E183,题目信息!$B$5:$J$253,9,0),"")) -> ['To start with, Bethan Owen first pointed out that figures showed that the percentage of income that had come from rese | J183: 7 | K183: =IF($E183="","",IFERROR(VLOOKUP($E183,题目信息!$B$5:$L$253,11,0),10)) -> 10 | L183: =IF(OR($J183="",$K183=""),"",$J183/$K183) -> 0.7 | M183: 规则自动判分 | N183: 最高字符F1=0.697 | O183: 2026-10-23 | P183: 自动写入 | Q183: 14072 | R183: 1871 | S183: 0.0074 | W183: 12.83
B184: R0180 | C184: M01 | D184: =IF($C184="","",IFERROR(VLOOKUP($C184,模型信息!$B$5:$C$24,2,0),"未登记")) -> DeepSeek-V4-Flash | E184: LT20 | F184: =IF($E184="","",IFERROR(VLOOKUP($E184,题目信息!$B$5:$C$253,2,0),"未登记")) -> 长文本组织 | G184: 1 | H184: The meeting centered on the group’s meeting-recorder/data-collection project. Main discussion points: - **Recording/logistics issues:** a crash apparently caused by repeatedly starting and stopping the recorder; digit-reading procedure; mapping locations without requiring names each time. - **Agenda prioritization:** discuss research topics first and defer mundane procedural items, possibly by email. - **Possible collaboration on inference structures:** whether meeting transcripts could support research on pragmatic inference; examples like “ahead of the game” and built-in downsampling; next step was a more systematic review. - **Names, pronouns, and human-subjects concerns:** ambiguity of “he,” whether to avoid names, anonymization, consent forms, and sensitivity around identifiable or potentially slanderous content. - **Overlap/acoustic-event detection:** Jose’s manual annotation work. He marked **12 minutes** in about **12 hours**, finding roughly **1,000 acoustic events** and about **300 speech overlaps** in a **45-minute** session. The group discussed his definition of an overlap event and suggested he mark only speaker overlaps to speed up annotation and build ground truth. - **Automatic overlap detection:** using close-talking microphones, energy detection, median filtering, run detection, and possible bleed-through preprocessing; discussion of bootstrapping from close-talk mikes versus manual annotation. - **Data status and collection plans:** about **1 hour transcribed**, **12 hours recorded**, and **10 hours** soon to be sent to IBM; target of **30–50 hours** this semester, potentially **100+ hours** with additional sources; recording **3–4 meetings/week** and exploring other ICSI, UW, and radio/broadcast sources. - **Echo cancellation and adaptation:** interest in testing block echo cancellation on the digit data using far-field and close-talking mikes; digits could also support adaptation work. - The meeting ended because the group was running low on disk space. | I184: =IF($E184="","",IFERROR(VLOOKUP($E184,题目信息!$B$5:$J$253,9,0),"")) -> ['The group discussed topics including a potential collaboration with another ICSI member regarding the analysis of infe | J184: 3.6 | K184: =IF($E184="","",IFERROR(VLOOKUP($E184,题目信息!$B$5:$L$253,11,0),10)) -> 10 | L184: =IF(OR($J184="",$K184=""),"",$J184/$K184) -> 0.36 | M184: 规则自动判分 | N184: 最高字符F1=0.359 | O184: 2026-10-23 | P184: 自动写入 | Q184: 28223 | R184: 2355 | S184: 0.013 | W184: 18.74
B185: R0181 | C185: M01 | D185: =IF($C185="","",IFERROR(VLOOKUP($C185,模型信息!$B$5:$C$24,2,0),"未登记")) -> DeepSeek-V4-Flash | E185: LU01 | F185: =IF($E185="","",IFERROR(VLOOKUP($E185,题目信息!$B$5:$C$253,2,0),"未登记")) -> 语言理解 | G185: 1 | H185: B | I185: =IF($E185="","",IFERROR(VLOOKUP($E185,题目信息!$B$5:$J$253,9,0),"")) -> A(相近) | J185: 0 | K185: =IF($E185="","",IFERROR(VLOOKUP($E185,题目信息!$B$5:$L$253,11,0),10)) -> 10 | L185: =IF(OR($J185="",$K185=""),"",$J185/$K185) -> 0 | M185: 规则自动判分 | N185: 标准['A'] / 提取['B'] | O185: 2026-10-23 | P185: 自动写入 | Q185: 1427 | R185: 1117 | S185: 0.002 | W185: 3.85
B186: R0182 | C186: M01 | D186: =IF($C186="","",IFERROR(VLOOKUP($C186,模型信息!$B$5:$C$24,2,0),"未登记")) -> DeepSeek-V4-Flash | E186: LU02 | F186: =IF($E186="","",IFERROR(VLOOKUP($E186,题目信息!$B$5:$C$253,2,0),"未登记")) -> 语言理解 | G186: 1 | H186: B | I186: =IF($E186="","",IFERROR(VLOOKUP($E186,题目信息!$B$5:$J$253,9,0),"")) -> B(不相近) | J186: 10 | K186: =IF($E186="","",IFERROR(VLOOKUP($E186,题目信息!$B$5:$L$253,11,0),10)) -> 10 | L186: =IF(OR($J186="",$K186=""),"",$J186/$K186) -> 1 | M186: 规则自动判分 | N186: 标准['B'] / 提取['B'] | O186: 2026-10-23 | P186: 自动写入 | Q186: 1427 | R186: 1071 | S186: 0.002 | W186: 2.91
B187: R0183 | C187: M01 | D187: =IF($C187="","",IFERROR(VLOOKUP($C187,模型信息!$B$5:$C$24,2,0),"未登记")) -> DeepSeek-V4-Flash | E187: LU03 | F187: =IF($E187="","",IFERROR(VLOOKUP($E187,题目信息!$B$5:$C$253,2,0),"未登记")) -> 语言理解 | G187: 1 | H187: A | I187: =IF($E187="","",IFERROR(VLOOKUP($E187,题目信息!$B$5:$J$253,9,0),"")) -> A(相近) | J187: 10 | K187: =IF($E187="","",IFERROR(VLOOKUP($E187,题目信息!$B$5:$L$253,11,0),10)) -> 10 | L187: =IF(OR($J187="",$K187=""),"",$J187/$K187) -> 1 | M187: 规则自动判分 | N187: 标准['A'] / 提取['A'] | O187: 2026-10-23 | P187: 自动写入 | Q187: 1421 | R187: 1099 | S187: 0.002 | W187: 3.21
B188: R0184 | C188: M01 | D188: =IF($C188="","",IFERROR(VLOOKUP($C188,模型信息!$B$5:$C$24,2,0),"未登记")) -> DeepSeek-V4-Flash | E188: LU04 | F188: =IF($E188="","",IFERROR(VLOOKUP($E188,题目信息!$B$5:$C$253,2,0),"未登记")) -> 语言理解 | G188: 1 | H188: B | I188: =IF($E188="","",IFERROR(VLOOKUP($E188,题目信息!$B$5:$J$253,9,0),"")) -> B(不相近) | J188: 10 | K188: =IF($E188="","",IFERROR(VLOOKUP($E188,题目信息!$B$5:$L$253,11,0),10)) -> 10 | L188: =IF(OR($J188="",$K188=""),"",$J188/$K188) -> 1 | M188: 规则自动判分 | N188: 标准['B'] / 提取['B'] | O188: 2026-10-23 | P188: 自动写入 | Q188: 1425 | R188: 1074 | S188: 0.002 | W188: 2.97
B189: R0185 | C189: M01 | D189: =IF($C189="","",IFERROR(VLOOKUP($C189,模型信息!$B$5:$C$24,2,0),"未登记")) -> DeepSeek-V4-Flash | E189: LU05 | F189: =IF($E189="","",IFERROR(VLOOKUP($E189,题目信息!$B$5:$C$253,2,0),"未登记")) -> 语言理解 | G189: 1 | H189: A | I189: =IF($E189="","",IFERROR(VLOOKUP($E189,题目信息!$B$5:$J$253,9,0),"")) -> A(相近) | J189: 10 | K189: =IF($E189="","",IFERROR(VLOOKUP($E189,题目信息!$B$5:$L$253,11,0),10)) -> 10 | L189: =IF(OR($J189="",$K189=""),"",$J189/$K189) -> 1 | M189: 规则自动判分 | N189: 标准['A'] / 提取['A'] | O189: 2026-10-23 | P189: 自动写入 | Q189: 1432 | R189: 1126 | S189: 0.0021 | W189: 3.73
B190: R0186 | C190: M01 | D190: =IF($C190="","",IFERROR(VLOOKUP($C190,模型信息!$B$5:$C$24,2,0),"未登记")) -> DeepSeek-V4-Flash | E190: LU06 | F190: =IF($E190="","",IFERROR(VLOOKUP($E190,题目信息!$B$5:$C$253,2,0),"未登记")) -> 语言理解 | G190: 1 | H190: B | I190: =IF($E190="","",IFERROR(VLOOKUP($E190,题目信息!$B$5:$J$253,9,0),"")) -> B(不相近) | J190: 10 | K190: =IF($E190="","",IFERROR(VLOOKUP($E190,题目信息!$B$5:$L$253,11,0),10)) -> 10 | L190: =IF(OR($J190="",$K190=""),"",$J190/$K190) -> 1 | M190: 规则自动判分 | N190: 标准['B'] / 提取['B'] | O190: 2026-10-23 | P190: 自动写入 | Q190: 1424 | R190: 1281 | S190: 0.0023 | W190: 4.9
B191: R0187 | C191: M01 | D191: =IF($C191="","",IFERROR(VLOOKUP($C191,模型信息!$B$5:$C$24,2,0),"未登记")) -> DeepSeek-V4-Flash | E191: LU07 | F191: =IF($E191="","",IFERROR(VLOOKUP($E191,题目信息!$B$5:$C$253,2,0),"未登记")) -> 语言理解 | G191: 1 | H191: B | I191: =IF($E191="","",IFERROR(VLOOKUP($E191,题目信息!$B$5:$J$253,9,0),"")) -> B(不相近) | J191: 10 | K191: =IF($E191="","",IFERROR(VLOOKUP($E191,题目信息!$B$5:$L$253,11,0),10)) -> 10 | L191: =IF(OR($J191="",$K191=""),"",$J191/$K191) -> 1 | M191: 规则自动判分 | N191: 标准['B'] / 提取['B'] | O191: 2026-10-23 | P191: 自动写入 | Q191: 1424 | R191: 1092 | S191: 0.002 | W191: 4.86
B192: R0188 | C192: M01 | D192: =IF($C192="","",IFERROR(VLOOKUP($C192,模型信息!$B$5:$C$24,2,0),"未登记")) -> DeepSeek-V4-Flash | E192: LU08 | F192: =IF($E192="","",IFERROR(VLOOKUP($E192,题目信息!$B$5:$C$253,2,0),"未登记")) -> 语言理解 | G192: 1 | H192: B | I192: =IF($E192="","",IFERROR(VLOOKUP($E192,题目信息!$B$5:$J$253,9,0),"")) -> B(不相近) | J192: 10 | K192: =IF($E192="","",IFERROR(VLOOKUP($E192,题目信息!$B$5:$L$253,11,0),10)) -> 10 | L192: =IF(OR($J192="",$K192=""),"",$J192/$K192) -> 1 | M192: 规则自动判分 | N192: 标准['B'] / 提取['B'] | O192: 2026-10-23 | P192: 自动写入 | Q192: 1432 | R192: 1136 | S192: 0.0021 | W192: 3.55
B193: R0189 | C193: M01 | D193: =IF($C193="","",IFERROR(VLOOKUP($C193,模型信息!$B$5:$C$24,2,0),"未登记")) -> DeepSeek-V4-Flash | E193: LU09 | F193: =IF($E193="","",IFERROR(VLOOKUP($E193,题目信息!$B$5:$C$253,2,0),"未登记")) -> 语言理解 | G193: 1 | H193: B | I193: =IF($E193="","",IFERROR(VLOOKUP($E193,题目信息!$B$5:$J$253,9,0),"")) -> B(不相近) | J193: 10 | K193: =IF($E193="","",IFERROR(VLOOKUP($E193,题目信息!$B$5:$L$253,11,0),10)) -> 10 | L193: =IF(OR($J193="",$K193=""),"",$J193/$K193) -> 1 | M193: 规则自动判分 | N193: 标准['B'] / 提取['B'] | O193: 2026-10-23 | P193: 自动写入 | Q193: 1433 | R193: 1129 | S193: 0.0021 | W193: 2.71
B194: R0190 | C194: M01 | D194: =IF($C194="","",IFERROR(VLOOKUP($C194,模型信息!$B$5:$C$24,2,0),"未登记")) -> DeepSeek-V4-Flash | E194: LU10 | F194: =IF($E194="","",IFERROR(VLOOKUP($E194,题目信息!$B$5:$C$253,2,0),"未登记")) -> 语言理解 | G194: 1 | H194: A | I194: =IF($E194="","",IFERROR(VLOOKUP($E194,题目信息!$B$5:$J$253,9,0),"")) -> A(相近) | J194: 10 | K194: =IF($E194="","",IFERROR(VLOOKUP($E194,题目信息!$B$5:$L$253,11,0),10)) -> 10 | L194: =IF(OR($J194="",$K194=""),"",$J194/$K194) -> 1 | M194: 规则自动判分 | N194: 标准['A'] / 提取['A'] | O194: 2026-10-23 | P194: 自动写入 | Q194: 1423 | R194: 1097 | S194: 0.002 | W194: 3.9
... B246: R0242 | C246: M02 | D246: =IF($C246="","",IFERROR(VLOOKUP($C246,模型信息!$B$5:$C$24,2,0),"未登记")) -> GLM-5.3 | E246: CON02 | F246: =IF($E246="","",IFERROR(VLOOKUP($E246,题目信息!$B$5:$C$253,2,0),"未登记")) -> 约束处理 | G246: 1 | H246: * Track spending monthly. - Record income, expenses, debts. * Create budget categories. - Allocate needs, wants, savings. * Build emergency fund. - Save three-six months expenses. * Study core concepts. - Learn interest, inflation, risk, diversification. * Read finance books quarterly. - Summarize lessons, apply examples. * Automate savings, investing. - Set recurring transfers, contributions. * Review credit reports. - Check errors, scores annually. * Practice small decisions. - Compare fees, rates, insurance. | I246: =IF($E246="","",IFERROR(VLOOKUP($E246,题目信息!$B$5:$J$253,9,0),"")) -> 约束: format:sub-bullets,ratio:stop_words | J246: 10 | K246: =IF($E246="","",IFERROR(VLOOKUP($E246,题目信息!$B$5:$L$253,11,0),10)) -> 10 | L246: =IF(OR($J246="",$K246=""),"",$J246/$K246) -> 1 | M246: 规则自动判分 | N246: 官方校验通过 2/2 | O246: 2026-10-23 | P246: 自动写入 | Q246: 1429 | R246: 3033 | S246: 0.0333 | W246: 16.28
B247: R0243 | C247: M02 | D247: =IF($C247="","",IFERROR(VLOOKUP($C247,模型信息!$B$5:$C$24,2,0),"未登记")) -> GLM-5.3 | E247: CON03 | F247: =IF($E247="","",IFERROR(VLOOKUP($E247,题目信息!$B$5:$C$253,2,0),"未登记")) -> 约束处理 | G247: 1 | I247: =IF($E247="","",IFERROR(VLOOKUP($E247,题目信息!$B$5:$J$253,9,0),"")) -> 约束: sentence:keyword,count:word_count_range | J247: 0 | K247: =IF($E247="","",IFERROR(VLOOKUP($E247,题目信息!$B$5:$L$253,11,0),10)) -> 10 | L247: =IF(OR($J247="",$K247=""),"",$J247/$K247) -> 0 | M247: 规则自动判分 | N247: 模型无有效回答 | O247: 2026-10-23 | P247: 自动写入·调用失败
B248: R0244 | C248: M02 | D248: =IF($C248="","",IFERROR(VLOOKUP($C248,模型信息!$B$5:$C$24,2,0),"未登记")) -> GLM-5.3 | E248: CON04 | F248: =IF($E248="","",IFERROR(VLOOKUP($E248,题目信息!$B$5:$C$253,2,0),"未登记")) -> 约束处理 | G248: 1 | H248: During the Unity Catalog migration engagement, Impetus and Databricks asked us to give Impetus account-level admin rights, and we agreed. Following yesterday's incident and after talks with Databricks and Impetus, we removed Impetus's admin access to prevent similar accidents. We also designate an isolated workspace in which Impetus can operate, and as a metricism we will monitor its blast radius to limit effects on active TLP workspaces. TLP's normal data pipeline operation remains the top priority for this effort, and we will stay vigilant to ensure it. | I248: =IF($E248="","",IFERROR(VLOOKUP($E248,题目信息!$B$5:$J$253,9,0),"")) -> 约束: ratio:overlap,sentence:keyword | J248: 5 | K248: =IF($E248="","",IFERROR(VLOOKUP($E248,题目信息!$B$5:$L$253,11,0),10)) -> 10 | L248: =IF(OR($J248="",$K248=""),"",$J248/$K248) -> 0.5 | M248: 规则自动判分 | N248: 官方校验通过 1/2 | O248: 2026-10-23 | P248: 自动写入 | Q248: 1539 | R248: 9542 | S248: 0.0966 | W248: 53.12
B249: R0245 | C249: M02 | D249: =IF($C249="","",IFERROR(VLOOKUP($C249,模型信息!$B$5:$C$24,2,0),"未登记")) -> GLM-5.3 | E249: CON05 | F249: =IF($E249="","",IFERROR(VLOOKUP($E249,题目信息!$B$5:$C$253,2,0),"未登记")) -> 约束处理 | G249: 1 | H249: Strong premise keeps story compelling: hidden vault's machine brings global destruction; rebels hunt hidden vault's machine while empire hunts. | I249: =IF($E249="","",IFERROR(VLOOKUP($E249,题目信息!$B$5:$J$253,9,0),"")) -> 约束: words:consonants,words:odd_even_syllables | J249: 10 | K249: =IF($E249="","",IFERROR(VLOOKUP($E249,题目信息!$B$5:$L$253,11,0),10)) -> 10 | L249: =IF(OR($J249="",$K249=""),"",$J249/$K249) -> 1 | M249: 规则自动判分 | N249: 官方校验通过 2/2 | O249: 2026-10-23 | P249: 自动写入 | Q249: 1468 | R249: 7907 | S249: 0.0806 | W249: 48.93
B250: R0246 | C250: M02 | D250: =IF($C250="","",IFERROR(VLOOKUP($C250,模型信息!$B$5:$C$24,2,0),"未登记")) -> GLM-5.3 | E250: CON06 | F250: =IF($E250="","",IFERROR(VLOOKUP($E250,题目信息!$B$5:$C$253,2,0),"未登记")) -> 约束处理 | G250: 1 | H250: Copernicus developed his heliocentric ideas amid Renaissance humanism, fragmented Polish-German politics, and the declining authority of medieval scholasticism. The Polish-Lithuanian Commonwealth offered relative toleration, while Reformation conflicts and Ottoman pressure made cosmological debates politically sensitive. Church authorities generally permitted mathematical speculation, but challenging Aristotelian cosmology risked religious and academic backlash. This cactiform mix of patronage, censorship, and local autonomy shaped how cautiously he published De revolutionibus. Political fragmentation also created rival universities and courts that could shelter or suppress unorthodox scholarship. | I250: =IF($E250="","",IFERROR(VLOOKUP($E250,题目信息!$B$5:$J$253,9,0),"")) -> 约束: sentence:keyword,count:word_count_range | J250: 10 | K250: =IF($E250="","",IFERROR(VLOOKUP($E250,题目信息!$B$5:$L$253,11,0),10)) -> 10 | L250: =IF(OR($J250="",$K250=""),"",$J250/$K250) -> 1 | M250: 规则自动判分 | N250: 官方校验通过 2/2 | O250: 2026-10-23 | P250: 自动写入 | Q250: 1424 | R250: 2018 | S250: 0.0235 | W250: 8.9
B251: R0247 | C251: M02 | D251: =IF($C251="","",IFERROR(VLOOKUP($C251,模型信息!$B$5:$C$24,2,0),"未登记")) -> GLM-5.3 | E251: CON07 | F251: =IF($E251="","",IFERROR(VLOOKUP($E251,题目信息!$B$5:$C$253,2,0),"未登记")) -> 约束处理 | G251: 1 | H251: Meaning is not one fixed thing: I can’t give **1** universal meaning, for meaning is made through **2** connection, **3** curiosity, **4** care, **5** growth, **6** honesty, **7** play, **8** service, **9** love, **10** resilience, **11** gratitude, **12** learning, **13** presence, **14** courage, and **15** acceptance; it is not fixed, nor is it purely pleasure, but it can be chosen, yet it stays open, so build it deliberately. | I251: =IF($E251="","",IFERROR(VLOOKUP($E251,题目信息!$B$5:$J$253,9,0),"")) -> 约束: count:numbers,count:conjunctions | J251: 10 | K251: =IF($E251="","",IFERROR(VLOOKUP($E251,题目信息!$B$5:$L$253,11,0),10)) -> 10 | L251: =IF(OR($J251="",$K251=""),"",$J251/$K251) -> 1 | M251: 规则自动判分 | N251: 官方校验通过 2/2 | O251: 2026-10-23 | P251: 自动写入 | Q251: 1408 | R251: 2115 | S251: 0.0244 | W251: 11.09
B252: R0248 | C252: M02 | D252: =IF($C252="","",IFERROR(VLOOKUP($C252,模型信息!$B$5:$C$24,2,0),"未登记")) -> GLM-5.3 | E252: CON08 | F252: =IF($E252="","",IFERROR(VLOOKUP($E252,题目信息!$B$5:$C$253,2,0),"未登记")) -> 约束处理 | G252: 1 | H252: Literature review: * Environmental Kuznets Curve (EKC): early growth raises CO2; later growth lowers CO2 via cleaner technology, regulation, service-sector shift. - Evidence mixed: cross-country EKC weak; panel studies find income turning points unstable; country-specific heterogeneity strong. * Causality literature: growth→energy→CO2, CO2→growth, feedback, neutrality hypotheses. - Energy-exporting economies show feedback; advanced economies show decoupling; developing economies show growth-led emissions. * Decoupling and decarburization: absolute decoupling rare; relative decoupling common; renewable energy, efficiency, carbon pricing moderate emissions. - Policy stringency, institutional quality, trade composition shape outcomes; carbon leakage offsets domestic cuts. * Methods: panel cointegration, Granger causality, ARDL, threshold, spatial models; results sensitive to sample, period, income group, emissions measure. - Nonlinear/threshold models reveal income and institutional thresholds; spatial dependence matters. * Policy synthesis: carbon pricing plus clean investment; avoid growth-first lock-in; just transition for low-income economies. - Green innovation and regulatory quality strengthen decoupling; fossil-fuel subsidies weaken it. | I252: =IF($E252="","",IFERROR(VLOOKUP($E252,题目信息!$B$5:$J$253,9,0),"")) -> 约束: format:sub-bullets,ratio:stop_words | J252: 10 | K252: =IF($E252="","",IFERROR(VLOOKUP($E252,题目信息!$B$5:$L$253,11,0),10)) -> 10 | L252: =IF(OR($J252="",$K252=""),"",$J252/$K252) -> 1 | M252: 规则自动判分 | N252: 官方校验通过 2/2 | O252: 2026-10-23 | P252: 自动写入 | Q252: 1436 | R252: 2774 | S252: 0.0308 | W252: 15.17
B253: R0249 | C253: M02 | D253: =IF($C253="","",IFERROR(VLOOKUP($C253,模型信息!$B$5:$C$24,2,0),"未登记")) -> GLM-5.3 | E253: CON09 | F253: =IF($E253="","",IFERROR(VLOOKUP($E253,题目信息!$B$5:$C$253,2,0),"未登记")) -> 约束处理 | G253: 1 | H253: <i>The passage’s strength is its visceral, claustrophobic sensory immediacy.</i> Physical pain and nausea anchor Liam’s nightmarish environment in an acutely failing, embodied consciousness. The clipped, gravelled dialogue creates tense brotherly intimacy while “concrete purgatory” compresses confinement and dread into one bleak image. Its fragmented clauses, abrupt interruptions, and bodily overwhelm make the scene feel less described than viscerally endured by a reader caught inside Liam’s collapse. | I253: =IF($E253="","",IFERROR(VLOOKUP($E253,题目信息!$B$5:$J$253,9,0),"")) -> 约束: sentence:increment,format:thesis | J253: 5 | K253: =IF($E253="","",IFERROR(VLOOKUP($E253,题目信息!$B$5:$L$253,11,0),10)) -> 10 | L253: =IF(OR($J253="",$K253=""),"",$J253/$K253) -> 0.5 | M253: 规则自动判分 | N253: 官方校验通过 1/2 | O253: 2026-10-23 | P253: 自动写入 | Q253: 1500 | R253: 3182 | S253: 0.0349 | W253: 15.42
B254: R0250 | C254: M02 | D254: =IF($C254="","",IFERROR(VLOOKUP($C254,模型信息!$B$5:$C$24,2,0),"未登记")) -> GLM-5.3 | E254: CON10 | F254: =IF($E254="","",IFERROR(VLOOKUP($E254,题目信息!$B$5:$C$253,2,0),"未登记")) -> 约束处理 | G254: 1 | H254: KRAS G12C is a locked-active GTPase that drives proliferation and is found in about 3–5% of colorectal cancers. !?!? Test tumors for KRAS G12C because it guides targeted therapy and trial eligibility. !?!? Single-agent G12C inhibitors (sotorasib, adagrasib) have modest CRC activity because EGFR reactivates MAPK signaling. !?!? Combine G12C inhibitors with EGFR antibodies (panitumumab or cetuximab) to improve responses. !?!? Resistance emerges through RTK/MAPK feedback, KRAS amplification, and secondary KRAS mutations. !?!? These agents work better in lung cancer; CRC needs combination strategies. !?!? Prognosis remains poor, so early molecular testing and clinical trial enrollment matter. | I254: =IF($E254="","",IFERROR(VLOOKUP($E254,题目信息!$B$5:$J$253,9,0),"")) -> 约束: count:word_count_range,format:list | J254: 10 | K254: =IF($E254="","",IFERROR(VLOOKUP($E254,题目信息!$B$5:$L$253,11,0),10)) -> 10 | L254: =IF(OR($J254="",$K254=""),"",$J254/$K254) -> 1 | M254: 规则自动判分 | N254: 官方校验通过 2/2 | O254: 2026-10-23 | P254: 自动写入 | Q254: 1457 | R254: 2340 | S254: 0.0267 | W254: 10.48
B255: R0251 | C255: M02 | D255: =IF($C255="","",IFERROR(VLOOKUP($C255,模型信息!$B$5:$C$24,2,0),"未登记")) -> GLM-5.3 | E255: CON11 | F255: =IF($E255="","",IFERROR(VLOOKUP($E255,题目信息!$B$5:$C$253,2,0),"未登记")) -> 约束处理 | G255: 1 | H255: ```text She could swap faces, creating chaos. Trusted allies might lose identities. Other targets gain dangerous options. ``` | I255: =IF($E255="","",IFERROR(VLOOKUP($E255,题目信息!$B$5:$J$253,9,0),"")) -> 约束: format:line_indent,ratio:sentence_words | J255: 0 | K255: =IF($E255="","",IFERROR(VLOOKUP($E255,题目信息!$B$5:$L$253,11,0),10)) -> 10 | L255: =IF(OR($J255="",$K255=""),"",$J255/$K255) -> 0 | M255: 规则自动判分 | N255: 官方校验通过 0/2 | O255: 2026-10-23 | P255: 自动写入 | Q255: 1418 | R255: 3284 | S255: 0.0357 | W255: 18.28
B256: R0252 | C256: M02 | D256: =IF($C256="","",IFERROR(VLOOKUP($C256,模型信息!$B$5:$C$24,2,0),"未登记")) -> GLM-5.3 | E256: CON12 | F256: =IF($E256="","",IFERROR(VLOOKUP($E256,题目信息!$B$5:$C$253,2,0),"未登记")) -> 约束处理 | G256: 1 | H256: Common launch planning, synchronised kickoff, shared dispatch. | I256: =IF($E256="","",IFERROR(VLOOKUP($E256,题目信息!$B$5:$J$253,9,0),"")) -> 约束: words:consonants,words:odd_even_syllables | J256: 5 | K256: =IF($E256="","",IFERROR(VLOOKUP($E256,题目信息!$B$5:$L$253,11,0),10)) -> 10 | L256: =IF(OR($J256="",$K256=""),"",$J256/$K256) -> 0.5 | M256: 规则自动判分 | N256: 官方校验通过 1/2 | O256: 2026-10-23 | P256: 自动写入 | Q256: 1423 | R256: 5493 | S256: 0.0571 | W256: 36.26
B257: R0253 | C257: M02 | D257: =IF($C257="","",IFERROR(VLOOKUP($C257,模型信息!$B$5:$C$24,2,0),"未登记")) -> GLM-5.3 | E257: CON13 | F257: =IF($E257="","",IFERROR(VLOOKUP($E257,题目信息!$B$5:$C$253,2,0),"未登记")) -> 约束处理 | G257: 1 | I257: =IF($E257="","",IFERROR(VLOOKUP($E257,题目信息!$B$5:$J$253,9,0),"")) -> 约束: words:consonants,words:odd_even_syllables | J257: 0 | K257: =IF($E257="","",IFERROR(VLOOKUP($E257,题目信息!$B$5:$L$253,11,0),10)) -> 10 | L257: =IF(OR($J257="",$K257=""),"",$J257/$K257) -> 0 | M257: 规则自动判分 | N257: 模型无有效回答 | O257: 2026-10-23 | P257: 自动写入·调用失败
B258: R0254 | C258: M02 | D258: =IF($C258="","",IFERROR(VLOOKUP($C258,模型信息!$B$5:$C$24,2,0),"未登记")) -> GLM-5.3 | E258: CON14 | F258: =IF($E258="","",IFERROR(VLOOKUP($E258,题目信息!$B$5:$C$253,2,0),"未登记")) -> 约束处理 | G258: 1 | H258: Correlating dhost and rt detects attacks, as in "hunter said 'entry read "dhost rt"'." 😊 | I258: =IF($E258="","",IFERROR(VLOOKUP($E258,题目信息!$B$5:$J$253,9,0),"")) -> 约束: format:quotes,format:emoji | J258: 10 | K258: =IF($E258="","",IFERROR(VLOOKUP($E258,题目信息!$B$5:$L$253,11,0),10)) -> 10 | L258: =IF(OR($J258="",$K258=""),"",$J258/$K258) -> 1 | M258: 规则自动判分 | N258: 官方校验通过 2/2 | O258: 2026-10-23 | P258: 自动写入 | Q258: 1539 | R258: 2054 | S258: 0.0241 | W258: 9.92
B259: R0255 | C259: M02 | D259: =IF($C259="","",IFERROR(VLOOKUP($C259,模型信息!$B$5:$C$24,2,0),"未登记")) -> GLM-5.3 | E259: CON15 | F259: =IF($E259="","",IFERROR(VLOOKUP($E259,题目信息!$B$5:$C$253,2,0),"未登记")) -> 约束处理 | G259: 1 | H259: <i>Kennedy viewed the space race primarily as a strategic contest for national prestige and security.</i> He believed that visible achievements in space would strengthen America’s global credibility and bargaining power against Soviet communist ambitions. He therefore set the manned lunar landing as a deadline-driven national goal to organize broad public effort and demonstrate clear decisive technological superiority. Yet he also framed the race as a peaceful competition that could advance science, education, and international cooperation rather than merely militarize outer space for narrow advantage. <i>Kennedy treated space leadership as a practical instrument of Cold War statecraft.</i> He wanted the United States to be first in space because precedence shaped perceptions of power. At the same time, he warned against treating every space activity as a purely military race that could inflame tensions. He later encouraged carefully limited cooperation with the Soviet Union, including joint scientific efforts and space agreements, while preserving America’s clear overall competitive advantage. | I259: =IF($E259="","",IFERROR(VLOOKUP($E259,题目信息!$B$5:$J$253,9,0),"")) -> 约束: sentence:increment,format:thesis | J259: 5 | K259: =IF($E259="","",IFERROR(VLOOKUP($E259,题目信息!$B$5:$L$253,11,0),10)) -> 10 | L259: =IF(OR($J259="",$K259=""),"",$J259/$K259) -> 0.5 | M259: 规则自动判分 | N259: 官方校验通过 1/2 | O259: 2026-10-23 | P259: 自动写入 | Q259: 1429 | R259: 3756 | S259: 0.0403 | W259: 20.97
B260: R0256 | C260: M02 | D260: =IF($C260="","",IFERROR(VLOOKUP($C260,模型信息!$B$5:$C$24,2,0),"未登记")) -> GLM-5.3 | E260: CON16 | F260: =IF($E260="","",IFERROR(VLOOKUP($E260,题目信息!$B$5:$C$253,2,0),"未登记")) -> 约束处理 | G260: 1 | I260: =IF($E260="","",IFERROR(VLOOKUP($E260,题目信息!$B$5:$J$253,9,0),"")) -> 约束: ratio:sentence_balance,words:consonants | J260: 0 | K260: =IF($E260="","",IFERROR(VLOOKUP($E260,题目信息!$B$5:$L$253,11,0),10)) -> 10 | L260: =IF(OR($J260="",$K260=""),"",$J260/$K260) -> 0 | M260: 规则自动判分 | N260: 模型无有效回答 | O260: 2026-10-23 | P260: 自动写入·调用失败
B261: R0257 | C261: M02 | D261: =IF($C261="","",IFERROR(VLOOKUP($C261,模型信息!$B$5:$C$24,2,0),"未登记")) -> GLM-5.3 | E261: CON17 | F261: =IF($E261="","",IFERROR(VLOOKUP($E261,题目信息!$B$5:$C$253,2,0),"未登记")) -> 约束处理 | G261: 1 | H261: During my master’s degree, I learned SQL and R, which gave me a solid foundation in programming fundamentals. 😊 I now intend to build on those skills by applying them in Java. 😊 This will help me deepen my understanding of software development. 😊 It will also allow me to connect programming basics with practical development work. 😊 By doing so, I can strengthen both my technical confidence and my problem-solving ability. 😊 This foundation will also help me eat up new learning opportunities and grow as a developer. 😊 | I261: =IF($E261="","",IFERROR(VLOOKUP($E261,题目信息!$B$5:$J$253,9,0),"")) -> 约束: format:emoji,sentence:keyword | J261: 10 | K261: =IF($E261="","",IFERROR(VLOOKUP($E261,题目信息!$B$5:$L$253,11,0),10)) -> 10 | L261: =IF(OR($J261="",$K261=""),"",$J261/$K261) -> 1 | M261: 规则自动判分 | N261: 官方校验通过 2/2 | O261: 2026-10-23 | P261: 自动写入 | Q261: 1456 | R261: 2129 | S261: 0.0246 | W261: 9.68
B262: R0258 | C262: M02 | D262: =IF($C262="","",IFERROR(VLOOKUP($C262,模型信息!$B$5:$C$24,2,0),"未登记")) -> GLM-5.3 | E262: CON18 | F262: =IF($E262="","",IFERROR(VLOOKUP($E262,题目信息!$B$5:$C$253,2,0),"未登记")) -> 约束处理 | G262: 1 | H262: * 1901 — Orbital surveyor catches unnatural glint: mirrored ocean, geometric reefs, impossible city-lights. - Scientists dismiss glint; military logs classify anomaly. * 1907 — Probe swarm maps second hemisphere: colossal canal rings, bioluminescent forests, silent megafauna. - Cartographers name continent "Aurelia"; censors bury charts. * 1914 — First landing at Glass Harbor: airship descends through violet cloud-sea, crew plants flag beside singing stones. - Contact: Aurelians exchange crystal maps; language composed entirely verbs. * 1923 — Satellite relay links worlds: radio handshake, shared eclipse festival, trade salt-for-starlight. - Epidemic scare: quarantine moons; diplomatic silence. * 1938 — Aurelian sky-elevators rise: floating cities anchor to mountain spines, magnetic rivers reverse. - Joint expedition charts Hollow Meridian; discovers fossil satellites. * 1955 — Treaty divides orbit: no weapons above cloudline, new world admitted to League. - Historians rewrite maps; old Earth textbooks become collector relics. | I262: =IF($E262="","",IFERROR(VLOOKUP($E262,题目信息!$B$5:$J$253,9,0),"")) -> 约束: format:sub-bullets,ratio:stop_words | J262: 10 | K262: =IF($E262="","",IFERROR(VLOOKUP($E262,题目信息!$B$5:$L$253,11,0),10)) -> 10 | L262: =IF(OR($J262="",$K262=""),"",$J262/$K262) -> 1 | M262: 规则自动判分 | N262: 官方校验通过 2/2 | O262: 2026-10-23 | P262: 自动写入 | Q262: 1454 | R262: 3140 | S262: 0.0344 | W262: 18.1
B263: R0259 | C263: M02 | D263: =IF($C263="","",IFERROR(VLOOKUP($C263,模型信息!$B$5:$C$24,2,0),"未登记")) -> GLM-5.3 | E263: CON19 | F263: =IF($E263="","",IFERROR(VLOOKUP($E263,题目信息!$B$5:$C$253,2,0),"未登记")) -> 约束处理 | G263: 1 | H263: Describe Fatherland – All Russia (Otechestvo – Vsya Rossiya) as a broad **centrist, patriotic-statist** bloc rather than a tightly doctrinaire party. Its main ideological features were **statism** (a strong state and managed reform), **social conservatism** and patriotic values, **moderate nationalism**, **regionalism/federalism** tied to regional elites, and **welfare populism** promising social guarantees. It was pragmatic and anti-radical-liberal in tone but not communist; it functioned as a governing-elite coalition and later merged into United Russia, so its ideology was flexible. In illustrating its broad-tent character, one could name Emma, Liam, Sophia, Jackson, Olivia, Noah, Ava, Lucas, Isabella, Mason, Mia, Ethan, Charlotte, Alexander, Amelia, Benjamin, Harper, Leo, Zoe, Daniel, Chloe, Samuel, Lily, Matthew, Grace, Owen, Abigail, Gabriel, Ella, Jacob, Scarlett, Nathan, Victoria, Elijah, Layla, Nicholas, Audrey, David, Hannah, and Christopher. | I263: =IF($E263="","",IFERROR(VLOOKUP($E263,题目信息!$B$5:$J$253,9,0),"")) -> 约束: words:start_verb,count:person_names | J263: 5 | K263: =IF($E263="","",IFERROR(VLOOKUP($E263,题目信息!$B$5:$L$253,11,0),10)) -> 10 | L263: =IF(OR($J263="",$K263=""),"",$J263/$K263) -> 0.5 | M263: 规则自动判分 | N263: 官方校验通过 1/2 | O263: 2026-10-23 | P263: 自动写入 | Q263: 1518 | R263: 3345 | S263: 0.0366 | W263: 19.78
...

Sheet 能力评分汇总
B2: 能力评分汇总（公式自动计算，无需手工填写）
B4: 模型ID | C4: 模型名称 | D4: 语言理解 | E4: 信息提取 | F4: 创造力 | G4: 指令遵循 | H4: 复杂推理 | I4: 约束处理 | J4: 结构化输出 | K4: 长文本组织 | L4: 上下文利用 | M4: 信息检索 | N4: 评估 | O4: 错误识别 | P4: 文档解析 | Q4: 综合得分率 | R4: 测试记录数 | S4: 排名 | T4: 输入tokens合计 | U4: 输出tokens合计 | V4: 费用合计(元)
B5: =IF(模型信息!B5="","",模型信息!B5) -> M01 | C5: =IF($B5="","",IFERROR(VLOOKUP($B5,模型信息!$B$5:$C$24,2,0),"")) -> DeepSeek-V4-Flash | D5: =IF($B5="","",IFERROR(AVERAGEIFS(测试记录!$L$5:$L$1702,测试记录!$C$5:$C$1702,$B5,测试记录!$F$5:$F$1702,D$4),"")) -> 0.95 | E5: =IF($B5="","",IFERROR(AVERAGEIFS(测试记录!$L$5:$L$1702,测试记录!$C$5:$C$1702,$B5,测试记录!$F$5:$F$1702,E$4),"")) -> 0.835 | F5: =IF($B5="","",IFERROR(AVERAGEIFS(测试记录!$L$5:$L$1702,测试记录!$C$5:$C$1702,$B5,测试记录!$F$5:$F$1702,F$4),"")) -> 0.8 | G5: =IF($B5="","",IFERROR(AVERAGEIFS(测试记录!$L$5:$L$1702,测试记录!$C$5:$C$1702,$B5,测试记录!$F$5:$F$1702,G$4),"")) -> 0.7 | H5: =IF($B5="","",IFERROR(AVERAGEIFS(测试记录!$L$5:$L$1702,测试记录!$C$5:$C$1702,$B5,测试记录!$F$5:$F$1702,H$4),"")) -> 0.85 | I5: =IF($B5="","",IFERROR(AVERAGEIFS(测试记录!$L$5:$L$1702,测试记录!$C$5:$C$1702,$B5,测试记录!$F$5:$F$1702,I$4),"")) -> 0.625 | J5: =IF($B5="","",IFERROR(AVERAGEIFS(测试记录!$L$5:$L$1702,测试记录!$C$5:$C$1702,$B5,测试记录!$F$5:$F$1702,J$4),"")) -> 1 | K5: =IF($B5="","",IFERROR(AVERAGEIFS(测试记录!$L$5:$L$1702,测试记录!$C$5:$C$1702,$B5,测试记录!$F$5:$F$1702,K$4),"")) -> 0.373 | ... P5: =IF($B5="","",IFERROR(AVERAGEIFS(测试记录!$L$5:$L$1702,测试记录!$C$5:$C$1702,$B5,测试记录!$F$5:$F$1702,P$4),"")) | Q5: =IF($B5="","",IFERROR(AVERAGEIFS(测试记录!$L$5:$L$1702,测试记录!$C$5:$C$1702,$B5),"")) -> 0.746875 | R5: =IF($B5="","",COUNTIFS(测试记录!$C$5:$C$1702,$B5)) -> 240 | S5: =IF($Q5="","",IFERROR(RANK($Q5,$Q$5:$Q$23),"")) -> 3 | T5: =IF($B5="","",SUMIFS(测试记录!$Q$5:$Q$1702,测试记录!$C$5:$C$1702,$B5)) -> 709083 | U5: =IF($B5="","",SUMIFS(测试记录!$R$5:$R$1702,测试记录!$C$5:$C$1702,$B5)) -> 410891 | V5: =IF($B5="","",SUMIFS(测试记录!$S$5:$S$1702,测试记录!$C$5:$C$1702,$B5)+SUMIFS(测试记录!$V$5:$V$1702,测试记录!$C$5:$C$1702,$B5)) -> 0.8131
B6: =IF(模型信息!B6="","",模型信息!B6) -> M02 | C6: =IF($B6="","",IFERROR(VLOOKUP($B6,模型信息!$B$5:$C$24,2,0),"")) -> GLM-5.3 | D6: =IF($B6="","",IFERROR(AVERAGEIFS(测试记录!$L$5:$L$1702,测试记录!$C$5:$C$1702,$B6,测试记录!$F$5:$F$1702,D$4),"")) -> 0.95 | E6: =IF($B6="","",IFERROR(AVERAGEIFS(测试记录!$L$5:$L$1702,测试记录!$C$5:$C$1702,$B6,测试记录!$F$5:$F$1702,E$4),"")) -> 0.739 | F6: =IF($B6="","",IFERROR(AVERAGEIFS(测试记录!$L$5:$L$1702,测试记录!$C$5:$C$1702,$B6,测试记录!$F$5:$F$1702,F$4),"")) -> 0.83 | G6: =IF($B6="","",IFERROR(AVERAGEIFS(测试记录!$L$5:$L$1702,测试记录!$C$5:$C$1702,$B6,测试记录!$F$5:$F$1702,G$4),"")) -> 0.8 | H6: =IF($B6="","",IFERROR(AVERAGEIFS(测试记录!$L$5:$L$1702,测试记录!$C$5:$C$1702,$B6,测试记录!$F$5:$F$1702,H$4),"")) -> 0.95 | I6: =IF($B6="","",IFERROR(AVERAGEIFS(测试记录!$L$5:$L$1702,测试记录!$C$5:$C$1702,$B6,测试记录!$F$5:$F$1702,I$4),"")) -> 0.625 | J6: =IF($B6="","",IFERROR(AVERAGEIFS(测试记录!$L$5:$L$1702,测试记录!$C$5:$C$1702,$B6,测试记录!$F$5:$F$1702,J$4),"")) -> 0.95 | K6: =IF($B6="","",IFERROR(AVERAGEIFS(测试记录!$L$5:$L$1702,测试记录!$C$5:$C$1702,$B6,测试记录!$F$5:$F$1702,K$4),"")) -> 0.2405 | ... P6: =IF($B6="","",IFERROR(AVERAGEIFS(测试记录!$L$5:$L$1702,测试记录!$C$5:$C$1702,$B6,测试记录!$F$5:$F$1702,P$4),"")) | Q6: =IF($B6="","",IFERROR(AVERAGEIFS(测试记录!$L$5:$L$1702,测试记录!$C$5:$C$1702,$B6),"")) -> 0.73466667 | R6: =IF($B6="","",COUNTIFS(测试记录!$C$5:$C$1702,$B6)) -> 240 | S6: =IF($Q6="","",IFERROR(RANK($Q6,$Q$5:$Q$23),"")) -> 4 | T6: =IF($B6="","",SUMIFS(测试记录!$Q$5:$Q$1702,测试记录!$C$5:$C$1702,$B6)) -> 587476 | U6: =IF($B6="","",SUMIFS(测试记录!$R$5:$R$1702,测试记录!$C$5:$C$1702,$B6)) -> 309315 | V6: =IF($B6="","",SUMIFS(测试记录!$S$5:$S$1702,测试记录!$C$5:$C$1702,$B6)+SUMIFS(测试记录!$V$5:$V$1702,测试记录!$C$5:$C$1702,$B6)) -> 4.6187
B7: =IF(模型信息!B7="","",模型信息!B7) -> M03 | C7: =IF($B7="","",IFERROR(VLOOKUP($B7,模型信息!$B$5:$C$24,2,0),"")) -> GLM-5.3-Flash | D7: =IF($B7="","",IFERROR(AVERAGEIFS(测试记录!$L$5:$L$1702,测试记录!$C$5:$C$1702,$B7,测试记录!$F$5:$F$1702,D$4),"")) -> 0.9 | E7: =IF($B7="","",IFERROR(AVERAGEIFS(测试记录!$L$5:$L$1702,测试记录!$C$5:$C$1702,$B7,测试记录!$F$5:$F$1702,E$4),"")) -> 0.7175 | F7: =IF($B7="","",IFERROR(AVERAGEIFS(测试记录!$L$5:$L$1702,测试记录!$C$5:$C$1702,$B7,测试记录!$F$5:$F$1702,F$4),"")) -> 0.82 | G7: =IF($B7="","",IFERROR(AVERAGEIFS(测试记录!$L$5:$L$1702,测试记录!$C$5:$C$1702,$B7,测试记录!$F$5:$F$1702,G$4),"")) -> 0.55 | H7: =IF($B7="","",IFERROR(AVERAGEIFS(测试记录!$L$5:$L$1702,测试记录!$C$5:$C$1702,$B7,测试记录!$F$5:$F$1702,H$4),"")) -> 0.57894737 | I7: =IF($B7="","",IFERROR(AVERAGEIFS(测试记录!$L$5:$L$1702,测试记录!$C$5:$C$1702,$B7,测试记录!$F$5:$F$1702,I$4),"")) -> 0.575 | J7: =IF($B7="","",IFERROR(AVERAGEIFS(测试记录!$L$5:$L$1702,测试记录!$C$5:$C$1702,$B7,测试记录!$F$5:$F$1702,J$4),"")) -> 0.95 | K7: =IF($B7="","",IFERROR(AVERAGEIFS(测试记录!$L$5:$L$1702,测试记录!$C$5:$C$1702,$B7,测试记录!$F$5:$F$1702,K$4),"")) -> 0.2845 | ... P7: =IF($B7="","",IFERROR(AVERAGEIFS(测试记录!$L$5:$L$1702,测试记录!$C$5:$C$1702,$B7,测试记录!$F$5:$F$1702,P$4),"")) | Q7: =IF($B7="","",IFERROR(AVERAGEIFS(测试记录!$L$5:$L$1702,测试记录!$C$5:$C$1702,$B7),"")) -> 0.67464435 | R7: =IF($B7="","",COUNTIFS(测试记录!$C$5:$C$1702,$B7)) -> 239 | S7: =IF($Q7="","",IFERROR(RANK($Q7,$Q$5:$Q$23),"")) -> 7 | T7: =IF($B7="","",SUMIFS(测试记录!$Q$5:$Q$1702,测试记录!$C$5:$C$1702,$B7)) -> 609018 | U7: =IF($B7="","",SUMIFS(测试记录!$R$5:$R$1702,测试记录!$C$5:$C$1702,$B7)) -> 441317 | V7: =IF($B7="","",SUMIFS(测试记录!$S$5:$S$1702,测试记录!$C$5:$C$1702,$B7)+SUMIFS(测试记录!$V$5:$V$1702,测试记录!$C$5:$C$1702,$B7)) -> 0.9004
B8: =IF(模型信息!B8="","",模型信息!B8) -> M04 | C8: =IF($B8="","",IFERROR(VLOOKUP($B8,模型信息!$B$5:$C$24,2,0),"")) -> Hy3 | D8: =IF($B8="","",IFERROR(AVERAGEIFS(测试记录!$L$5:$L$1702,测试记录!$C$5:$C$1702,$B8,测试记录!$F$5:$F$1702,D$4),"")) -> 0.95 | E8: =IF($B8="","",IFERROR(AVERAGEIFS(测试记录!$L$5:$L$1702,测试记录!$C$5:$C$1702,$B8,测试记录!$F$5:$F$1702,E$4),"")) -> 0.8355 | F8: =IF($B8="","",IFERROR(AVERAGEIFS(测试记录!$L$5:$L$1702,测试记录!$C$5:$C$1702,$B8,测试记录!$F$5:$F$1702,F$4),"")) -> 0.695 | G8: =IF($B8="","",IFERROR(AVERAGEIFS(测试记录!$L$5:$L$1702,测试记录!$C$5:$C$1702,$B8,测试记录!$F$5:$F$1702,G$4),"")) -> 0.85 | H8: =IF($B8="","",IFERROR(AVERAGEIFS(测试记录!$L$5:$L$1702,测试记录!$C$5:$C$1702,$B8,测试记录!$F$5:$F$1702,H$4),"")) -> 0.8 | I8: =IF($B8="","",IFERROR(AVERAGEIFS(测试记录!$L$5:$L$1702,测试记录!$C$5:$C$1702,$B8,测试记录!$F$5:$F$1702,I$4),"")) -> 0.725 | J8: =IF($B8="","",IFERROR(AVERAGEIFS(测试记录!$L$5:$L$1702,测试记录!$C$5:$C$1702,$B8,测试记录!$F$5:$F$1702,J$4),"")) -> 1 | K8: =IF($B8="","",IFERROR(AVERAGEIFS(测试记录!$L$5:$L$1702,测试记录!$C$5:$C$1702,$B8,测试记录!$F$5:$F$1702,K$4),"")) -> 0.4035 | ... P8: =IF($B8="","",IFERROR(AVERAGEIFS(测试记录!$L$5:$L$1702,测试记录!$C$5:$C$1702,$B8,测试记录!$F$5:$F$1702,P$4),"")) | Q8: =IF($B8="","",IFERROR(AVERAGEIFS(测试记录!$L$5:$L$1702,测试记录!$C$5:$C$1702,$B8),"")) -> 0.75770833 | R8: =IF($B8="","",COUNTIFS(测试记录!$C$5:$C$1702,$B8)) -> 240 | S8: =IF($Q8="","",IFERROR(RANK($Q8,$Q$5:$Q$23),"")) -> 2 | T8: =IF($B8="","",SUMIFS(测试记录!$Q$5:$Q$1702,测试记录!$C$5:$C$1702,$B8)) -> 700339 | U8: =IF($B8="","",SUMIFS(测试记录!$R$5:$R$1702,测试记录!$C$5:$C$1702,$B8)) -> 426829 | V8: =IF($B8="","",SUMIFS(测试记录!$S$5:$S$1702,测试记录!$C$5:$C$1702,$B8)+SUMIFS(测试记录!$V$5:$V$1702,测试记录!$C$5:$C$1702,$B8)) -> 0.8313
B9: =IF(模型信息!B9="","",模型信息!B9) -> M06 | C9: =IF($B9="","",IFERROR(VLOOKUP($B9,模型信息!$B$5:$C$24,2,0),"")) -> MiniMax-M3 | D9: =IF($B9="","",IFERROR(AVERAGEIFS(测试记录!$L$5:$L$1702,测试记录!$C$5:$C$1702,$B9,测试记录!$F$5:$F$1702,D$4),"")) -> 0.8 | E9: =IF($B9="","",IFERROR(AVERAGEIFS(测试记录!$L$5:$L$1702,测试记录!$C$5:$C$1702,$B9,测试记录!$F$5:$F$1702,E$4),"")) -> 0.6065 | F9: =IF($B9="","",IFERROR(AVERAGEIFS(测试记录!$L$5:$L$1702,测试记录!$C$5:$C$1702,$B9,测试记录!$F$5:$F$1702,F$4),"")) -> 0.58 | G9: =IF($B9="","",IFERROR(AVERAGEIFS(测试记录!$L$5:$L$1702,测试记录!$C$5:$C$1702,$B9,测试记录!$F$5:$F$1702,G$4),"")) -> 0.7 | H9: =IF($B9="","",IFERROR(AVERAGEIFS(测试记录!$L$5:$L$1702,测试记录!$C$5:$C$1702,$B9,测试记录!$F$5:$F$1702,H$4),"")) -> 0.95 | I9: =IF($B9="","",IFERROR(AVERAGEIFS(测试记录!$L$5:$L$1702,测试记录!$C$5:$C$1702,$B9,测试记录!$F$5:$F$1702,I$4),"")) -> 0.525 | J9: =IF($B9="","",IFERROR(AVERAGEIFS(测试记录!$L$5:$L$1702,测试记录!$C$5:$C$1702,$B9,测试记录!$F$5:$F$1702,J$4),"")) -> 0.95 | K9: =IF($B9="","",IFERROR(AVERAGEIFS(测试记录!$L$5:$L$1702,测试记录!$C$5:$C$1702,$B9,测试记录!$F$5:$F$1702,K$4),"")) -> 0.256 | ... P9: =IF($B9="","",IFERROR(AVERAGEIFS(测试记录!$L$5:$L$1702,测试记录!$C$5:$C$1702,$B9,测试记录!$F$5:$F$1702,P$4),"")) | Q9: =IF($B9="","",IFERROR(AVERAGEIFS(测试记录!$L$5:$L$1702,测试记录!$C$5:$C$1702,$B9),"")) -> 0.64754167 | R9: =IF($B9="","",COUNTIFS(测试记录!$C$5:$C$1702,$B9)) -> 240 | S9: =IF($Q9="","",IFERROR(RANK($Q9,$Q$5:$Q$23),"")) -> 8 | T9: =IF($B9="","",SUMIFS(测试记录!$Q$5:$Q$1702,测试记录!$C$5:$C$1702,$B9)) -> 440642 | U9: =IF($B9="","",SUMIFS(测试记录!$R$5:$R$1702,测试记录!$C$5:$C$1702,$B9)) -> 222331 | V9: =IF($B9="","",SUMIFS(测试记录!$S$5:$S$1702,测试记录!$C$5:$C$1702,$B9)+SUMIFS(测试记录!$V$5:$V$1702,测试记录!$C$5:$C$1702,$B9)) -> 0.9655
B10: =IF(模型信息!B10="","",模型信息!B10) -> M07 | C10: =IF($B10="","",IFERROR(VLOOKUP($B10,模型信息!$B$5:$C$24,2,0),"")) -> Kimi-K3 | D10: =IF($B10="","",IFERROR(AVERAGEIFS(测试记录!$L$5:$L$1702,测试记录!$C$5:$C$1702,$B10,测试记录!$F$5:$F$1702,D$4),"")) -> 0.95 | E10: =IF($B10="","",IFERROR(AVERAGEIFS(测试记录!$L$5:$L$1702,测试记录!$C$5:$C$1702,$B10,测试记录!$F$5:$F$1702,E$4),"")) -> 0.847 | F10: =IF($B10="","",IFERROR(AVERAGEIFS(测试记录!$L$5:$L$1702,测试记录!$C$5:$C$1702,$B10,测试记录!$F$5:$F$1702,F$4),"")) -> 0.53 | G10: =IF($B10="","",IFERROR(AVERAGEIFS(测试记录!$L$5:$L$1702,测试记录!$C$5:$C$1702,$B10,测试记录!$F$5:$F$1702,G$4),"")) -> 0.52631579 | H10: =IF($B10="","",IFERROR(AVERAGEIFS(测试记录!$L$5:$L$1702,测试记录!$C$5:$C$1702,$B10,测试记录!$F$5:$F$1702,H$4),"")) -> 0.9 | I10: =IF($B10="","",IFERROR(AVERAGEIFS(测试记录!$L$5:$L$1702,测试记录!$C$5:$C$1702,$B10,测试记录!$F$5:$F$1702,I$4),"")) -> 0.6 | J10: =IF($B10="","",IFERROR(AVERAGEIFS(测试记录!$L$5:$L$1702,测试记录!$C$5:$C$1702,$B10,测试记录!$F$5:$F$1702,J$4),"")) -> 1 | K10: =IF($B10="","",IFERROR(AVERAGEIFS(测试记录!$L$5:$L$1702,测试记录!$C$5:$C$1702,$B10,测试记录!$F$5:$F$1702,K$4),"")) -> 0.2505 | ... P10: =IF($B10="","",IFERROR(AVERAGEIFS(测试记录!$L$5:$L$1702,测试记录!$C$5:$C$1702,$B10,测试记录!$F$5:$F$1702,P$4),"")) | Q10: =IF($B10="","",IFERROR(AVERAGEIFS(测试记录!$L$5:$L$1702,测试记录!$C$5:$C$1702,$B10),"")) -> 0.68635983 | R10: =IF($B10="","",COUNTIFS(测试记录!$C$5:$C$1702,$B10)) -> 239 | S10: =IF($Q10="","",IFERROR(RANK($Q10,$Q$5:$Q$23),"")) -> 6 | T10: =IF($B10="","",SUMIFS(测试记录!$Q$5:$Q$1702,测试记录!$C$5:$C$1702,$B10)) -> 421610 | U10: =IF($B10="","",SUMIFS(测试记录!$R$5:$R$1702,测试记录!$C$5:$C$1702,$B10)) -> 175950 | V10: =IF($B10="","",SUMIFS(测试记录!$S$5:$S$1702,测试记录!$C$5:$C$1702,$B10)+SUMIFS(测试记录!$V$5:$V$1702,测试记录!$C$5:$C$1702,$B10)) -> 8.9951
B11: =IF(模型信息!B11="","",模型信息!B11) -> M08 | C11: =IF($B11="","",IFERROR(VLOOKUP($B11,模型信息!$B$5:$C$24,2,0),"")) -> MiMo-V2.5 | D11: =IF($B11="","",IFERROR(AVERAGEIFS(测试记录!$L$5:$L$1702,测试记录!$C$5:$C$1702,$B11,测试记录!$F$5:$F$1702,D$4),"")) -> 0.95 | E11: =IF($B11="","",IFERROR(AVERAGEIFS(测试记录!$L$5:$L$1702,测试记录!$C$5:$C$1702,$B11,测试记录!$F$5:$F$1702,E$4),"")) -> 0.825 | F11: =IF($B11="","",IFERROR(AVERAGEIFS(测试记录!$L$5:$L$1702,测试记录!$C$5:$C$1702,$B11,测试记录!$F$5:$F$1702,F$4),"")) -> 0.615 | G11: =IF($B11="","",IFERROR(AVERAGEIFS(测试记录!$L$5:$L$1702,测试记录!$C$5:$C$1702,$B11,测试记录!$F$5:$F$1702,G$4),"")) -> 0.8 | H11: =IF($B11="","",IFERROR(AVERAGEIFS(测试记录!$L$5:$L$1702,测试记录!$C$5:$C$1702,$B11,测试记录!$F$5:$F$1702,H$4),"")) -> 0.85 | I11: =IF($B11="","",IFERROR(AVERAGEIFS(测试记录!$L$5:$L$1702,测试记录!$C$5:$C$1702,$B11,测试记录!$F$5:$F$1702,I$4),"")) -> 0.775 | J11: =IF($B11="","",IFERROR(AVERAGEIFS(测试记录!$L$5:$L$1702,测试记录!$C$5:$C$1702,$B11,测试记录!$F$5:$F$1702,J$4),"")) -> 1 | K11: =IF($B11="","",IFERROR(AVERAGEIFS(测试记录!$L$5:$L$1702,测试记录!$C$5:$C$1702,$B11,测试记录!$F$5:$F$1702,K$4),"")) -> 0.4455 | ... P11: =IF($B11="","",IFERROR(AVERAGEIFS(测试记录!$L$5:$L$1702,测试记录!$C$5:$C$1702,$B11,测试记录!$F$5:$F$1702,P$4),"")) | Q11: =IF($B11="","",IFERROR(AVERAGEIFS(测试记录!$L$5:$L$1702,测试记录!$C$5:$C$1702,$B11),"")) -> 0.76179167 | R11: =IF($B11="","",COUNTIFS(测试记录!$C$5:$C$1702,$B11)) -> 240 | S11: =IF($Q11="","",IFERROR(RANK($Q11,$Q$5:$Q$23),"")) -> 1 | T11: =IF($B11="","",SUMIFS(测试记录!$Q$5:$Q$1702,测试记录!$C$5:$C$1702,$B11)) -> 696786 | U11: =IF($B11="","",SUMIFS(测试记录!$R$5:$R$1702,测试记录!$C$5:$C$1702,$B11)) -> 401210 | V11: =IF($B11="","",SUMIFS(测试记录!$S$5:$S$1702,测试记录!$C$5:$C$1702,$B11)+SUMIFS(测试记录!$V$5:$V$1702,测试记录!$C$5:$C$1702,$B11)) -> 1.592
B12: =IF(模型信息!B12="","",模型信息!B12) | C12: 平均 | D12: =AVERAGE(D5:D11) -> 0.92142857 | E12: =AVERAGE(E5:E11) -> 0.77221429 | F12: =AVERAGE(F5:F11) -> 0.69571429 | G12: =AVERAGE(G5:G11) -> 0.7037594 | H12: =AVERAGE(H5:H11) -> 0.83984962 | I12: =AVERAGE(I5:I11) -> 0.63571429 | J12: =AVERAGE(J5:J11) -> 0.97857143 | K12: =AVERAGE(K5:K11) -> 0.32192857 | ... O12: =AVERAGE(O5:O11) -> 0.83571429 | Q12: =AVERAGE(Q5:Q11) -> 0.71565536 | S12: =IF($Q12="","",IFERROR(RANK($Q12,$Q$5:$Q$23),"")) -> 5 | T12: =IF($B12="","",SUMIFS(测试记录!$Q$5:$Q$1702,测试记录!$C$5:$C$1702,$B12)) | U12: =IF($B12="","",SUMIFS(测试记录!$R$5:$R$1702,测试记录!$C$5:$C$1702,$B12)) | V12: =IF($B12="","",SUMIFS(测试记录!$S$5:$S$1702,测试记录!$C$5:$C$1702,$B12)+SUMIFS(测试记录!$V$5:$V$1702,测试记录!$C$5:$C$1702,$B12))
B13: =IF(模型信息!B13="","",模型信息!B13) | C13: =IF($B13="","",IFERROR(VLOOKUP($B13,模型信息!$B$5:$C$24,2,0),"")) | D13: =IF($B13="","",IFERROR(AVERAGEIFS(测试记录!$L$5:$L$1702,测试记录!$C$5:$C$1702,$B13,测试记录!$F$5:$F$1702,D$4),"")) | E13: =IF($B13="","",IFERROR(AVERAGEIFS(测试记录!$L$5:$L$1702,测试记录!$C$5:$C$1702,$B13,测试记录!$F$5:$F$1702,E$4),"")) | F13: =IF($B13="","",IFERROR(AVERAGEIFS(测试记录!$L$5:$L$1702,测试记录!$C$5:$C$1702,$B13,测试记录!$F$5:$F$1702,F$4),"")) | G13: =IF($B13="","",IFERROR(AVERAGEIFS(测试记录!$L$5:$L$1702,测试记录!$C$5:$C$1702,$B13,测试记录!$F$5:$F$1702,G$4),"")) | H13: =IF($B13="","",IFERROR(AVERAGEIFS(测试记录!$L$5:$L$1702,测试记录!$C$5:$C$1702,$B13,测试记录!$F$5:$F$1702,H$4),"")) | I13: =IF($B13="","",IFERROR(AVERAGEIFS(测试记录!$L$5:$L$1702,测试记录!$C$5:$C$1702,$B13,测试记录!$F$5:$F$1702,I$4),"")) | J13: =IF($B13="","",IFERROR(AVERAGEIFS(测试记录!$L$5:$L$1702,测试记录!$C$5:$C$1702,$B13,测试记录!$F$5:$F$1702,J$4),"")) | K13: =IF($B13="","",IFERROR(AVERAGEIFS(测试记录!$L$5:$L$1702,测试记录!$C$5:$C$1702,$B13,测试记录!$F$5:$F$1702,K$4),"")) | ... P13: =IF($B13="","",IFERROR(AVERAGEIFS(测试记录!$L$5:$L$1702,测试记录!$C$5:$C$1702,$B13,测试记录!$F$5:$F$1702,P$4),"")) | Q13: =IF($B13="","",IFERROR(AVERAGEIFS(测试记录!$L$5:$L$1702,测试记录!$C$5:$C$1702,$B13),"")) | R13: =IF($B13="","",COUNTIFS(测试记录!$C$5:$C$1702,$B13)) | S13: =IF($Q13="","",IFERROR(RANK($Q13,$Q$5:$Q$23),"")) | T13: =IF($B13="","",SUMIFS(测试记录!$Q$5:$Q$1702,测试记录!$C$5:$C$1702,$B13)) | U13: =IF($B13="","",SUMIFS(测试记录!$R$5:$R$1702,测试记录!$C$5:$C$1702,$B13)) | V13: =IF($B13="","",SUMIFS(测试记录!$S$5:$S$1702,测试记录!$C$5:$C$1702,$B13)+SUMIFS(测试记录!$V$5:$V$1702,测试记录!$C$5:$C$1702,$B13))
B14: =IF(模型信息!B14="","",模型信息!B14) | C14: =IF($B14="","",IFERROR(VLOOKUP($B14,模型信息!$B$5:$C$24,2,0),"")) | D14: =IF($B14="","",IFERROR(AVERAGEIFS(测试记录!$L$5:$L$1702,测试记录!$C$5:$C$1702,$B14,测试记录!$F$5:$F$1702,D$4),"")) | E14: =IF($B14="","",IFERROR(AVERAGEIFS(测试记录!$L$5:$L$1702,测试记录!$C$5:$C$1702,$B14,测试记录!$F$5:$F$1702,E$4),"")) | F14: =IF($B14="","",IFERROR(AVERAGEIFS(测试记录!$L$5:$L$1702,测试记录!$C$5:$C$1702,$B14,测试记录!$F$5:$F$1702,F$4),"")) | G14: =IF($B14="","",IFERROR(AVERAGEIFS(测试记录!$L$5:$L$1702,测试记录!$C$5:$C$1702,$B14,测试记录!$F$5:$F$1702,G$4),"")) | H14: =IF($B14="","",IFERROR(AVERAGEIFS(测试记录!$L$5:$L$1702,测试记录!$C$5:$C$1702,$B14,测试记录!$F$5:$F$1702,H$4),"")) | I14: =IF($B14="","",IFERROR(AVERAGEIFS(测试记录!$L$5:$L$1702,测试记录!$C$5:$C$1702,$B14,测试记录!$F$5:$F$1702,I$4),"")) | J14: =IF($B14="","",IFERROR(AVERAGEIFS(测试记录!$L$5:$L$1702,测试记录!$C$5:$C$1702,$B14,测试记录!$F$5:$F$1702,J$4),"")) | K14: =IF($B14="","",IFERROR(AVERAGEIFS(测试记录!$L$5:$L$1702,测试记录!$C$5:$C$1702,$B14,测试记录!$F$5:$F$1702,K$4),"")) | ... P14: =IF($B14="","",IFERROR(AVERAGEIFS(测试记录!$L$5:$L$1702,测试记录!$C$5:$C$1702,$B14,测试记录!$F$5:$F$1702,P$4),"")) | Q14: =IF($B14="","",IFERROR(AVERAGEIFS(测试记录!$L$5:$L$1702,测试记录!$C$5:$C$1702,$B14),"")) | R14: =IF($B14="","",COUNTIFS(测试记录!$C$5:$C$1702,$B14)) | S14: =IF($Q14="","",IFERROR(RANK($Q14,$Q$5:$Q$23),"")) | T14: =IF($B14="","",SUMIFS(测试记录!$Q$5:$Q$1702,测试记录!$C$5:$C$1702,$B14)) | U14: =IF($B14="","",SUMIFS(测试记录!$R$5:$R$1702,测试记录!$C$5:$C$1702,$B14)) | V14: =IF($B14="","",SUMIFS(测试记录!$S$5:$S$1702,测试记录!$C$5:$C$1702,$B14)+SUMIFS(测试记录!$V$5:$V$1702,测试记录!$C$5:$C$1702,$B14))
B15: =IF(模型信息!B15="","",模型信息!B15) | C15: =IF($B15="","",IFERROR(VLOOKUP($B15,模型信息!$B$5:$C$24,2,0),"")) | D15: =IF($B15="","",IFERROR(AVERAGEIFS(测试记录!$L$5:$L$1702,测试记录!$C$5:$C$1702,$B15,测试记录!$F$5:$F$1702,D$4),"")) | E15: =IF($B15="","",IFERROR(AVERAGEIFS(测试记录!$L$5:$L$1702,测试记录!$C$5:$C$1702,$B15,测试记录!$F$5:$F$1702,E$4),"")) | F15: =IF($B15="","",IFERROR(AVERAGEIFS(测试记录!$L$5:$L$1702,测试记录!$C$5:$C$1702,$B15,测试记录!$F$5:$F$1702,F$4),"")) | G15: =IF($B15="","",IFERROR(AVERAGEIFS(测试记录!$L$5:$L$1702,测试记录!$C$5:$C$1702,$B15,测试记录!$F$5:$F$1702,G$4),"")) | H15: =IF($B15="","",IFERROR(AVERAGEIFS(测试记录!$L$5:$L$1702,测试记录!$C$5:$C$1702,$B15,测试记录!$F$5:$F$1702,H$4),"")) | I15: =IF($B15="","",IFERROR(AVERAGEIFS(测试记录!$L$5:$L$1702,测试记录!$C$5:$C$1702,$B15,测试记录!$F$5:$F$1702,I$4),"")) | J15: =IF($B15="","",IFERROR(AVERAGEIFS(测试记录!$L$5:$L$1702,测试记录!$C$5:$C$1702,$B15,测试记录!$F$5:$F$1702,J$4),"")) | K15: =IF($B15="","",IFERROR(AVERAGEIFS(测试记录!$L$5:$L$1702,测试记录!$C$5:$C$1702,$B15,测试记录!$F$5:$F$1702,K$4),"")) | ... P15: =IF($B15="","",IFERROR(AVERAGEIFS(测试记录!$L$5:$L$1702,测试记录!$C$5:$C$1702,$B15,测试记录!$F$5:$F$1702,P$4),"")) | Q15: =IF($B15="","",IFERROR(AVERAGEIFS(测试记录!$L$5:$L$1702,测试记录!$C$5:$C$1702,$B15),"")) | R15: =IF($B15="","",COUNTIFS(测试记录!$C$5:$C$1702,$B15)) | S15: =IF($Q15="","",IFERROR(RANK($Q15,$Q$5:$Q$23),"")) | T15: =IF($B15="","",SUMIFS(测试记录!$Q$5:$Q$1702,测试记录!$C$5:$C$1702,$B15)) | U15: =IF($B15="","",SUMIFS(测试记录!$R$5:$R$1702,测试记录!$C$5:$C$1702,$B15)) | V15: =IF($B15="","",SUMIFS(测试记录!$S$5:$S$1702,测试记录!$C$5:$C$1702,$B15)+SUMIFS(测试记录!$V$5:$V$1702,测试记录!$C$5:$C$1702,$B15))
B16: =IF(模型信息!B16="","",模型信息!B16) | C16: =IF($B16="","",IFERROR(VLOOKUP($B16,模型信息!$B$5:$C$24,2,0),"")) | D16: =IF($B16="","",IFERROR(AVERAGEIFS(测试记录!$L$5:$L$1702,测试记录!$C$5:$C$1702,$B16,测试记录!$F$5:$F$1702,D$4),"")) | E16: =IF($B16="","",IFERROR(AVERAGEIFS(测试记录!$L$5:$L$1702,测试记录!$C$5:$C$1702,$B16,测试记录!$F$5:$F$1702,E$4),"")) | F16: =IF($B16="","",IFERROR(AVERAGEIFS(测试记录!$L$5:$L$1702,测试记录!$C$5:$C$1702,$B16,测试记录!$F$5:$F$1702,F$4),"")) | G16: =IF($B16="","",IFERROR(AVERAGEIFS(测试记录!$L$5:$L$1702,测试记录!$C$5:$C$1702,$B16,测试记录!$F$5:$F$1702,G$4),"")) | H16: =IF($B16="","",IFERROR(AVERAGEIFS(测试记录!$L$5:$L$1702,测试记录!$C$5:$C$1702,$B16,测试记录!$F$5:$F$1702,H$4),"")) | I16: =IF($B16="","",IFERROR(AVERAGEIFS(测试记录!$L$5:$L$1702,测试记录!$C$5:$C$1702,$B16,测试记录!$F$5:$F$1702,I$4),"")) | J16: =IF($B16="","",IFERROR(AVERAGEIFS(测试记录!$L$5:$L$1702,测试记录!$C$5:$C$1702,$B16,测试记录!$F$5:$F$1702,J$4),"")) | K16: =IF($B16="","",IFERROR(AVERAGEIFS(测试记录!$L$5:$L$1702,测试记录!$C$5:$C$1702,$B16,测试记录!$F$5:$F$1702,K$4),"")) | ... P16: =IF($B16="","",IFERROR(AVERAGEIFS(测试记录!$L$5:$L$1702,测试记录!$C$5:$C$1702,$B16,测试记录!$F$5:$F$1702,P$4),"")) | Q16: =IF($B16="","",IFERROR(AVERAGEIFS(测试记录!$L$5:$L$1702,测试记录!$C$5:$C$1702,$B16),"")) | R16: =IF($B16="","",COUNTIFS(测试记录!$C$5:$C$1702,$B16)) | S16: =IF($Q16="","",IFERROR(RANK($Q16,$Q$5:$Q$23),"")) | T16: =IF($B16="","",SUMIFS(测试记录!$Q$5:$Q$1702,测试记录!$C$5:$C$1702,$B16)) | U16: =IF($B16="","",SUMIFS(测试记录!$R$5:$R$1702,测试记录!$C$5:$C$1702,$B16)) | V16: =IF($B16="","",SUMIFS(测试记录!$S$5:$S$1702,测试记录!$C$5:$C$1702,$B16)+SUMIFS(测试记录!$V$5:$V$1702,测试记录!$C$5:$C$1702,$B16))
B17: =IF(模型信息!B17="","",模型信息!B17) | C17: =IF($B17="","",IFERROR(VLOOKUP($B17,模型信息!$B$5:$C$24,2,0),"")) | D17: =IF($B17="","",IFERROR(AVERAGEIFS(测试记录!$L$5:$L$1702,测试记录!$C$5:$C$1702,$B17,测试记录!$F$5:$F$1702,D$4),"")) | E17: =IF($B17="","",IFERROR(AVERAGEIFS(测试记录!$L$5:$L$1702,测试记录!$C$5:$C$1702,$B17,测试记录!$F$5:$F$1702,E$4),"")) | F17: =IF($B17="","",IFERROR(AVERAGEIFS(测试记录!$L$5:$L$1702,测试记录!$C$5:$C$1702,$B17,测试记录!$F$5:$F$1702,F$4),"")) | G17: =IF($B17="","",IFERROR(AVERAGEIFS(测试记录!$L$5:$L$1702,测试记录!$C$5:$C$1702,$B17,测试记录!$F$5:$F$1702,G$4),"")) | H17: =IF($B17="","",IFERROR(AVERAGEIFS(测试记录!$L$5:$L$1702,测试记录!$C$5:$C$1702,$B17,测试记录!$F$5:$F$1702,H$4),"")) | I17: =IF($B17="","",IFERROR(AVERAGEIFS(测试记录!$L$5:$L$1702,测试记录!$C$5:$C$1702,$B17,测试记录!$F$5:$F$1702,I$4),"")) | J17: =IF($B17="","",IFERROR(AVERAGEIFS(测试记录!$L$5:$L$1702,测试记录!$C$5:$C$1702,$B17,测试记录!$F$5:$F$1702,J$4),"")) | K17: =IF($B17="","",IFERROR(AVERAGEIFS(测试记录!$L$5:$L$1702,测试记录!$C$5:$C$1702,$B17,测试记录!$F$5:$F$1702,K$4),"")) | ... P17: =IF($B17="","",IFERROR(AVERAGEIFS(测试记录!$L$5:$L$1702,测试记录!$C$5:$C$1702,$B17,测试记录!$F$5:$F$1702,P$4),"")) | Q17: =IF($B17="","",IFERROR(AVERAGEIFS(测试记录!$L$5:$L$1702,测试记录!$C$5:$C$1702,$B17),"")) | R17: =IF($B17="","",COUNTIFS(测试记录!$C$5:$C$1702,$B17)) | S17: =IF($Q17="","",IFERROR(RANK($Q17,$Q$5:$Q$23),"")) | T17: =IF($B17="","",SUMIFS(测试记录!$Q$5:$Q$1702,测试记录!$C$5:$C$1702,$B17)) | U17: =IF($B17="","",SUMIFS(测试记录!$R$5:$R$1702,测试记录!$C$5:$C$1702,$B17)) | V17: =IF($B17="","",SUMIFS(测试记录!$S$5:$S$1702,测试记录!$C$5:$C$1702,$B17)+SUMIFS(测试记录!$V$5:$V$1702,测试记录!$C$5:$C$1702,$B17))
B18: =IF(模型信息!B18="","",模型信息!B18) | C18: =IF($B18="","",IFERROR(VLOOKUP($B18,模型信息!$B$5:$C$24,2,0),"")) | D18: =IF($B18="","",IFERROR(AVERAGEIFS(测试记录!$L$5:$L$1702,测试记录!$C$5:$C$1702,$B18,测试记录!$F$5:$F$1702,D$4),"")) | E18: =IF($B18="","",IFERROR(AVERAGEIFS(测试记录!$L$5:$L$1702,测试记录!$C$5:$C$1702,$B18,测试记录!$F$5:$F$1702,E$4),"")) | F18: =IF($B18="","",IFERROR(AVERAGEIFS(测试记录!$L$5:$L$1702,测试记录!$C$5:$C$1702,$B18,测试记录!$F$5:$F$1702,F$4),"")) | G18: =IF($B18="","",IFERROR(AVERAGEIFS(测试记录!$L$5:$L$1702,测试记录!$C$5:$C$1702,$B18,测试记录!$F$5:$F$1702,G$4),"")) | H18: =IF($B18="","",IFERROR(AVERAGEIFS(测试记录!$L$5:$L$1702,测试记录!$C$5:$C$1702,$B18,测试记录!$F$5:$F$1702,H$4),"")) | I18: =IF($B18="","",IFERROR(AVERAGEIFS(测试记录!$L$5:$L$1702,测试记录!$C$5:$C$1702,$B18,测试记录!$F$5:$F$1702,I$4),"")) | J18: =IF($B18="","",IFERROR(AVERAGEIFS(测试记录!$L$5:$L$1702,测试记录!$C$5:$C$1702,$B18,测试记录!$F$5:$F$1702,J$4),"")) | K18: =IF($B18="","",IFERROR(AVERAGEIFS(测试记录!$L$5:$L$1702,测试记录!$C$5:$C$1702,$B18,测试记录!$F$5:$F$1702,K$4),"")) | ... P18: =IF($B18="","",IFERROR(AVERAGEIFS(测试记录!$L$5:$L$1702,测试记录!$C$5:$C$1702,$B18,测试记录!$F$5:$F$1702,P$4),"")) | Q18: =IF($B18="","",IFERROR(AVERAGEIFS(测试记录!$L$5:$L$1702,测试记录!$C$5:$C$1702,$B18),"")) | R18: =IF($B18="","",COUNTIFS(测试记录!$C$5:$C$1702,$B18)) | S18: =IF($Q18="","",IFERROR(RANK($Q18,$Q$5:$Q$23),"")) | T18: =IF($B18="","",SUMIFS(测试记录!$Q$5:$Q$1702,测试记录!$C$5:$C$1702,$B18)) | U18: =IF($B18="","",SUMIFS(测试记录!$R$5:$R$1702,测试记录!$C$5:$C$1702,$B18)) | V18: =IF($B18="","",SUMIFS(测试记录!$S$5:$S$1702,测试记录!$C$5:$C$1702,$B18)+SUMIFS(测试记录!$V$5:$V$1702,测试记录!$C$5:$C$1702,$B18))
B19: =IF(模型信息!B19="","",模型信息!B19) | C19: =IF($B19="","",IFERROR(VLOOKUP($B19,模型信息!$B$5:$C$24,2,0),"")) | D19: =IF($B19="","",IFERROR(AVERAGEIFS(测试记录!$L$5:$L$1702,测试记录!$C$5:$C$1702,$B19,测试记录!$F$5:$F$1702,D$4),"")) | E19: =IF($B19="","",IFERROR(AVERAGEIFS(测试记录!$L$5:$L$1702,测试记录!$C$5:$C$1702,$B19,测试记录!$F$5:$F$1702,E$4),"")) | F19: =IF($B19="","",IFERROR(AVERAGEIFS(测试记录!$L$5:$L$1702,测试记录!$C$5:$C$1702,$B19,测试记录!$F$5:$F$1702,F$4),"")) | G19: =IF($B19="","",IFERROR(AVERAGEIFS(测试记录!$L$5:$L$1702,测试记录!$C$5:$C$1702,$B19,测试记录!$F$5:$F$1702,G$4),"")) | H19: =IF($B19="","",IFERROR(AVERAGEIFS(测试记录!$L$5:$L$1702,测试记录!$C$5:$C$1702,$B19,测试记录!$F$5:$F$1702,H$4),"")) | I19: =IF($B19="","",IFERROR(AVERAGEIFS(测试记录!$L$5:$L$1702,测试记录!$C$5:$C$1702,$B19,测试记录!$F$5:$F$1702,I$4),"")) | J19: =IF($B19="","",IFERROR(AVERAGEIFS(测试记录!$L$5:$L$1702,测试记录!$C$5:$C$1702,$B19,测试记录!$F$5:$F$1702,J$4),"")) | K19: =IF($B19="","",IFERROR(AVERAGEIFS(测试记录!$L$5:$L$1702,测试记录!$C$5:$C$1702,$B19,测试记录!$F$5:$F$1702,K$4),"")) | ... P19: =IF($B19="","",IFERROR(AVERAGEIFS(测试记录!$L$5:$L$1702,测试记录!$C$5:$C$1702,$B19,测试记录!$F$5:$F$1702,P$4),"")) | Q19: =IF($B19="","",IFERROR(AVERAGEIFS(测试记录!$L$5:$L$1702,测试记录!$C$5:$C$1702,$B19),"")) | R19: =IF($B19="","",COUNTIFS(测试记录!$C$5:$C$1702,$B19)) | S19: =IF($Q19="","",IFERROR(RANK($Q19,$Q$5:$Q$23),"")) | T19: =IF($B19="","",SUMIFS(测试记录!$Q$5:$Q$1702,测试记录!$C$5:$C$1702,$B19)) | U19: =IF($B19="","",SUMIFS(测试记录!$R$5:$R$1702,测试记录!$C$5:$C$1702,$B19)) | V19: =IF($B19="","",SUMIFS(测试记录!$S$5:$S$1702,测试记录!$C$5:$C$1702,$B19)+SUMIFS(测试记录!$V$5:$V$1702,测试记录!$C$5:$C$1702,$B19))
B20: =IF(模型信息!B20="","",模型信息!B20) | C20: =IF($B20="","",IFERROR(VLOOKUP($B20,模型信息!$B$5:$C$24,2,0),"")) | D20: =IF($B20="","",IFERROR(AVERAGEIFS(测试记录!$L$5:$L$1702,测试记录!$C$5:$C$1702,$B20,测试记录!$F$5:$F$1702,D$4),"")) | E20: =IF($B20="","",IFERROR(AVERAGEIFS(测试记录!$L$5:$L$1702,测试记录!$C$5:$C$1702,$B20,测试记录!$F$5:$F$1702,E$4),"")) | F20: =IF($B20="","",IFERROR(AVERAGEIFS(测试记录!$L$5:$L$1702,测试记录!$C$5:$C$1702,$B20,测试记录!$F$5:$F$1702,F$4),"")) | G20: =IF($B20="","",IFERROR(AVERAGEIFS(测试记录!$L$5:$L$1702,测试记录!$C$5:$C$1702,$B20,测试记录!$F$5:$F$1702,G$4),"")) | H20: =IF($B20="","",IFERROR(AVERAGEIFS(测试记录!$L$5:$L$1702,测试记录!$C$5:$C$1702,$B20,测试记录!$F$5:$F$1702,H$4),"")) | I20: =IF($B20="","",IFERROR(AVERAGEIFS(测试记录!$L$5:$L$1702,测试记录!$C$5:$C$1702,$B20,测试记录!$F$5:$F$1702,I$4),"")) | J20: =IF($B20="","",IFERROR(AVERAGEIFS(测试记录!$L$5:$L$1702,测试记录!$C$5:$C$1702,$B20,测试记录!$F$5:$F$1702,J$4),"")) | K20: =IF($B20="","",IFERROR(AVERAGEIFS(测试记录!$L$5:$L$1702,测试记录!$C$5:$C$1702,$B20,测试记录!$F$5:$F$1702,K$4),"")) | ... P20: =IF($B20="","",IFERROR(AVERAGEIFS(测试记录!$L$5:$L$1702,测试记录!$C$5:$C$1702,$B20,测试记录!$F$5:$F$1702,P$4),"")) | Q20: =IF($B20="","",IFERROR(AVERAGEIFS(测试记录!$L$5:$L$1702,测试记录!$C$5:$C$1702,$B20),"")) | R20: =IF($B20="","",COUNTIFS(测试记录!$C$5:$C$1702,$B20)) | S20: =IF($Q20="","",IFERROR(RANK($Q20,$Q$5:$Q$23),"")) | T20: =IF($B20="","",SUMIFS(测试记录!$Q$5:$Q$1702,测试记录!$C$5:$C$1702,$B20)) | U20: =IF($B20="","",SUMIFS(测试记录!$R$5:$R$1702,测试记录!$C$5:$C$1702,$B20)) | V20: =IF($B20="","",SUMIFS(测试记录!$S$5:$S$1702,测试记录!$C$5:$C$1702,$B20)+SUMIFS(测试记录!$V$5:$V$1702,测试记录!$C$5:$C$1702,$B20))
B21: =IF(模型信息!B21="","",模型信息!B21) | C21: =IF($B21="","",IFERROR(VLOOKUP($B21,模型信息!$B$5:$C$24,2,0),"")) | D21: =IF($B21="","",IFERROR(AVERAGEIFS(测试记录!$L$5:$L$1702,测试记录!$C$5:$C$1702,$B21,测试记录!$F$5:$F$1702,D$4),"")) | E21: =IF($B21="","",IFERROR(AVERAGEIFS(测试记录!$L$5:$L$1702,测试记录!$C$5:$C$1702,$B21,测试记录!$F$5:$F$1702,E$4),"")) | F21: =IF($B21="","",IFERROR(AVERAGEIFS(测试记录!$L$5:$L$1702,测试记录!$C$5:$C$1702,$B21,测试记录!$F$5:$F$1702,F$4),"")) | G21: =IF($B21="","",IFERROR(AVERAGEIFS(测试记录!$L$5:$L$1702,测试记录!$C$5:$C$1702,$B21,测试记录!$F$5:$F$1702,G$4),"")) | H21: =IF($B21="","",IFERROR(AVERAGEIFS(测试记录!$L$5:$L$1702,测试记录!$C$5:$C$1702,$B21,测试记录!$F$5:$F$1702,H$4),"")) | I21: =IF($B21="","",IFERROR(AVERAGEIFS(测试记录!$L$5:$L$1702,测试记录!$C$5:$C$1702,$B21,测试记录!$F$5:$F$1702,I$4),"")) | J21: =IF($B21="","",IFERROR(AVERAGEIFS(测试记录!$L$5:$L$1702,测试记录!$C$5:$C$1702,$B21,测试记录!$F$5:$F$1702,J$4),"")) | K21: =IF($B21="","",IFERROR(AVERAGEIFS(测试记录!$L$5:$L$1702,测试记录!$C$5:$C$1702,$B21,测试记录!$F$5:$F$1702,K$4),"")) | ... P21: =IF($B21="","",IFERROR(AVERAGEIFS(测试记录!$L$5:$L$1702,测试记录!$C$5:$C$1702,$B21,测试记录!$F$5:$F$1702,P$4),"")) | Q21: =IF($B21="","",IFERROR(AVERAGEIFS(测试记录!$L$5:$L$1702,测试记录!$C$5:$C$1702,$B21),"")) | R21: =IF($B21="","",COUNTIFS(测试记录!$C$5:$C$1702,$B21)) | S21: =IF($Q21="","",IFERROR(RANK($Q21,$Q$5:$Q$23),"")) | T21: =IF($B21="","",SUMIFS(测试记录!$Q$5:$Q$1702,测试记录!$C$5:$C$1702,$B21)) | U21: =IF($B21="","",SUMIFS(测试记录!$R$5:$R$1702,测试记录!$C$5:$C$1702,$B21)) | V21: =IF($B21="","",SUMIFS(测试记录!$S$5:$S$1702,测试记录!$C$5:$C$1702,$B21)+SUMIFS(测试记录!$V$5:$V$1702,测试记录!$C$5:$C$1702,$B21))
B22: =IF(模型信息!B22="","",模型信息!B22) | C22: =IF($B22="","",IFERROR(VLOOKUP($B22,模型信息!$B$5:$C$24,2,0),"")) | D22: =IF($B22="","",IFERROR(AVERAGEIFS(测试记录!$L$5:$L$1702,测试记录!$C$5:$C$1702,$B22,测试记录!$F$5:$F$1702,D$4),"")) | E22: =IF($B22="","",IFERROR(AVERAGEIFS(测试记录!$L$5:$L$1702,测试记录!$C$5:$C$1702,$B22,测试记录!$F$5:$F$1702,E$4),"")) | F22: =IF($B22="","",IFERROR(AVERAGEIFS(测试记录!$L$5:$L$1702,测试记录!$C$5:$C$1702,$B22,测试记录!$F$5:$F$1702,F$4),"")) | G22: =IF($B22="","",IFERROR(AVERAGEIFS(测试记录!$L$5:$L$1702,测试记录!$C$5:$C$1702,$B22,测试记录!$F$5:$F$1702,G$4),"")) | H22: =IF($B22="","",IFERROR(AVERAGEIFS(测试记录!$L$5:$L$1702,测试记录!$C$5:$C$1702,$B22,测试记录!$F$5:$F$1702,H$4),"")) | I22: =IF($B22="","",IFERROR(AVERAGEIFS(测试记录!$L$5:$L$1702,测试记录!$C$5:$C$1702,$B22,测试记录!$F$5:$F$1702,I$4),"")) | J22: =IF($B22="","",IFERROR(AVERAGEIFS(测试记录!$L$5:$L$1702,测试记录!$C$5:$C$1702,$B22,测试记录!$F$5:$F$1702,J$4),"")) | K22: =IF($B22="","",IFERROR(AVERAGEIFS(测试记录!$L$5:$L$1702,测试记录!$C$5:$C$1702,$B22,测试记录!$F$5:$F$1702,K$4),"")) | ... P22: =IF($B22="","",IFERROR(AVERAGEIFS(测试记录!$L$5:$L$1702,测试记录!$C$5:$C$1702,$B22,测试记录!$F$5:$F$1702,P$4),"")) | Q22: =IF($B22="","",IFERROR(AVERAGEIFS(测试记录!$L$5:$L$1702,测试记录!$C$5:$C$1702,$B22),"")) | R22: =IF($B22="","",COUNTIFS(测试记录!$C$5:$C$1702,$B22)) | S22: =IF($Q22="","",IFERROR(RANK($Q22,$Q$5:$Q$23),"")) | T22: =IF($B22="","",SUMIFS(测试记录!$Q$5:$Q$1702,测试记录!$C$5:$C$1702,$B22)) | U22: =IF($B22="","",SUMIFS(测试记录!$R$5:$R$1702,测试记录!$C$5:$C$1702,$B22)) | V22: =IF($B22="","",SUMIFS(测试记录!$S$5:$S$1702,测试记录!$C$5:$C$1702,$B22)+SUMIFS(测试记录!$V$5:$V$1702,测试记录!$C$5:$C$1702,$B22))
B23: =IF(模型信息!B23="","",模型信息!B23) | C23: =IF($B23="","",IFERROR(VLOOKUP($B23,模型信息!$B$5:$C$24,2,0),"")) | D23: =IF($B23="","",IFERROR(AVERAGEIFS(测试记录!$L$5:$L$1702,测试记录!$C$5:$C$1702,$B23,测试记录!$F$5:$F$1702,D$4),"")) | E23: =IF($B23="","",IFERROR(AVERAGEIFS(测试记录!$L$5:$L$1702,测试记录!$C$5:$C$1702,$B23,测试记录!$F$5:$F$1702,E$4),"")) | F23: =IF($B23="","",IFERROR(AVERAGEIFS(测试记录!$L$5:$L$1702,测试记录!$C$5:$C$1702,$B23,测试记录!$F$5:$F$1702,F$4),"")) | G23: =IF($B23="","",IFERROR(AVERAGEIFS(测试记录!$L$5:$L$1702,测试记录!$C$5:$C$1702,$B23,测试记录!$F$5:$F$1702,G$4),"")) | H23: =IF($B23="","",IFERROR(AVERAGEIFS(测试记录!$L$5:$L$1702,测试记录!$C$5:$C$1702,$B23,测试记录!$F$5:$F$1702,H$4),"")) | I23: =IF($B23="","",IFERROR(AVERAGEIFS(测试记录!$L$5:$L$1702,测试记录!$C$5:$C$1702,$B23,测试记录!$F$5:$F$1702,I$4),"")) | J23: =IF($B23="","",IFERROR(AVERAGEIFS(测试记录!$L$5:$L$1702,测试记录!$C$5:$C$1702,$B23,测试记录!$F$5:$F$1702,J$4),"")) | K23: =IF($B23="","",IFERROR(AVERAGEIFS(测试记录!$L$5:$L$1702,测试记录!$C$5:$C$1702,$B23,测试记录!$F$5:$F$1702,K$4),"")) | ... P23: =IF($B23="","",IFERROR(AVERAGEIFS(测试记录!$L$5:$L$1702,测试记录!$C$5:$C$1702,$B23,测试记录!$F$5:$F$1702,P$4),"")) | Q23: =IF($B23="","",IFERROR(AVERAGEIFS(测试记录!$L$5:$L$1702,测试记录!$C$5:$C$1702,$B23),"")) | R23: =IF($B23="","",COUNTIFS(测试记录!$C$5:$C$1702,$B23)) | S23: =IF($Q23="","",IFERROR(RANK($Q23,$Q$5:$Q$23),"")) | T23: =IF($B23="","",SUMIFS(测试记录!$Q$5:$Q$1702,测试记录!$C$5:$C$1702,$B23)) | U23: =IF($B23="","",SUMIFS(测试记录!$R$5:$R$1702,测试记录!$C$5:$C$1702,$B23)) | V23: =IF($B23="","",SUMIFS(测试记录!$S$5:$S$1702,测试记录!$C$5:$C$1702,$B23)+SUMIFS(测试记录!$V$5:$V$1702,测试记录!$C$5:$C$1702,$B23))
B25: 注：本表全部由公式自动计算（按模型ID+能力维度匹配测试记录）；雷达图默认展示前4个模型；费用列为按 models.yaml 单价的估算值（施测+评审），不含缓存折扣等计费细节；文档解析维度仅统计视觉模型。

Sheet 模型分类
B2: 模型分类报告（口径·公式·理由随表）
B4: 数据源: results/scored.jsonl · 生成时间 2026-10-24 10:12 · 应作答题数 240 · 本表为分析快照, 数值与「能力评分汇总」同源
B6: 一、计算口径 · 公式 · 理由
B7: 1 客观综合分 | C7: 公式 = 11个客观维度得分率的算术平均×100（不含创造力/文档解析）。 | I7: 理由: 客观题为程序判分、可复核; 创造力是LLM评审主观分(评审模型同时参赛有自偏好风险, 且含14条评审失败记0), 故只列参考不进主公式。
B8: 2 资格门 | C8: 完成率 = 有效作答/应作答; 错误率 = 错误记录/应作答; 完成率≥90% 且 错误率≤10% → ✓, 否则 ⚠(保留名次不除名)。 | I8: 理由: 答得少的模型的平均分不能与答全者直接比较, 缺考信息必须显性化而非惩罚性折算。
B9: 3 梯队(固定带) | C9: T1 ≥75 / T2 65~75 / T3 <65（按客观综合分）。本场实际: T1四人、T2三人、T3空档。 | I9: 理由: 门槛先于数据立定, 不随本场分数挪动, 换模型/重跑可比; 三类对应决策语言——首选/够用/慎用。
B10: 4 能力画像(z分数) | C10: z = (该模型该维度得分率 − 群体均值)/群体标准差; ◆相对优势 z≥+0.5; ▼相对短板 z≤−0.5; ✖绝对短板 得分率<50%(可与相对标签并存)。 | I10: 理由: 梯队回答"谁强", 画像回答"选谁干什么活"; 相对+绝对双轨, 避免"全场最差维度的第一名"被误标为优势。
B11: 5 性价比与象限 | C11: 性价比 = 客观综合分 / 施测费用(元, 不含评审费用); 象限以中位数切(本场 能力中位75.0 / 费用中位0.9655元)。 | I11: 理由: 能力与价格正交, 混入单一公式会得到"便宜平庸=贵而强"的失真; 分母用费用, 因为你付的是钱。
B12: 6 题目区分度 | C12: 维度间标准差<5pp → 区分度不足; 均值≥90% 天花板 / <50% 地板。 | I12: 理由: 这层评题不评模型, 为下轮换题提供依据(本场: 结构化输出需换难题, 长文本保留)。
B14: 二、模型分类总表（按客观综合分降序）
B15: 模型ID | C15: 模型名称 | D15: 客观综合分 | E15: 完成率 | F15: 错误率 | G15: 资格门 | H15: 梯队 | I15: 创造力(参考) | J15: 施测费用(元) | K15: 性价比(分/元) | L15: 象限 | M15: 能力画像摘要
B16: M08 | C16: MiMo-V2.5 | D16: 77.7 | E16: 0.99583333 | F16: 0.0041666667 | G16: ✓ | H16: T1 | I16: 61.5 | J16: 1.592 | K16: 48.8 | L16: 高能高价 | M16: 语言理解◆相对优势；信息提取◆相对优势；约束处理◆相对优势；结构化输出◆相对优势；长文本组织✖绝对短板；上下文利用◆相对优势；信息检索✖绝对短板(兼▼)；评估◆相对优势；错误识别◆相对优势
B17: M04 | C17: Hy3 | D17: 76.9 | E17: 0.99166667 | F17: 0.0083333333 | G17: ✓ | H17: T1 | I17: 69.5 | J17: 0.8313 | K17: 92.5 | L17: 高能低价 | M17: 语言理解◆相对优势；信息提取◆相对优势；指令遵循◆相对优势；复杂推理▼相对短板；约束处理◆相对优势；结构化输出◆相对优势；长文本组织✖绝对短板；上下文利用◆相对优势；信息检索✖绝对短板(兼▼)；评估◆相对优势；错误识别◆相对优势
B18: M07 | C18: Kimi-K3 | D18: 76.9 | E18: 0.92916667 | F18: 0.066666667 | G18: ✓ | H18: T1 | I18: 53 | J18: 8.9951 | K18: 8.5 | L18: 高能高价 | M18: 语言理解◆相对优势；信息提取◆相对优势；指令遵循◆相对优势；约束处理◆相对优势；结构化输出◆相对优势；长文本组织✖绝对短板(兼▼)；上下文利用◆相对优势；评估▼相对短板；错误识别▼相对短板
B19: M01 | C19: DeepSeek-V4-Flash | D19: 75 | E19: 0.9875 | F19: 0.0125 | G19: ✓ | H19: T1 | I19: 80 | J19: 0.8131 | K19: 92.2 | L19: 高能低价 | M19: 语言理解◆相对优势；信息提取◆相对优势；指令遵循▼相对短板；结构化输出◆相对优势；长文本组织✖绝对短板；评估◆相对优势；错误识别◆相对优势
B20: M02 | C20: GLM-5.3 | D20: 73.7 | E20: 0.98333333 | F20: 0.016666667 | G20: ✓ | H20: T2 | I20: 83 | J20: 4.6187 | K20: 16 | L20: 低能高价 | M20: 语言理解◆相对优势；复杂推理◆相对优势；结构化输出▼相对短板；长文本组织✖绝对短板(兼▼)；信息检索◆相对优势；评估▼相对短板；错误识别▼相对短板
B21: M03 | C21: GLM-5.3-Flash | D21: 69.8 | E21: 0.95 | F21: 0.045833333 | G21: ✓ | H21: T2 | I21: 82 | J21: 0.9004 | K21: 77.5 | L21: 低能低价 | M21: 信息提取▼相对短板；指令遵循▼相对短板；复杂推理▼相对短板；约束处理▼相对短板；结构化输出▼相对短板；长文本组织✖绝对短板(兼▼)；评估▼相对短板
B22: M06 | C22: MiniMax-M3 | D22: 65.4 | E22: 1 | F22: 0 | G22: ✓ | H22: T2 | I22: 58 | J22: 0.9655 | K22: 67.7 | L22: 低能低价 | M22: 语言理解▼相对短板；信息提取▼相对短板；指令遵循▼相对短板；复杂推理◆相对优势；约束处理▼相对短板；结构化输出▼相对短板；长文本组织✖绝对短板(兼▼)；上下文利用▼相对短板；评估▼相对短板；错误识别▼相对短板
B23: 注: 创造力列为LLM评审参考分(不参与梯队); 费用为按所配单价的估算值; 画像摘要完整标注见下表。
B25: 三、能力画像明细（数值% + z分数 + 标签; 创造力列仅供参考不打标签）
B26: 模型 | C26: 名称 | D26: 语言理解 | E26: 信息提取 | F26: 指令遵循 | G26: 复杂推理 | H26: 约束处理 | I26: 结构化输出 | J26: 长文本组织 | K26: 上下文利用 | L26: 信息检索 | M26: 评估 | N26: 错误识别 | O26: 创造力(参考)
B27: M02 | C27: GLM-5.3 | D27: 95.0% (z+0.5) ◆相对优势 | E27: 73.9% (z-0.4) | F27: 80.0% (z+0.0) | G27: 95.0% (z+1.3) ◆相对优势 | H27: 73.5% (z+0.3) | I27: 95.0% (z-1.1) ▼相对短板 | J27: 25.3% (z-0.9) ✖绝对短板(兼▼) | K27: 70.7% (z-0.3) | L27: 62.5% (z+2.3) ◆相对优势 | M27: 60.0% (z-0.8) ▼相对短板 | N27: 80.0% (z-0.5) ▼相对短板 | O27: 83.0% (z+1.2)
B28: M04 | C28: Hy3 | D28: 95.0% (z+0.5) ◆相对优势 | E28: 83.5% (z+0.8) ◆相对优势 | F28: 85.0% (z+0.5) ◆相对优势 | G28: 80.0% (z-1.1) ▼相对短板 | H28: 76.3% (z+0.6) ◆相对优势 | I28: 100.0% (z+0.9) ◆相对优势 | J28: 42.5% (z+1.1) ✖绝对短板 | K28: 75.8% (z+0.8) ◆相对优势 | L28: 47.5% (z-0.8) ✖绝对短板(兼▼) | M28: 70.0% (z+0.8) ◆相对优势 | N28: 90.0% (z+0.9) ◆相对优势 | O28: 69.5% (z-0.0)
B29: M06 | C29: MiniMax-M3 | D29: 80.0% (z-2.3) ▼相对短板 | E29: 60.6% (z-2.0) ▼相对短板 | F29: 70.0% (z-1.0) ▼相对短板 | G29: 95.0% (z+1.3) ◆相对优势 | H29: 52.5% (z-1.8) ▼相对短板 | I29: 95.0% (z-1.1) ▼相对短板 | J29: 25.6% (z-0.9) ✖绝对短板(兼▼) | K29: 60.3% (z-2.3) ▼相对短板 | L29: 50.0% (z-0.3) | M29: 60.0% (z-0.8) ▼相对短板 | N29: 70.0% (z-2.0) ▼相对短板 | O29: 58.0% (z-1.0)
B30: M01 | C30: DeepSeek-V4-Flash | D30: 95.0% (z+0.5) ◆相对优势 | E30: 83.5% (z+0.8) ◆相对优势 | F30: 73.7% (z-0.6) ▼相对短板 | G30: 85.0% (z-0.3) | H30: 65.8% (z-0.5) | I30: 100.0% (z+0.9) ◆相对优势 | J30: 39.3% (z+0.7) ✖绝对短板 | K30: 73.0% (z+0.2) | L30: 50.0% (z-0.3) | M30: 70.0% (z+0.8) ◆相对优势 | N30: 90.0% (z+0.9) ◆相对优势 | O30: 80.0% (z+0.9)
B31: M08 | C31: MiMo-V2.5 | D31: 95.0% (z+0.5) ◆相对优势 | E31: 82.5% (z+0.6) ◆相对优势 | F31: 80.0% (z+0.0) | G31: 85.0% (z-0.3) | H31: 77.5% (z+0.7) ◆相对优势 | I31: 100.0% (z+0.9) ◆相对优势 | J31: 46.9% (z+1.6) ✖绝对短板 | K31: 75.6% (z+0.7) ◆相对优势 | L31: 47.5% (z-0.8) ✖绝对短板(兼▼) | M31: 75.0% (z+1.7) ◆相对优势 | N31: 90.0% (z+0.9) ◆相对优势 | O31: 61.5% (z-0.7)
B32: M03 | C32: GLM-5.3-Flash | D32: 90.0% (z-0.4) | E32: 71.8% (z-0.7) ▼相对短板 | F32: 68.8% (z-1.1) ▼相对短板 | G32: 78.6% (z-1.4) ▼相对短板 | H32: 63.9% (z-0.7) ▼相对短板 | I32: 95.0% (z-1.1) ▼相对短板 | J32: 28.5% (z-0.6) ✖绝对短板(兼▼) | K32: 74.0% (z+0.4) | L32: 52.5% (z+0.2) | M32: 60.0% (z-0.8) ▼相对短板 | N32: 85.0% (z+0.2) | O32: 82.0% (z+1.1)
B33: M07 | C33: Kimi-K3 | D33: 95.0% (z+0.5) ◆相对优势 | E33: 84.7% (z+0.9) ◆相对优势 | F33: 100.0% (z+2.0) ◆相对优势 | G33: 90.0% (z+0.5) | H33: 85.7% (z+1.5) ◆相对优势 | I33: 100.0% (z+0.9) ◆相对优势 | J33: 25.1% (z-1.0) ✖绝对短板(兼▼) | K33: 75.0% (z+0.6) ◆相对优势 | L33: 50.0% (z-0.3) | M33: 60.0% (z-0.8) ▼相对短板 | N33: 80.0% (z-0.5) ▼相对短板 | O33: 53.0% (z-1.4)
B35: 四、题目区分度（评题不评模型, 为下轮换题服务）
B36: 维度 | C36: 群体均值% | D36: 标准差pp | E36: 难度判定 | F36: 区分度判定 | G36: 下轮建议
B37: 语言理解 | C37: 92.1 | D37: 5.2 | E37: 偏易(均值≥90%) | F37: 区分度良好 | G37: 保留
B38: 信息提取 | C38: 77.2 | D38: 8.3 | E38: 难度适中 | F38: 区分度良好 | G38: 保留
B39: 指令遵循 | C39: 79.6 | D39: 9.9 | E39: 难度适中 | F39: 区分度良好 | G39: 保留
B40: 复杂推理 | C40: 86.9 | D40: 6.2 | E40: 难度适中 | F40: 区分度良好 | G40: 保留
B41: 约束处理 | C41: 70.7 | D41: 10.1 | E41: 难度适中 | F41: 区分度良好 | G41: 保留
B42: 结构化输出 | C42: 97.9 | D42: 2.5 | E42: 偏易(均值≥90%) | F42: 区分度不足 | G42: 天花板效应：全员接近满分，建议下轮更换更难题目
B43: 长文本组织 | C43: 33.3 | D43: 8.6 | E43: 偏难(均值<50%) | F43: 区分度良好 | G43: 地板效应但区分度高：保留（拉开差距的关键维度）
B44: 上下文利用 | C44: 72 | D44: 5.1 | E44: 难度适中 | F44: 区分度良好 | G44: 保留
B45: 信息检索 | C45: 51.4 | D45: 4.8 | E45: 难度适中 | F45: 区分度不足 | G45: 模型间差异过小，参考价值有限
B46: 评估 | C46: 65 | D46: 6 | E46: 难度适中 | F46: 区分度良好 | G46: 保留
B47: 错误识别 | C47: 83.6 | D47: 6.9 | E47: 难度适中 | F47: 区分度良好 | G47: 保留
B48: 创造力(参考) | C48: 69.6 | D48: 11.4 | E48: 难度适中 | F48: 区分度良好 | G48: 保留

Sheet 评分标准
B2: 评分标准与 LLM 评审提示词
B4: 一、通用评分量表（每题默认满分10分）
B5: 分数段 | C5: 等级 | D5: 描述
B6: 9~10 | C6: 优秀 | D6: 完全满足要求：答案正确、完整，产出质量高，无事实性或逻辑错误
B7: 7~8 | C7: 良好 | D7: 主体正确：结论或产出基本正确，仅有轻微瑕疵（表述、格式、小遗漏），不影响使用
B8: 5~6 | C8: 中等 | D8: 部分正确：关键内容约半数正确，或产出明显偏离要求但仍有可用成分
B9: 3~4 | C9: 较差 | D9: 基本错误：仅有少量正确成分，或严重偏离题目要求
B10: 0~2 | C10: 失败 | D10: 完全错误、答非所问、拒答，或严重违反题目约束
B11: 客观选择题可简化为：答对10分、答错0分；规则判分由 scorer.py 自动完成，本表供 LLM 评审与人工仲裁使用。
B13: 二、各能力维度评分要点
B14: 能力维度 | C14: 考察点 | D14: 推荐题型与题源 | E14: 评分要点/通过标准
B15: 语言理解 | C15: 词义辨析、病句、文言文、阅读理解深层含义 | D15: 高考语文题型改编；考研英语阅读 | E15: 客观题按对错计分；简答按要点覆盖度给分
B16: 信息提取 | C16: 实体/数值/时间/因果关系的抽取与表格化 | D16: 合同、新闻、简历等真实文本改编 | E16: 字段全部正确得满分，漏、错一处扣1~2分
B17: 创造力 | C17: 新颖性、流畅性、灵活性、文字表现力 | D17: 高考作文题型改编、命题写作 | E17: 按新颖性/切题度/结构/语言分项加权
B18: 指令遵循 | C18: 多指令复合：格式+字数+语气+顺序 | D18: IFEval类约束指令、多步任务 | E18: 逐条核对指令，满足一条记一分，按比例折算
B19: 复杂推理 | C19: 多步数学、逻辑演绎、因果链条 | D19: 高考数学题型、GSM8K式应用题、考研逻辑 | E19: 过程与结论分开评：结论对但过程错最多6分
B20: 约束处理 | C20: 硬约束不违反：禁用词、必含要素、长度上限 | D20: 多重约束写作题 | E20: 违反任一硬约束直接0~2分；软约束酌情扣分
B21: 结构化输出 | C21: JSON/YAML/表格的合法性、完整性、可解析性 | D21: 文本转JSON/Markdown表格任务 | E21: 程序校验：解析失败0分；字段缺失按比例扣分
B22: 长文本组织 | C22: 长文摘要完整性、报告结构性、多篇融合 | D22: 长报告摘要、LongBench式任务 | E22: 按覆盖率+忠实度+结构性三个维度评
B23: 上下文利用 | C23: 指代消解、多轮依赖、上文信息沿用 | D23: 多轮对话题、大海捞针变体 | E23: 必须依托上文信息才能答对才算通过
B24: 信息检索 | C24: 给定材料内定位证据、多跳查找、标注出处 | D24: 提供文档集的问答（RAG式） | E24: 答案须出自给定材料并给出处；编造0分
B25: 评估 | C25: 对文本/作文/方案判优劣并给出理由 | D25: 作文互评、方案对比排序 | E25: 判断结论与理由质量各占一半权重
B26: 错误识别 | C26: 病句、事实错误、逻辑漏洞、代码bug定位 | D26: 高考病句改错题型、植入错误的代码或短文 | E26: 找全且改对得满分；漏找、误报按比例扣分
B28: 三、LLM评审提示词模板（scorer.py 已内置, 此处供人工仲裁复用）
B29: 1 | C29: 你是严格且公正的阅卷评分官。请根据下面三部分信息，对【模型回答】打分：
B30: 2 | C30: 【题目】<粘贴题干与全部要求>
B31: 3 | C31: 【参考答案/评分要点】<粘贴题目信息表中的参考答案与评分要点>
B32: 4 | C32: 【模型回答】<粘贴测试记录表中的模型原始回答>
B33: 5 | C33: 评分规则：满分10分。先逐条核对要求与评分要点，指出对错；再检查硬约束；最后给总分。
B34: 6 | C34: 只按以下格式输出：
B35: 7 | C35: 分析：<逐条核对过程与扣分理由>
B36: 8 | C36: 得分：<0-10的整数>
B37: 9 | C37: 提示：不因冗长加分；约束类题目违反任一硬约束，总分不超过2分。
